Workbook
Name att_actdate: Attribution!$F$14:$F$21
Name att_actlr: Attribution!$C$10
Name att_actpct: Attribution!$E$14:$E$21
Name att_asof: Attribution!$C$7
Name att_m0: Attribution!$C$6
Name att_m1: Attribution!$C$8
Name att_m2: Attribution!$C$9
Name att_reconciles: Attribution!$B$32
Name br_selrow: Bridge!$F$36
Name calc_amod_p: _calc!$K$4:$K$72
Name calc_amod_p1: _calc!$L$4:$L$72
Name calc_aother: _calc!$R$4:$R$72
Name calc_arate_p: _calc!$I$4:$I$72
Name calc_arate_p1: _calc!$J$4:$J$72
Name calc_bu: _calc!$U$4:$U$72
Name calc_carry: _calc!$Q$4:$Q$72
Name calc_crl: _calc!$C$4:$C$72
Name calc_cylr_p: _calc!$N$4:$N$72
Name calc_cylr_p1: _calc!$O$4:$O$72
Name calc_cylr_prog: _calc!$CO$4:$CO$72
Name calc_cylr1_prog: _calc!$CP$4:$CP$72
Name calc_echg: _calc!$P$4:$P$72
Name calc_ecy_p: _calc!$E$4:$E$72
Name calc_ecy_p1: _calc!$F$4:$F$72
Name calc_ecy_pm1: _calc!$D$4:$D$72
Name calc_ep: _calc!$V$4:$V$72
Name calc_key: _calc!$A$4:$A$72
Name calc_lrcur: _calc!$M$4:$M$72
Name calc_mbar_p: _calc!$G$4:$G$72
Name calc_mbar_p1: _calc!$H$4:$H$72
Name calc_netmode: _calc!$AK$4:$AK$72
Name calc_netx: _calc!$AL$4:$AL$72
Name calc_nplanned: _calc!$CV$4:$CV$72
Name calc_ntaken: _calc!$CU$4:$CU$72
Name calc_proggap: _calc!$CT$4:$CT$72
Name calc_progident: _calc!$CS$4:$CS$72
Name calc_state: _calc!$T$4:$T$72
Name calc_term: _calc!$B$4:$B$72
Name calc_trend: _calc!$S$4:$S$72
Name calc_w_amod: _calc!$AD$4:$AD$72
Name calc_w_amod1: _calc!$AI$4:$AI$72
Name calc_w_aother: _calc!$CN$4:$CN$72
Name calc_w_arate: _calc!$AB$4:$AB$72
Name calc_w_arate1: _calc!$AH$4:$AH$72
Name calc_w_crl: _calc!$Z$4:$Z$72
Name calc_w_cylr: _calc!$AF$4:$AF$72
Name calc_w_cylr_prog: _calc!$CQ$4:$CQ$72
Name calc_w_cylr1: _calc!$AJ$4:$AJ$72
Name calc_w_cylr1_prog: _calc!$CR$4:$CR$72
Name calc_w_ecy: _calc!$AA$4:$AA$72
Name calc_w_lrcur: _calc!$AE$4:$AE$72
Name calc_w_m0: _calc!$X$4:$X$72
Name calc_w_m1: _calc!$Y$4:$Y$72
Name calc_w_mbar: _calc!$AC$4:$AC$72
Name calc_w_mind: _calc!$W$4:$W$72
Name calc_w_trend: _calc!$AG$4:$AG$72
Name ck_overall: Checks!$C$3
Name fd_avgdel: 'Flow Dashboard'!$U$79
Name fd_tkw: _calc!$N$4729:$N$4776
Name lr_aother: Inputs!$N$12:$N$80

Sheet Read Me
B2: Calendar-Year Plan Loss Ratio Workbook — Inland Marine
B3: Plan year 2027 | one workbook per LOB; rows are BU x state | version 2.7.0 | built 07/31/2026 by src/build_workbook.py (generator v2.7.0) | classic formula mode (Excel-2007-era functions only)
B5: Where to go
B6: =HYPERLINK("#Control!A1","Control") -> Control | C6: Pick the plan year, BU and state; global toggles; the six headline KPIs.
B7: =HYPERLINK("#Inputs!A1","Inputs") -> Inputs | C7: Enter or paste the book: loss ratios and mods (tbl_LR), seasonality, and the policy term.
B8: =HYPERLINK("#'Rate Log'!A1","Rate Log") -> Rate Log | C8: Enter or paste rate changes — every row shows its combo's plan LR moving as you type.
B9: =HYPERLINK("#Portfolio!A1","Portfolio") -> Portfolio | C9: Every BU x state combo at once, plus the Decision Board: top movers, contribution to the book, the portfolio bridge.
B10: =HYPERLINK("#'State Summary'!A1","State Summary") -> State Summary | C10: One row per state with a BU filter ('All' = EP-weighted) — the leadership exhibit. Rate changes carry T/P status tokens and the plan LR is the visible product of the four factors beside it.
B11: =HYPERLINK("#'Program Flow'!A1","Program Flow") -> Program Flow | C11: What the program AS LOGGED is delivering — state x month YoY grids for the written rate, mod, and net legs (the descriptive twin of Net Delivery). 'All' = the EP-weighted book view.
B12: =HYPERLINK("#'Net Delivery'!A1","Net Delivery") -> Net Delivery | C12: For net-target combos: the month-by-month rate leg and the pricing change that satisfies the target, plus the suggested filing.
B13: =HYPERLINK("#Bridge!A1","Bridge") -> Bridge | C13: The selected combo's answer: projected LR -> CY plan LR, factor by factor.
B14: =HYPERLINK("#Walkthrough!A1","Walkthrough") -> Walkthrough | C14: The fully worked example — every calculation for the selected combo, start to finish.
B15: =HYPERLINK("#'One-Pager'!A1","One-Pager") -> One-Pager | C15: A print-ready brief of the selected combo — the page you hand a VP.
B16: =HYPERLINK("#'Flow Dashboard'!A1","Flow Dashboard") -> Flow Dashboard | C16: When rate and price actually earn in — monthly flow charts, the runway, the carryover ledger.
B17: =HYPERLINK("#Scenarios!A1","Scenarios") -> Scenarios | C17: Four what-if lever sets side by side against Base (S1 ships seeded as a demo).
B18: =HYPERLINK("#Compare!A1","Compare") -> Compare | C18: Any two combos side by side across the full factor chain.
B19: =HYPERLINK("#Solver!A1","Solver") -> Solver | C19: Inverse planning: the required change for a target CY LR, and timing sensitivity — can follow Control or solve any combo.
B20: =HYPERLINK("#Attribution!A1","Attribution") -> Attribution | C20: After the year closes: decompose actual vs plan into rate, timing, mod, and loss.
B21: =HYPERLINK("#'Rate Engine'!A1","Rate Engine") -> Rate Engine | C21: Audit trail: 48 writing cohorts x earning matrix behind the earned rate level.
B22: =HYPERLINK("#'Mod Engine'!A1","Mod Engine") -> Mod Engine | C22: Audit trail: the written schedule-mod path and the earned mod.
B23: =HYPERLINK("#Checks!A1","Checks") -> Checks | C23: The trust panel — must show ALL CHECKS PASS.
B24: =HYPERLINK("#Methodology!A1","Methodology") -> Methodology | C24: The full writeup: formulas as implemented, conventions, named ranges.
B25: _lists / _calc / _netcalc / _oracle | C25: Hidden machinery: validation lists, the per-combo engine blocks, the Net Delivery blocks, and the baked oracle constants. Nothing to edit there.
B27: What this workbook does
C28: Converts the projected loss ratio from a rate level indication (policy-year basis, rate fully earned) into a CALENDAR-YEAR plan loss ratio at the plan year's average earned rate level — the number a plan is actually written against.
C29: Method: standard on-leveling (Werner & Modlin, Basic Ratemaking, Ch. 5) through a monthly written-index x earning-matrix engine, extended with a schedule-mod adjustment, optional seasonality, and an optional net rate selection.
C30: Every displayed figure is calculated, never typed, and ties to an independent Python oracle at build time; the Checks sheet proves the workbook's integrity live.
B32: THE BRIDGE IN ONE LINE | C32: CY plan LR = projected LR (current level) x rate earn-in x mod drift x other adj
C33: The following year (indicative) additionally applies one year of net trend and uses that year's earn-in factors.
B35: Quick start
B36: 1. | C36: Replace the SAMPLE rows with your book: tbl_LR, seasonality, and the policy term on Inputs; the rate change log (one row per change) on the Rate Log sheet. Do not insert or delete rows — spare rows are provided. Rename BUs and states directly in tbl_LR: every dropdown and exhibit follows the live roster automatically.
B37: 2. | C37: On Control, pick the plan year, BU, and state, and set the global toggles (seasonality, the mod-adjustment master switch, the default net trend).
B38: 3. | C38: Read the KPI row on Control; audit any figure through Rate Engine -> Mod Engine -> Bridge.
B39: 4. | C39: State Summary is the per-state exhibit (BU filter; 'All' combines on adjusted-EP weights). Portfolio shows every combo at once.
B40: 5. | C40: Scenarios: up to four lever sets (rate points, timing shift, achievement, mod path, net selection) side by side against Base.
B41: 6. | C41: Optional NET RATE SELECTION per combo (tbl_LR): a combined rate + price year-over-year target from 1/1 of the plan year — see Methodology 6b for exactly what it supersedes.
B42: 7. | C42: Solver: Mode A returns the single change needed for a target CY LR at a chosen date (it replaces the whole planned program — see the note there); Mode B shows the full-year LR under each possible start month.
B43: 8. | C43: Attribution (after the year closes): enter achieved changes, actual dates, the actual mod path, and the actual CY LR for a plan-vs-actual waterfall.
B44: 9. | C44: Checks must show ALL CHECKS PASS (also surfaced on Control). Oracle-tie rows apply only while the seeded sample is intact and report N/A afterward — regenerate the workbook to re-bake them for your data. For a new plan year, regenerate from config/config.yaml and paste inputs into the fresh copy (table schemas are stable).
B46: Color legend
B47: Blue font on light yellow | C47: Required input — enter a value
B48: Blue font, no fill | C48: Optional input / lever
B49: Black font | C49: Formula calculated on the same sheet
B50: Green font | C50: Link pulled from another sheet
B51: Grey small font | C51: Engine helper — do not edit
B53: Glossary — terms and symbols
B54: Indication rate level (CRL_ind) | C54: The cumulative rate level the indication assumed FULLY EARNED — the product of all rate changes flagged 'in indication'. This is the 'assumed rate in the indication'.
B55: Earned rate level (E_CY) | C55: The rate level the plan calendar year ACTUALLY earns. Policies written last year carry older rates into its early months, and new actions earn in only gradually as the book turns over — so the earned level rarely matches the indication's.
B56: Rate earn-in (A_rate) | C56: Indication rate level / earned rate level. Above 1.000: the plan year earns less rate than the indication assumed, pushing the plan LR up. Below 1.000: extra rate the indication never counted earns in, pushing it down.
B57: Schedule mods (M_ind / M_0 / M_1) | C57: The average schedule mod assumed in the indication; the current written average; the projected average at plan-year end. Optional anchors: M_prior (~a year before the as-of) and M_2 (end of the following year). Drift in the average mod is a price change that earns in exactly like rate.
B58: Earned mod / mod drift (A_mod) | C58: The average schedule mod the plan year's premium actually carries, and A_mod = M_ind / earned mod — the identical earn-in logic applied to the price lever.
B59: Written vs earned | C59: 'Written' = the level at which new policies go on the books each month. 'Earned' = what the calendar year's premium actually carries, once each policy's term spreads it across months. Every factor in this workbook is an earned-basis answer.
B60: Achievement % | C60: For PLANNED rate changes only: the share of the filed change you expect to realize (80% of a +5% filing = +4.0% effective). Once a change is TAKEN, enter the achieved rate directly in Filed % — achievement is ignored on taken rows.
B61: In indication? (Y/N) | C61: Marks the rate changes the indication already counted in its projected loss ratio. They form CRL_ind; changes not counted there earn in as extra rate.
B62: Carryover | C62: E_CY(P+1) / E_CY(P) - 1: the earned rate change already locked in for the following year by this year's actions, before any new ones.
B63: Unearned runway | C63: Written level / earned level - 1 at a point in time: rate already on the books but not yet visible in earned premium — it will earn in over the coming months.
B64: Net rate selection (optional) | C64: Instead of an explicit program, a combo can target a combined rate + price year-over-year change from 1/1 of the plan year; history still earns as modeled, and planned rows plus the mod projection are superseded from that date (Methodology 6b). The bridge then shows one combined factor with mod drift = 1.000.
B65: Adjusted plan EP | C65: Adjusted plan earned premium (000s) — the weight behind every EP-weighted total on Portfolio and State Summary.
B66: Other adjustment (A_other) | C66: A manual factor for anything outside rate and mod earn-in; requires a written reason when it differs from 1.000.
B68: Conventions and notes
C69: Percentages are stored as decimal fractions (5.0% = 0.05) and formatted as percents.
C70: No VBA or macros anywhere. No merged cells. No external links. No volatile functions. Automatic calculation. Classic formula mode: only Excel-2007-era functions, so the file recalculates in LibreOffice and any corporate Excel build.
C71: Sheets are NOT protected (an intentional choice — the Checks panel is the integrity mechanism; protection without passwords would add friction without security).
C72: First-open checklist: (1) open the file and let it calculate; (2) confirm Control shows ALL CHECKS PASS; (3) confirm the Bridge shows 61.82% for ABD|AZ while sample data is intact; (4) replace sample inputs with your book.
B74: Version log
C75: v2.7.0 — 07/31/2026 — built from config/config.yaml (see DECISIONS.md in the repo for every judgment call).

Sheet Control
B2: Calendar-Year Plan Loss Ratio — Inland Marine
B3: Plan year 2027 | one workbook per LOB; combos are BU x state | generated by src/build_workbook.py v2.7.0 | classic formula mode
B4: Jump to: | C4: =HYPERLINK("#Inputs!A1","Inputs") -> Inputs | D4: =HYPERLINK("#'Rate Log'!A1","Rate Log") -> Rate Log | E4: =HYPERLINK("#Portfolio!A1","Portfolio") -> Portfolio | F4: =HYPERLINK("#'State Summary'!A1","State Summary") -> State Summary | G4: =HYPERLINK("#'Program Flow'!A1","Program Flow") -> Program Flow | H4: =HYPERLINK("#'Net Delivery'!A1","Net Delivery") -> Net Delivery | I4: =HYPERLINK("#Bridge!A1","Bridge") -> Bridge | J4: =HYPERLINK("#Walkthrough!A1","Walkthrough") -> Walkthrough | K4: =HYPERLINK("#One-Pager!A1","One-Pager") -> One-Pager | L4: =HYPERLINK("#'Flow Dashboard'!A1","Flow Dashboard") -> Flow Dashboard | M4: =HYPERLINK("#Scenarios!A1","Scenarios") -> Scenarios | N4: =HYPERLINK("#Compare!A1","Compare") -> Compare | O4: =HYPERLINK("#Solver!A1","Solver") -> Solver | P4: =HYPERLINK("#Attribution!A1","Attribution") -> Attribution | Q4: =HYPERLINK("#'Rate Engine'!A1","Rate Engine") -> Rate Engine | R4: =HYPERLINK("#'Mod Engine'!A1","Mod Engine") -> Mod Engine | S4: =HYPERLINK("#Checks!A1","Checks") -> Checks | T4: =HYPERLINK("#Methodology!A1","Methodology") -> Methodology | U4: =HYPERLINK("#'Read Me'!A1","Read Me") -> Read Me
B5: Selection
B6: Plan year (P) | C6: 2027 | E6: Selected key | F6: =$C$7&"|"&$C$8 -> ABD|AZ
B7: Business unit | C7: ABD | E7: Combo found in tbl_LR? | F7: =IF($G$7,"yes","NO — add the row to tbl_LR") -> yes | G7: =COUNTIF(lr_key,$F$6)>0 -> TRUE
B8: State | C8: AZ | E8: Policy term (months) | F8: =nr_TermMonths -> 6
B9: Scenario in focus | C9: Base | E9: Line of business | F9: Inland Marine
B10: =IF(nr_PlanYear=2027,"","NOTE: plan year differs from the generated 2027. All CALCULATIONS follow the plan year entered above; sample data and some printed notes still describe the generated book. Regenerate for a clean copy.")
B11: Global toggles
B12: Seasonality (written weights) | C12: OFF | D12: ON applies tbl_Seasonality weights for the selected STATE; OFF = uniform writings (classic parallelogram).
B13: Mod adjustment (master) | C13: ON | D13: Set OFF if the indication's premium trend already reflects schedule mod drift — otherwise the drift is double-counted.
B14: Projected-LR KPI shows | C14: As input
B15: Default net trend for CY 2028 | C15: 0 | D15: Annual net loss-over-premium trend applied once for the CY 2028 view wherever a combo's tbl_LR trend cell is blank; a per-state entry overrides this default.
B16: =IF(nr_SelOK,"","WARNING: the selected BU | state has no row in tbl_LR - engines show neutral factors until a row is added.")
B17: Key results — selected BU x state
B18: =IF(nr_BasisDisp="As input","Projected LR (as input)","Projected LR (current level)") -> Projected LR (as input) | D18: ="CY "&nr_PlanYear&" plan loss ratio" -> CY 2027 plan loss ratio | F18: ="CY earned rate chg vs indication" -> CY earned rate chg vs indication | H18: ="Carryover into "&(nr_PlanYear+1) -> Carryover into 2028 | J18: ="Written mod: current / projected" -> Written mod: current / projected | L18: ="Checks status" -> Checks status | N18: ="Book: program vs asserted" -> Book: program vs asserted
B19: =IF(nr_SelOK,IF(nr_BasisDisp="As input",nr_LRproj,nr_LRcur),"—") -> 0.65 | D19: =IF(nr_SelOK,nr_CYLR_P,"—") -> 0.61816314 | F19: =IF(nr_SelOK,nr_EChgVsInd,"—") -> 0.025 | H19: =IF(nr_SelOK,nr_YoY_P1,"—") -> 0.024390244 | J19: =IF(nr_SelOK,nr_M0,"—") -> 0.86 | K19: =IF(nr_SelOK,nr_M1,"—") -> 0.89 | L19: =ck_overall -> ALL CHECKS PASS | N19: =IF(OR(SUMPRODUCT(calc_netmode)=0,SUM(calc_ep)=0),"—",(SUM(calc_w_cylr_prog)-SUM(calc_w_cylr))/SUM(calc_ep)*100) -> -0.010987577
B20: from the rate level indication | D20: projected LR x rate earn-in x mod drift x other | F20: how the year's earned rate compares with the level the indication assumed | H20: earned rate change already locked in for next year | J20: current written mod / projected at plan-year end | L20: see the Checks sheet | N20: plan LR if you book the logged program instead of the net target
B22: Rate and price flow summary | F22: Compare with another combo
B23: Metric | C23: ="CY "&nr_PlanYear -> CY 2027 | D23: ="CY "&(nr_PlanYear+1)&" (indicative)" -> CY 2028 (indicative) | F23: This view | G23: =nr_SelKey -> ABD|AZ
B24: Earned rate level (E_CY) | C24: =nr_ECY_P -> 1.12996 | D24: =nr_ECY_P1 -> 1.15752 | F24: Compare to: business unit | I24: =IF(OR($G$24="",$G$25=""),"",$G$24&"|"&$G$25)
B25: Rate earn-in factor (A_rate) | C25: =nr_Arate_P -> 0.97560976 | D25: =nr_Arate_P1 -> 0.95238095 | F25: Compare to: state | I25: =IF($I$24="",0,IF(COUNTIF(calc_key,$I$24)=0,0,MATCH($I$24,calc_key,0))) -> 0
B26: Earned schedule mod | C26: =nr_MEarned_P -> 0.87197757 | D26: =nr_MEarned_P1 -> 0.88898067 | G26: selected | H26: compare | I26: difference
B27: Mod drift factor (A_mod) | C27: =nr_Amod_P -> 0.97479572 | D27: =nr_Amod_P1 -> 0.95615127 | F27: Projected LR (current level) | G27: =IF(nr_SelOK,nr_LRcur,"—") -> 0.65 | H27: =IF($I$25=0,"—",INDEX(calc_lrcur,$I$25)) -> — | I27: =IF(OR($I$25=0,NOT(nr_SelOK)),"",IF(AND(ISNUMBER($G27),ISNUMBER($H27)),$H27-$G27,""))
B28: Earned rate chg (year over year) | C28: =nr_YoY_P -> 0.07044335 | D28: =nr_YoY_P1 -> 0.024390244 | F28: ="CY "&nr_PlanYear&" plan LR" -> CY 2027 plan LR | G28: =IF(nr_SelOK,nr_CYLR_P,"—") -> 0.61816314 | H28: =IF($I$25=0,"—",INDEX(calc_cylr_p,$I$25)) -> — | I28: =IF(OR($I$25=0,NOT(nr_SelOK)),"",IF(AND(ISNUMBER($G28),ISNUMBER($H28)),$H28-$G28,""))
B29: CY plan loss ratio | C29: =nr_CYLR_P -> 0.61816314 | D29: =nr_CYLR_P1 -> 0.59190317 | F29: Rate earn-in (A_rate) | G29: =IF(nr_SelOK,nr_Arate_P,"—") -> 0.97560976 | H29: =IF($I$25=0,"—",INDEX(calc_arate_p,$I$25)) -> — | I29: =IF(OR($I$25=0,NOT(nr_SelOK)),"",IF(AND(ISNUMBER($G29),ISNUMBER($H29)),$H29-$G29,""))
B30: Next-year column is indicative — see the canonical caveat on the Bridge. | F30: Mod drift (A_mod) | G30: =IF(nr_SelOK,nr_Amod_P,"—") -> 0.97479572 | H30: =IF($I$25=0,"—",INDEX(calc_amod_p,$I$25)) -> — | I30: =IF(OR($I$25=0,NOT(nr_SelOK)),"",IF(AND(ISNUMBER($G30),ISNUMBER($H30)),$H30-$G30,""))
F31: Earned rate level (E_CY) | G31: =IF(nr_SelOK,nr_ECY_P,"—") -> 1.12996 | H31: =IF($I$25=0,"—",INDEX(calc_ecy_p,$I$25)) -> — | I31: =IF(OR($I$25=0,NOT(nr_SelOK)),"",IF(AND(ISNUMBER($G31),ISNUMBER($H31)),$H31-$G31,""))
B32: Scenario spotlight | F32: Indication rate level (CRL_ind) | G32: =IF(nr_SelOK,nr_CRLind,"—") -> 1.1024 | H32: =IF($I$25=0,"—",INDEX(calc_crl,$I$25)) -> — | I32: =IF(OR($I$25=0,NOT(nr_SelOK)),"",IF(AND(ISNUMBER($G32),ISNUMBER($H32)),$H32-$G32,""))
B33: Scenario in focus | C33: =nr_SelScenario -> Base | F33: ="Carryover into "&(nr_PlanYear+1) -> Carryover into 2028 | G33: =IF(nr_SelOK,nr_YoY_P1,"—") -> 0.024390244 | H33: =IF($I$25=0,"—",INDEX(calc_carry,$I$25)) -> — | I33: =IF(OR($I$25=0,NOT(nr_SelOK)),"",IF(AND(ISNUMBER($G33),ISNUMBER($H33)),$H33-$G33,""))
B34: CY plan LR under scenario | C34: =INDEX(sc_res_cylr,MATCH(nr_SelScenario,sc_res_names,0)) -> 0.61816314 | F34: ="CY "&(nr_PlanYear+1)&" plan LR" -> CY 2028 plan LR | G34: =IF(nr_SelOK,nr_CYLR_P1,"—") -> 0.59190317 | H34: =IF($I$25=0,"—",INDEX(calc_cylr_p1,$I$25)) -> — | I34: =IF(OR($I$25=0,NOT(nr_SelOK)),"",IF(AND(ISNUMBER($G34),ISNUMBER($H34)),$H34-$G34,""))
B35: Delta vs Base | C35: =(INDEX(sc_res_cylr,MATCH(nr_SelScenario,sc_res_names,0))-nr_CYLR_P)*100 -> 0 | F35: Pick a BU and state to light this up; the compare column reads the same hidden all-combo engine every exhibit uses.
B37: Scenario definitions live on the Scenarios sheet; the Bridge and engine sheets always show Base inputs (see Methodology).

Sheet Inputs
A1: Inputs — Inland Marine
A2: Loss-ratio and mod inputs (one row per BU x state), seasonality, and the policy term — blue font = enter values; yellow fill = required. Rate changes live on the Rate Log sheet. Structure is fixed; do not insert or delete rows.
A3: Go to: | C3: =HYPERLINK("#Control!A1","Control") -> Control | E3: =HYPERLINK("#'Rate Log'!A1","Rate Log") -> Rate Log | G3: =HYPERLINK("#Bridge!A1","Bridge") -> Bridge | I3: =HYPERLINK("#'State Summary'!A1","State Summary") -> State Summary | K3: =HYPERLINK("#Checks!A1","Checks") -> Checks | M3: =HYPERLINK("#'Read Me'!A1","Read Me") -> Read Me
A4: SAMPLE DATA: every populated row below is illustrative and should be replaced with your book. ABD|AZ carries the documented worked example used by the Checks sheet. | T4: tbl_LR A:R is one contiguous paste block — keys, helpers, and live results sit to the right. The rate change log lives on the Rate Log sheet.
A6: Workbook parameters
A7: Line of business | B7: Inland Marine
A8: Policy term (months) | B8: 6 | C8: Applies to every BU x state in this workbook (one workbook per LOB, D37).
A10: tbl_LR — one row per BU x state (projected LR and mod inputs). Columns A:R are one contiguous paste block. | T10: engine helper — do not edit | V10: live results (formulas — do not edit)
A11: BU | B11: State | C11: Projected loss ratio | D11: LR basis | E11: Indication selected chg (s) | F11: Mod assumed in indication (M_ind) | G11: Current avg written mod (M_0) | H11: Current mod as-of date | I11: Projected mod, end of plan yr (M_1) | J11: Mod ~1 yr before as-of (M_prior, opt) | K11: Projected mod, end plan yr+1 (M_2, opt) | L11: Adj plan EP (000s) | M11: Net trend, plan yr+1 (opt) | N11: Other adj factor (A_other) | O11: Reason for other adj | P11: Apply mod adjustment? | Q11: Net rate selection, plan yr (opt) | R11: Net rate selection, plan yr+1 (opt) | T11: Key | V11: This combo's CY plan LR | W11: Chg vs projected (pts) | X11: Rate earn-in (A_rate) | Y11: Mod drift (A_mod)
A12: ABD | B12: AZ | C12: 0.65 | D12: current | E12: 0.05 | F12: 0.85 | G12: 0.86 | H12: 46295 | I12: 0.89 | L12: 6400 | N12: 1 | P12: ON | T12: =IF(OR($A12="",$B12=""),"",$A12&"|"&$B12) -> ABD|AZ | V12: =IF($T12="","",INDEX(calc_cylr_p,1)) -> 0.61816314 | W12: =IF($T12="","",(INDEX(calc_cylr_p,1)-INDEX(calc_lrcur,1))*100) -> -3.1836864 | X12: =IF($T12="","",INDEX(calc_arate_p,1)) -> 0.97560976 | Y12: =IF($T12="","",INDEX(calc_amod_p,1)) -> 0.97479572
A13: ABD | B13: CO | C13: 0.588 | D13: current | E13: 0.05 | F13: 0.92 | G13: 0.91 | H13: 46295 | I13: 0.915 | L13: 16800 | N13: 1 | P13: ON | T13: =IF(OR($A13="",$B13=""),"",$A13&"|"&$B13) -> ABD|CO | V13: =IF($T13="","",INDEX(calc_cylr_p,2)) -> 0.57775356 | W13: =IF($T13="","",(INDEX(calc_cylr_p,2)-INDEX(calc_lrcur,2))*100) -> -1.0246436 | X13: =IF($T13="","",INDEX(calc_arate_p,2)) -> 0.97402597 | Y13: =IF($T13="","",INDEX(calc_amod_p,2)) -> 1.0087761
A14: ABD | B14: DE | C14: 0.572 | D14: current | E14: 0.05 | F14: 0.92 | G14: 0.91 | H14: 46295 | I14: 0.93 | L14: 13600 | N14: 1 | P14: ON | T14: =IF(OR($A14="",$B14=""),"",$A14&"|"&$B14) -> ABD|DE | V14: =IF($T14="","",INDEX(calc_cylr_p,3)) -> 0.57325552 | W14: =IF($T14="","",(INDEX(calc_cylr_p,3)-INDEX(calc_lrcur,3))*100) -> 0.12555247 | X14: =IF($T14="","",INDEX(calc_arate_p,3)) -> 1 | Y14: =IF($T14="","",INDEX(calc_amod_p,3)) -> 1.002195
A15: ABD | B15: FL | C15: 0.6 | D15: current | E15: 0.05 | F15: 0.92 | G15: 0.92 | H15: 46295 | I15: 0.92 | L15: 10400 | N15: 1 | P15: OFF | T15: =IF(OR($A15="",$B15=""),"",$A15&"|"&$B15) -> ABD|FL | V15: =IF($T15="","",INDEX(calc_cylr_p,4)) -> 0.6 | W15: =IF($T15="","",(INDEX(calc_cylr_p,4)-INDEX(calc_lrcur,4))*100) -> 0 | X15: =IF($T15="","",INDEX(calc_arate_p,4)) -> 1 | Y15: =IF($T15="","",INDEX(calc_amod_p,4)) -> 1
A16: ABD | B16: GA | C16: 0.584 | D16: current | E16: 0.05 | F16: 0.92 | G16: 0.91 | H16: 46295 | I16: 0.925 | L16: 7200 | N16: 1 | P16: ON | T16: =IF(OR($A16="",$B16=""),"",$A16&"|"&$B16) -> ABD|GA | V16: =IF($T16="","",INDEX(calc_cylr_p,5)) -> 0.5865574 | W16: =IF($T16="","",(INDEX(calc_cylr_p,5)-INDEX(calc_lrcur,5))*100) -> 0.25573995 | X16: =IF($T16="","",INDEX(calc_arate_p,5)) -> 1 | Y16: =IF($T16="","",INDEX(calc_amod_p,5)) -> 1.0043791
A17: ABD | B17: IA | C17: 0.568 | D17: current | E17: 0.05 | F17: 0.92 | G17: 0.91 | H17: 46295 | I17: 0.905 | J17: 0.9 | K17: 0.91 | L17: 17600 | N17: 1 | P17: ON | T17: =IF(OR($A17="",$B17=""),"",$A17&"|"&$B17) -> ABD|IA | V17: =IF($T17="","",INDEX(calc_cylr_p,6)) -> 0.56797978 | W17: =IF($T17="","",(INDEX(calc_cylr_p,6)-INDEX(calc_lrcur,6))*100) -> -0.0020222516 | X17: =IF($T17="","",INDEX(calc_arate_p,6)) -> 0.98684211 | Y17: =IF($T17="","",INDEX(calc_amod_p,6)) -> 1.0132973
A18: ABD | B18: IL | C18: 0.596 | D18: current | E18: 0.05 | F18: 0.92 | G18: 0.91 | H18: 46295 | I18: 0.92 | L18: 14400 | N18: 1 | P18: ON | T18: =IF(OR($A18="",$B18=""),"",$A18&"|"&$B18) -> ABD|IL | V18: =IF($T18="","",INDEX(calc_cylr_p,7)) -> 0.59991738 | W18: =IF($T18="","",(INDEX(calc_cylr_p,7)-INDEX(calc_lrcur,7))*100) -> 0.39173798 | X18: =IF($T18="","",INDEX(calc_arate_p,7)) -> 1 | Y18: =IF($T18="","",INDEX(calc_amod_p,7)) -> 1.0065728
A19: ABD | B19: IN | C19: 0.58 | D19: current | E19: 0.05 | F19: 0.92 | G19: 0.91 | H19: 46295 | I19: 0.9 | L19: 11200 | N19: 1 | P19: ON | T19: =IF(OR($A19="",$B19=""),"",$A19&"|"&$B19) -> ABD|IN | V19: =IF($T19="","",INDEX(calc_cylr_p,8)) -> 0.58911496 | W19: =IF($T19="","",(INDEX(calc_cylr_p,8)-INDEX(calc_lrcur,8))*100) -> 0.91149614 | X19: =IF($T19="","",INDEX(calc_arate_p,8)) -> 1.0002672 | Y19: =IF($T19="","",INDEX(calc_amod_p,8)) -> 1.0154442
A20: ABD | B20: KY | C20: 0.564 | D20: current | E20: 0.05 | F20: 0.92 | G20: 0.91 | H20: 46295 | I20: 0.915 | L20: 8000 | N20: 1 | P20: ON | T20: =IF(OR($A20="",$B20=""),"",$A20&"|"&$B20) -> ABD|KY | V20: =IF($T20="","",INDEX(calc_cylr_p,9)) -> 0.5689497 | W20: =IF($T20="","",(INDEX(calc_cylr_p,9)-INDEX(calc_lrcur,9))*100) -> 0.49497005 | X20: =IF($T20="","",INDEX(calc_arate_p,9)) -> 1 | Y20: =IF($T20="","",INDEX(calc_amod_p,9)) -> 1.0087761
A21: ABD | B21: MD | C21: 0.592 | D21: current | E21: 0.05 | F21: 0.92 | G21: 0.91 | H21: 46295 | I21: 0.93 | L21: 18400 | N21: 1 | P21: ON | T21: =IF(OR($A21="",$B21=""),"",$A21&"|"&$B21) -> ABD|MD | V21: =IF($T21="","",INDEX(calc_cylr_p,10)) -> 0.59391575 | W21: =IF($T21="","",(INDEX(calc_cylr_p,10)-INDEX(calc_lrcur,10))*100) -> 0.19157518 | X21: =IF($T21="","",INDEX(calc_arate_p,10)) -> 1.0010388 | Y21: =IF($T21="","",INDEX(calc_amod_p,10)) -> 1.002195
A22: ABD | B22: MI | C22: 0.576 | D22: current | E22: 0.05 | F22: 0.92 | G22: 0.91 | H22: 46295 | I22: 0.91 | L22: 15200 | N22: 1 | P22: ON | T22: =IF(OR($A22="",$B22=""),"",$A22&"|"&$B22) -> ABD|MI | V22: =IF($T22="","",INDEX(calc_cylr_p,11)) -> 0.58360113 | W22: =IF($T22="","",(INDEX(calc_cylr_p,11)-INDEX(calc_lrcur,11))*100) -> 0.76011325 | X22: =IF($T22="","",INDEX(calc_arate_p,11)) -> 1.0021834 | Y22: =IF($T22="","",INDEX(calc_amod_p,11)) -> 1.010989
A23: ABD | B23: MN | C23: 0.56 | D23: current | E23: 0.05 | F23: 0.92 | G23: 0.91 | H23: 46295 | I23: 0.925 | L23: 12000 | N23: 1 | P23: ON | T23: =IF(OR($A23="",$B23=""),"",$A23&"|"&$B23) -> ABD|MN | V23: =IF($T23="","",INDEX(calc_cylr_p,12)) -> 0.5624523 | W23: =IF($T23="","",(INDEX(calc_cylr_p,12)-INDEX(calc_lrcur,12))*100) -> 0.24523009 | X23: =IF($T23="","",INDEX(calc_arate_p,12)) -> 1 | Y23: =IF($T23="","",INDEX(calc_amod_p,12)) -> 1.0043791
A24: ABD | B24: NM | C24: 0.588 | D24: current | E24: 0.05 | F24: 0.92 | G24: 0.91 | H24: 46295 | I24: 0.905 | L24: 8800 | N24: 1 | P24: ON | T24: =IF(OR($A24="",$B24=""),"",$A24&"|"&$B24) -> ABD|NM | V24: =IF($T24="","",INDEX(calc_cylr_p,13)) -> 0.59576847 | W24: =IF($T24="","",(INDEX(calc_cylr_p,13)-INDEX(calc_lrcur,13))*100) -> 0.77684724 | X24: =IF($T24="","",INDEX(calc_arate_p,13)) -> 1 | Y24: =IF($T24="","",INDEX(calc_amod_p,13)) -> 1.0132117
A25: ABD | B25: NC | C25: 0.572 | D25: current | E25: 0.05 | F25: 0.92 | G25: 0.91 | H25: 46295 | I25: 0.92 | L25: 19200 | N25: 1 | P25: ON | T25: =IF(OR($A25="",$B25=""),"",$A25&"|"&$B25) -> ABD|NC | V25: =IF($T25="","",INDEX(calc_cylr_p,14)) -> 0.56447023 | W25: =IF($T25="","",(INDEX(calc_cylr_p,14)-INDEX(calc_lrcur,14))*100) -> -0.75297716 | X25: =IF($T25="","",INDEX(calc_arate_p,14)) -> 0.98039216 | Y25: =IF($T25="","",INDEX(calc_amod_p,14)) -> 1.0065728
A26: ABD | B26: OH | C26: 0.6 | D26: current | E26: 0.05 | F26: 0.92 | G26: 0.91 | H26: 46295 | I26: 0.9 | L26: 16000 | N26: 1 | P26: ON | T26: =IF(OR($A26="",$B26=""),"",$A26&"|"&$B26) -> ABD|OH | V26: =IF($T26="","",INDEX(calc_cylr_p,15)) -> 0.6092665 | W26: =IF($T26="","",(INDEX(calc_cylr_p,15)-INDEX(calc_lrcur,15))*100) -> 0.92664955 | X26: =IF($T26="","",INDEX(calc_arate_p,15)) -> 1 | Y26: =IF($T26="","",INDEX(calc_amod_p,15)) -> 1.0154442
A27: ABD | B27: PA | C27: 0.584 | D27: current | E27: 0.05 | F27: 0.92 | G27: 0.91 | H27: 46295 | I27: 0.915 | L27: 12800 | N27: 1 | P27: ON | T27: =IF(OR($A27="",$B27=""),"",$A27&"|"&$B27) -> ABD|PA | V27: =IF($T27="","",INDEX(calc_cylr_p,16)) -> 0.58912522 | W27: =IF($T27="","",(INDEX(calc_cylr_p,16)-INDEX(calc_lrcur,16))*100) -> 0.51252218 | X27: =IF($T27="","",INDEX(calc_arate_p,16)) -> 1 | Y27: =IF($T27="","",INDEX(calc_amod_p,16)) -> 1.0087761
A28: ABD | B28: SC | C28: 0.568 | D28: current | E28: 0.05 | F28: 0.92 | G28: 0.91 | H28: 46295 | I28: 0.93 | L28: 9600 | N28: 1 | P28: ON | T28: =IF(OR($A28="",$B28=""),"",$A28&"|"&$B28) -> ABD|SC | V28: =IF($T28="","",INDEX(calc_cylr_p,17)) -> 0.56924674 | W28: =IF($T28="","",(INDEX(calc_cylr_p,17)-INDEX(calc_lrcur,17))*100) -> 0.12467448 | X28: =IF($T28="","",INDEX(calc_arate_p,17)) -> 1 | Y28: =IF($T28="","",INDEX(calc_amod_p,17)) -> 1.002195
A29: ABD | B29: TN | C29: 0.596 | D29: current | E29: 0.05 | F29: 0.92 | G29: 0.91 | H29: 46295 | I29: 0.91 | L29: 6400 | N29: 1 | P29: ON | T29: =IF(OR($A29="",$B29=""),"",$A29&"|"&$B29) -> ABD|TN | V29: =IF($T29="","",INDEX(calc_cylr_p,18)) -> 0.59839394 | W29: =IF($T29="","",(INDEX(calc_cylr_p,18)-INDEX(calc_lrcur,18))*100) -> 0.23939371 | X29: =IF($T29="","",INDEX(calc_arate_p,18)) -> 0.99310345 | Y29: =IF($T29="","",INDEX(calc_amod_p,18)) -> 1.010989
A30: ABD | B30: VA | C30: 0.58 | D30: current | E30: 0.05 | F30: 0.92 | G30: 0.91 | H30: 46295 | I30: 0.925 | L30: 16800 | N30: 1 | P30: ON | T30: =IF(OR($A30="",$B30=""),"",$A30&"|"&$B30) -> ABD|VA | V30: =IF($T30="","",INDEX(calc_cylr_p,19)) -> 0.58253988 | W30: =IF($T30="","",(INDEX(calc_cylr_p,19)-INDEX(calc_lrcur,19))*100) -> 0.2539883 | X30: =IF($T30="","",INDEX(calc_arate_p,19)) -> 1 | Y30: =IF($T30="","",INDEX(calc_amod_p,19)) -> 1.0043791
A31: ABD | B31: WV | C31: 0.564 | D31: current | E31: 0.05 | F31: 0.92 | G31: 0.91 | H31: 46295 | I31: 0.905 | L31: 13600 | N31: 1 | P31: ON | T31: =IF(OR($A31="",$B31=""),"",$A31&"|"&$B31) -> ABD|WV | V31: =IF($T31="","",INDEX(calc_cylr_p,20)) -> 0.57167611 | W31: =IF($T31="","",(INDEX(calc_cylr_p,20)-INDEX(calc_lrcur,20))*100) -> 0.76761073 | X31: =IF($T31="","",INDEX(calc_arate_p,20)) -> 1.0003932 | Y31: =IF($T31="","",INDEX(calc_amod_p,20)) -> 1.0132117
A32: ABD | B32: WI | C32: 0.592 | D32: current | E32: 0.05 | F32: 0.92 | G32: 0.91 | H32: 46295 | I32: 0.92 | L32: 10400 | N32: 1 | P32: ON | T32: =IF(OR($A32="",$B32=""),"",$A32&"|"&$B32) -> ABD|WI | V32: =IF($T32="","",INDEX(calc_cylr_p,21)) -> 0.59589109 | W32: =IF($T32="","",(INDEX(calc_cylr_p,21)-INDEX(calc_lrcur,21))*100) -> 0.38910887 | X32: =IF($T32="","",INDEX(calc_arate_p,21)) -> 1 | Y32: =IF($T32="","",INDEX(calc_amod_p,21)) -> 1.0065728
A33: MM | B33: AZ | C33: 0.576 | D33: current | E33: 0.05 | F33: 0.92 | G33: 0.91 | H33: 46295 | I33: 0.9 | L33: 7200 | N33: 1 | P33: ON | T33: =IF(OR($A33="",$B33=""),"",$A33&"|"&$B33) -> MM|AZ | V33: =IF($T33="","",INDEX(calc_cylr_p,22)) -> 0.57071568 | W33: =IF($T33="","",(INDEX(calc_cylr_p,22)-INDEX(calc_lrcur,22))*100) -> -0.52843248 | X33: =IF($T33="","",INDEX(calc_arate_p,22)) -> 0.97575609 | Y33: =IF($T33="","",INDEX(calc_amod_p,22)) -> 1.0154442
A34: MM | B34: CO | C34: 0.56 | D34: proposed | E34: 0.08 | F34: 0.92 | G34: 0.91 | H34: 46295 | I34: 0.915 | L34: 17600 | M34: 0.01 | N34: 1 | P34: ON | T34: =IF(OR($A34="",$B34=""),"",$A34&"|"&$B34) -> MM|CO | V34: =IF($T34="","",INDEX(calc_cylr_p,23)) -> 0.61272625 | W34: =IF($T34="","",(INDEX(calc_cylr_p,23)-INDEX(calc_lrcur,23))*100) -> 0.79262522 | X34: =IF($T34="","",INDEX(calc_arate_p,23)) -> 1.0042918 | Y34: =IF($T34="","",INDEX(calc_amod_p,23)) -> 1.0087761
A35: MM | B35: DE | C35: 0.588 | D35: current | E35: 0.05 | F35: 0.92 | G35: 0.91 | H35: 46295 | I35: 0.93 | L35: 14400 | N35: 1.02 | O35: Commission timing | P35: ON | T35: =IF(OR($A35="",$B35=""),"",$A35&"|"&$B35) -> MM|DE | V35: =IF($T35="","",INDEX(calc_cylr_p,24)) -> 0.59431848 | W35: =IF($T35="","",(INDEX(calc_cylr_p,24)-INDEX(calc_lrcur,24))*100) -> 0.63184809 | X35: =IF($T35="","",INDEX(calc_arate_p,24)) -> 0.98875688 | Y35: =IF($T35="","",INDEX(calc_amod_p,24)) -> 1.002195
A36: MM | B36: FL | C36: 0.572 | D36: current | E36: 0.05 | F36: 0.92 | G36: 0.91 | H36: 46295 | I36: 0.91 | L36: 11200 | N36: 1 | P36: ON | T36: =IF(OR($A36="",$B36=""),"",$A36&"|"&$B36) -> MM|FL | V36: =IF($T36="","",INDEX(calc_cylr_p,25)) -> 0.56507959 | W36: =IF($T36="","",(INDEX(calc_cylr_p,25)-INDEX(calc_lrcur,25))*100) -> -0.69204051 | X36: =IF($T36="","",INDEX(calc_arate_p,25)) -> 0.97716333 | Y36: =IF($T36="","",INDEX(calc_amod_p,25)) -> 1.010989
A37: MM | B37: GA | C37: 0.6 | D37: current | E37: 0.05 | F37: 0.92 | G37: 0.91 | H37: 46295 | I37: 0.925 | L37: 8000 | N37: 1 | P37: ON | T37: =IF(OR($A37="",$B37=""),"",$A37&"|"&$B37) -> MM|GA | V37: =IF($T37="","",INDEX(calc_cylr_p,26)) -> 0.59469816 | W37: =IF($T37="","",(INDEX(calc_cylr_p,26)-INDEX(calc_lrcur,26))*100) -> -0.53018435 | X37: =IF($T37="","",INDEX(calc_arate_p,26)) -> 0.98684211 | Y37: =IF($T37="","",INDEX(calc_amod_p,26)) -> 1.0043791
A38: MM | B38: IA | C38: 0.584 | D38: current | E38: 0.05 | F38: 0.92 | G38: 0.91 | H38: 46295 | I38: 0.905 | L38: 18400 | N38: 1 | P38: ON | T38: =IF(OR($A38="",$B38=""),"",$A38&"|"&$B38) -> MM|IA | V38: =IF($T38="","",INDEX(calc_cylr_p,27)) -> 0.59171563 | W38: =IF($T38="","",(INDEX(calc_cylr_p,27)-INDEX(calc_lrcur,27))*100) -> 0.77156256 | X38: =IF($T38="","",INDEX(calc_arate_p,27)) -> 1 | Y38: =IF($T38="","",INDEX(calc_amod_p,27)) -> 1.0132117
A39: MM | B39: IL | C39: 0.568 | D39: current | E39: 0.05 | F39: 0.92 | G39: 0.91 | H39: 46295 | I39: 0.92 | L39: 15200 | N39: 1 | P39: ON | T39: =IF(OR($A39="",$B39=""),"",$A39&"|"&$B39) -> MM|IL | V39: =IF($T39="","",INDEX(calc_cylr_p,28)) -> 0.57173334 | W39: =IF($T39="","",(INDEX(calc_cylr_p,28)-INDEX(calc_lrcur,28))*100) -> 0.37333418 | X39: =IF($T39="","",INDEX(calc_arate_p,28)) -> 1 | Y39: =IF($T39="","",INDEX(calc_amod_p,28)) -> 1.0065728
A40: MM | B40: IN | C40: 0.596 | D40: current | E40: 0.05 | F40: 0.92 | G40: 0.91 | H40: 46295 | I40: 0.9 | L40: 12000 | N40: 1 | P40: ON | T40: =IF(OR($A40="",$B40=""),"",$A40&"|"&$B40) -> MM|IN | V40: =IF($T40="","",INDEX(calc_cylr_p,29)) -> 0.60520472 | W40: =IF($T40="","",(INDEX(calc_cylr_p,29)-INDEX(calc_lrcur,29))*100) -> 0.92047189 | X40: =IF($T40="","",INDEX(calc_arate_p,29)) -> 1 | Y40: =IF($T40="","",INDEX(calc_amod_p,29)) -> 1.0154442
A41: MM | B41: KY | C41: 0.58 | D41: current | E41: 0.05 | F41: 0.92 | G41: 0.91 | H41: 46295 | I41: 0.915 | L41: 8800 | N41: 1 | P41: ON | T41: =IF(OR($A41="",$B41=""),"",$A41&"|"&$B41) -> MM|KY | V41: =IF($T41="","",INDEX(calc_cylr_p,30)) -> 0.58363104 | W41: =IF($T41="","",(INDEX(calc_cylr_p,30)-INDEX(calc_lrcur,30))*100) -> 0.36310399 | X41: =IF($T41="","",INDEX(calc_arate_p,30)) -> 0.99750623 | Y41: =IF($T41="","",INDEX(calc_amod_p,30)) -> 1.0087761
A42: MM | B42: MD | C42: 0.564 | D42: current | E42: 0.05 | F42: 0.92 | G42: 0.91 | H42: 46295 | I42: 0.93 | L42: 19200 | N42: 1 | P42: ON | T42: =IF(OR($A42="",$B42=""),"",$A42&"|"&$B42) -> MM|MD | V42: =IF($T42="","",INDEX(calc_cylr_p,31)) -> 0.56523796 | W42: =IF($T42="","",(INDEX(calc_cylr_p,31)-INDEX(calc_lrcur,31))*100) -> 0.12379649 | X42: =IF($T42="","",INDEX(calc_arate_p,31)) -> 1 | Y42: =IF($T42="","",INDEX(calc_amod_p,31)) -> 1.002195
A43: MM | B43: MI | C43: 0.592 | D43: current | E43: 0.05 | F43: 0.92 | G43: 0.91 | H43: 46295 | I43: 0.91 | L43: 16000 | N43: 1 | P43: ON | T43: =IF(OR($A43="",$B43=""),"",$A43&"|"&$B43) -> MM|MI | V43: =IF($T43="","",INDEX(calc_cylr_p,32)) -> 0.59862658 | W43: =IF($T43="","",(INDEX(calc_cylr_p,32)-INDEX(calc_lrcur,32))*100) -> 0.66265759 | X43: =IF($T43="","",INDEX(calc_arate_p,32)) -> 1.0002023 | Y43: =IF($T43="","",INDEX(calc_amod_p,32)) -> 1.010989
A44: MM | B44: MN | C44: 0.576 | D44: current | E44: 0.05 | F44: 0.92 | G44: 0.91 | H44: 46295 | I44: 0.925 | L44: 12800 | N44: 1 | P44: ON | T44: =IF(OR($A44="",$B44=""),"",$A44&"|"&$B44) -> MM|MN | V44: =IF($T44="","",INDEX(calc_cylr_p,33)) -> 0.57852237 | W44: =IF($T44="","",(INDEX(calc_cylr_p,33)-INDEX(calc_lrcur,33))*100) -> 0.25223666 | X44: =IF($T44="","",INDEX(calc_arate_p,33)) -> 1 | Y44: =IF($T44="","",INDEX(calc_amod_p,33)) -> 1.0043791
A45: MM | B45: NM | C45: 0.56 | D45: current | E45: 0.05 | F45: 0.92 | G45: 0.91 | H45: 46295 | I45: 0.905 | L45: 9600 | N45: 1 | P45: ON | T45: =IF(OR($A45="",$B45=""),"",$A45&"|"&$B45) -> MM|NM | V45: =IF($T45="","",INDEX(calc_cylr_p,34)) -> 0.55790095 | W45: =IF($T45="","",(INDEX(calc_cylr_p,34)-INDEX(calc_lrcur,34))*100) -> -0.20990543 | X45: =IF($T45="","",INDEX(calc_arate_p,34)) -> 0.98326115 | Y45: =IF($T45="","",INDEX(calc_amod_p,34)) -> 1.0132117
A46: MM | B46: NC | C46: 0.588 | D46: current | E46: 0.05 | F46: 0.92 | G46: 0.91 | H46: 46295 | I46: 0.92 | L46: 6400 | N46: 1 | P46: ON | T46: =IF(OR($A46="",$B46=""),"",$A46&"|"&$B46) -> MM|NC | V46: =IF($T46="","",INDEX(calc_cylr_p,35)) -> 0.59561078 | W46: =IF($T46="","",(INDEX(calc_cylr_p,35)-INDEX(calc_lrcur,35))*100) -> 0.76107773 | X46: =IF($T46="","",INDEX(calc_arate_p,35)) -> 1.0063291 | Y46: =IF($T46="","",INDEX(calc_amod_p,35)) -> 1.0065728
A47: MM | B47: OH | C47: 0.572 | D47: current | E47: 0.05 | F47: 0.92 | G47: 0.91 | H47: 46295 | I47: 0.9 | L47: 16800 | N47: 1 | P47: ON | T47: =IF(OR($A47="",$B47=""),"",$A47&"|"&$B47) -> MM|OH | V47: =IF($T47="","",INDEX(calc_cylr_p,36)) -> 0.58083406 | W47: =IF($T47="","",(INDEX(calc_cylr_p,36)-INDEX(calc_lrcur,36))*100) -> 0.88340591 | X47: =IF($T47="","",INDEX(calc_arate_p,36)) -> 1 | Y47: =IF($T47="","",INDEX(calc_amod_p,36)) -> 1.0154442
A48: MM | B48: PA | C48: 0.6 | D48: current | E48: 0.05 | F48: 0.92 | G48: 0.91 | H48: 46295 | I48: 0.915 | L48: 13600 | N48: 1 | P48: ON | T48: =IF(OR($A48="",$B48=""),"",$A48&"|"&$B48) -> MM|PA | V48: =IF($T48="","",INDEX(calc_cylr_p,37)) -> 0.60526564 | W48: =IF($T48="","",(INDEX(calc_cylr_p,37)-INDEX(calc_lrcur,37))*100) -> 0.52656388 | X48: =IF($T48="","",INDEX(calc_arate_p,37)) -> 1 | Y48: =IF($T48="","",INDEX(calc_amod_p,37)) -> 1.0087761
A49: MM | B49: SC | C49: 0.584 | D49: current | E49: 0.05 | F49: 0.92 | G49: 0.91 | H49: 46295 | I49: 0.93 | L49: 10400 | N49: 1 | P49: ON | T49: =IF(OR($A49="",$B49=""),"",$A49&"|"&$B49) -> MM|SC | V49: =IF($T49="","",INDEX(calc_cylr_p,38)) -> 0.58124544 | W49: =IF($T49="","",(INDEX(calc_cylr_p,38)-INDEX(calc_lrcur,38))*100) -> -0.27545623 | X49: =IF($T49="","",INDEX(calc_arate_p,38)) -> 0.99310345 | Y49: =IF($T49="","",INDEX(calc_amod_p,38)) -> 1.002195
A50: MM | B50: TN | C50: 0.568 | D50: current | E50: 0.05 | F50: 0.92 | G50: 0.91 | H50: 46295 | I50: 0.91 | L50: 7200 | N50: 1 | P50: ON | T50: =IF(OR($A50="",$B50=""),"",$A50&"|"&$B50) -> MM|TN | V50: =IF($T50="","",INDEX(calc_cylr_p,39)) -> 0.57424176 | W50: =IF($T50="","",(INDEX(calc_cylr_p,39)-INDEX(calc_lrcur,39))*100) -> 0.62417582 | X50: =IF($T50="","",INDEX(calc_arate_p,39)) -> 1 | Y50: =IF($T50="","",INDEX(calc_amod_p,39)) -> 1.010989
A51: MM | B51: VA | C51: 0.596 | D51: current | E51: 0.05 | F51: 0.92 | G51: 0.91 | H51: 46295 | I51: 0.925 | L51: 17600 | N51: 1 | P51: ON | T51: =IF(OR($A51="",$B51=""),"",$A51&"|"&$B51) -> MM|VA | V51: =IF($T51="","",INDEX(calc_cylr_p,40)) -> 0.59860995 | W51: =IF($T51="","",(INDEX(calc_cylr_p,40)-INDEX(calc_lrcur,40))*100) -> 0.26099488 | X51: =IF($T51="","",INDEX(calc_arate_p,40)) -> 1 | Y51: =IF($T51="","",INDEX(calc_amod_p,40)) -> 1.0043791
A52: MM | B52: WV | C52: 0.58 | D52: current | E52: 0.05 | F52: 0.92 | G52: 0.91 | H52: 46295 | I52: 0.905 | L52: 14400 | N52: 1 | P52: ON | T52: =IF(OR($A52="",$B52=""),"",$A52&"|"&$B52) -> MM|WV | V52: =IF($T52="","",INDEX(calc_cylr_p,41)) -> 0.58766278 | W52: =IF($T52="","",(INDEX(calc_cylr_p,41)-INDEX(calc_lrcur,41))*100) -> 0.76627789 | X52: =IF($T52="","",INDEX(calc_arate_p,41)) -> 1 | Y52: =IF($T52="","",INDEX(calc_amod_p,41)) -> 1.0132117
A53: MM | B53: WI | C53: 0.564 | D53: current | E53: 0.05 | F53: 0.92 | G53: 0.91 | H53: 46295 | I53: 0.92 | L53: 11200 | N53: 1 | P53: ON | T53: =IF(OR($A53="",$B53=""),"",$A53&"|"&$B53) -> MM|WI | V53: =IF($T53="","",INDEX(calc_cylr_p,42)) -> 0.55296141 | W53: =IF($T53="","",(INDEX(calc_cylr_p,42)-INDEX(calc_lrcur,42))*100) -> -1.1038587 | X53: =IF($T53="","",INDEX(calc_arate_p,42)) -> 0.97402597 | Y53: =IF($T53="","",INDEX(calc_amod_p,42)) -> 1.0065728
A54: SBA | B54: AZ | C54: 0.592 | D54: current | E54: 0.05 | F54: 0.92 | G54: 0.91 | H54: 46295 | I54: 0.9 | L54: 8000 | N54: 1 | P54: ON | T54: =IF(OR($A54="",$B54=""),"",$A54&"|"&$B54) -> SBA|AZ | V54: =IF($T54="","",INDEX(calc_cylr_p,43)) -> 0.60114294 | W54: =IF($T54="","",(INDEX(calc_cylr_p,43)-INDEX(calc_lrcur,43))*100) -> 0.91429422 | X54: =IF($T54="","",INDEX(calc_arate_p,43)) -> 1 | Y54: =IF($T54="","",INDEX(calc_amod_p,43)) -> 1.0154442
A55: SBA | B55: CO | C55: 0.576 | D55: current | E55: 0.05 | F55: 0.92 | G55: 0.91 | H55: 46295 | I55: 0.915 | L55: 18400 | N55: 1 | P55: ON | T55: =IF(OR($A55="",$B55=""),"",$A55&"|"&$B55) -> SBA|CO | V55: =IF($T55="","",INDEX(calc_cylr_p,44)) -> 0.58124722 | W55: =IF($T55="","",(INDEX(calc_cylr_p,44)-INDEX(calc_lrcur,44))*100) -> 0.52472246 | X55: =IF($T55="","",INDEX(calc_arate_p,44)) -> 1.0003308 | Y55: =IF($T55="","",INDEX(calc_amod_p,44)) -> 1.0087761
A56: SBA | B56: DE | C56: 0.56 | D56: current | E56: 0.05 | F56: 0.92 | G56: 0.91 | H56: 46295 | I56: 0.93 | L56: 15200 | N56: 1 | P56: ON | T56: =IF(OR($A56="",$B56=""),"",$A56&"|"&$B56) -> SBA|DE | V56: =IF($T56="","",INDEX(calc_cylr_p,45)) -> 0.56122918 | W56: =IF($T56="","",(INDEX(calc_cylr_p,45)-INDEX(calc_lrcur,45))*100) -> 0.1229185 | X56: =IF($T56="","",INDEX(calc_arate_p,45)) -> 1 | Y56: =IF($T56="","",INDEX(calc_amod_p,45)) -> 1.002195
A57: SBA | B57: FL | C57: 0.588 | D57: current | E57: 0.05 | F57: 0.92 | G57: 0.91 | H57: 46295 | I57: 0.91 | L57: 12000 | N57: 1 | P57: ON | T57: =IF(OR($A57="",$B57=""),"",$A57&"|"&$B57) -> SBA|FL | V57: =IF($T57="","",INDEX(calc_cylr_p,46)) -> 0.58735 | W57: =IF($T57="","",(INDEX(calc_cylr_p,46)-INDEX(calc_lrcur,46))*100) -> -0.065000317 | X57: =IF($T57="","",INDEX(calc_arate_p,46)) -> 0.988037 | Y57: =IF($T57="","",INDEX(calc_amod_p,46)) -> 1.010989
A58: SBA | B58: GA | C58: 0.572 | D58: current | E58: 0.05 | F58: 0.92 | G58: 0.91 | H58: 46295 | I58: 0.925 | L58: 8800 | N58: 1 | P58: ON | T58: =IF(OR($A58="",$B58=""),"",$A58&"|"&$B58) -> SBA|GA | V58: =IF($T58="","",INDEX(calc_cylr_p,47)) -> 0.57450485 | W58: =IF($T58="","",(INDEX(calc_cylr_p,47)-INDEX(calc_lrcur,47))*100) -> 0.25048502 | X58: =IF($T58="","",INDEX(calc_arate_p,47)) -> 1 | Y58: =IF($T58="","",INDEX(calc_amod_p,47)) -> 1.0043791
A59: SBA | B59: IA | C59: 0.6 | D59: current | E59: 0.05 | F59: 0.92 | G59: 0.91 | H59: 46295 | I59: 0.905 | L59: 19200 | N59: 1 | P59: ON | T59: =IF(OR($A59="",$B59=""),"",$A59&"|"&$B59) -> SBA|IA | V59: =IF($T59="","",INDEX(calc_cylr_p,48)) -> 0.60792701 | W59: =IF($T59="","",(INDEX(calc_cylr_p,48)-INDEX(calc_lrcur,48))*100) -> 0.79270126 | X59: =IF($T59="","",INDEX(calc_arate_p,48)) -> 1 | Y59: =IF($T59="","",INDEX(calc_amod_p,48)) -> 1.0132117
A60: SBA | B60: IL | C60: 0.584 | D60: current | E60: 0.065 | F60: 0.92 | G60: 0.91 | H60: 46295 | I60: 0.92 | L60: 16000 | N60: 1 | P60: ON | T60: =IF(OR($A60="",$B60=""),"",$A60&"|"&$B60) -> SBA|IL | V60: =IF($T60="","",INDEX(calc_cylr_p,49)) -> 0.55196104 | W60: =IF($T60="","",(INDEX(calc_cylr_p,49)-INDEX(calc_lrcur,49))*100) -> -3.2038961 | X60: =IF($T60="","",INDEX(calc_arate_p,49)) -> 0.93896714 | Y60: =IF($T60="","",INDEX(calc_amod_p,49)) -> 1.0065728
A61: SBA | B61: IN | C61: 0.568 | D61: current | E61: 0.05 | F61: 0.92 | G61: 0.91 | H61: 46295 | I61: 0.9 | L61: 12800 | N61: 1 | P61: ON | T61: =IF(OR($A61="",$B61=""),"",$A61&"|"&$B61) -> SBA|IN | V61: =IF($T61="","",INDEX(calc_cylr_p,50)) -> 0.57533395 | W61: =IF($T61="","",(INDEX(calc_cylr_p,50)-INDEX(calc_lrcur,50))*100) -> 0.73339476 | X61: =IF($T61="","",INDEX(calc_arate_p,50)) -> 0.99750623 | Y61: =IF($T61="","",INDEX(calc_amod_p,50)) -> 1.0154442
A62: SBA | B62: KY | C62: 0.596 | D62: current | E62: 0.05 | F62: 0.92 | G62: 0.91 | H62: 46295 | I62: 0.915 | L62: 9600 | N62: 1 | P62: ON | Q62: 0.1 | T62: =IF(OR($A62="",$B62=""),"",$A62&"|"&$B62) -> SBA|KY | V62: =IF($T62="","",INDEX(calc_cylr_p,51)) -> 0.54805985 | W62: =IF($T62="","",(INDEX(calc_cylr_p,51)-INDEX(calc_lrcur,51))*100) -> -4.7940154 | X62: =IF($T62="","",INDEX(calc_arate_p,51)) -> 0.9195635 | Y62: =IF($T62="","",INDEX(calc_amod_p,51)) -> 1
A63: SBA | B63: MD | C63: 0.58 | D63: current | E63: 0.05 | F63: 0.92 | G63: 0.91 | H63: 46295 | I63: 0.93 | L63: 6400 | N63: 1 | P63: ON | T63: =IF(OR($A63="",$B63=""),"",$A63&"|"&$B63) -> SBA|MD | V63: =IF($T63="","",INDEX(calc_cylr_p,52)) -> 0.58127308 | W63: =IF($T63="","",(INDEX(calc_cylr_p,52)-INDEX(calc_lrcur,52))*100) -> 0.12730845 | X63: =IF($T63="","",INDEX(calc_arate_p,52)) -> 1 | Y63: =IF($T63="","",INDEX(calc_amod_p,52)) -> 1.002195
A64: SBA | B64: MI | C64: 0.564 | D64: current | E64: 0.05 | F64: 0.92 | G64: 0.91 | H64: 46295 | I64: 0.91 | L64: 16800 | N64: 1 | P64: ON | T64: =IF(OR($A64="",$B64=""),"",$A64&"|"&$B64) -> SBA|MI | V64: =IF($T64="","",INDEX(calc_cylr_p,53)) -> 0.5701978 | W64: =IF($T64="","",(INDEX(calc_cylr_p,53)-INDEX(calc_lrcur,53))*100) -> 0.61978022 | X64: =IF($T64="","",INDEX(calc_arate_p,53)) -> 1 | Y64: =IF($T64="","",INDEX(calc_amod_p,53)) -> 1.010989
A65: SBA | B65: MN | C65: 0.592 | D65: current | E65: 0.05 | F65: 0.92 | G65: 0.91 | H65: 46295 | I65: 0.925 | L65: 13600 | N65: 1 | P65: ON | T65: =IF(OR($A65="",$B65=""),"",$A65&"|"&$B65) -> SBA|MN | V65: =IF($T65="","",INDEX(calc_cylr_p,54)) -> 0.58293376 | W65: =IF($T65="","",(INDEX(calc_cylr_p,54)-INDEX(calc_lrcur,54))*100) -> -0.90662428 | X65: =IF($T65="","",INDEX(calc_arate_p,54)) -> 0.98039216 | Y65: =IF($T65="","",INDEX(calc_amod_p,54)) -> 1.0043791
A66: SBA | B66: NM | C66: 0.576 | D66: current | E66: 0.05 | F66: 0.92 | G66: 0.91 | H66: 46295 | I66: 0.905 | L66: 10400 | N66: 1 | P66: ON | T66: =IF(OR($A66="",$B66=""),"",$A66&"|"&$B66) -> SBA|NM | V66: =IF($T66="","",INDEX(calc_cylr_p,55)) -> 0.58360993 | W66: =IF($T66="","",(INDEX(calc_cylr_p,55)-INDEX(calc_lrcur,55))*100) -> 0.76099321 | X66: =IF($T66="","",INDEX(calc_arate_p,55)) -> 1 | Y66: =IF($T66="","",INDEX(calc_amod_p,55)) -> 1.0132117
A67: SBA | B67: NC | C67: 0.56 | D67: current | E67: 0.05 | F67: 0.92 | G67: 0.91 | H67: 46295 | I67: 0.92 | L67: 7200 | N67: 1 | P67: ON | T67: =IF(OR($A67="",$B67=""),"",$A67&"|"&$B67) -> SBA|NC | V67: =IF($T67="","",INDEX(calc_cylr_p,56)) -> 0.56375752 | W67: =IF($T67="","",(INDEX(calc_cylr_p,56)-INDEX(calc_lrcur,56))*100) -> 0.37575239 | X67: =IF($T67="","",INDEX(calc_arate_p,56)) -> 1.0001362 | Y67: =IF($T67="","",INDEX(calc_amod_p,56)) -> 1.0065728
A68: SBA | B68: OH | C68: 0.588 | D68: current | E68: 0.05 | F68: 0.92 | G68: 0.91 | H68: 46295 | I68: 0.9 | L68: 17600 | N68: 1 | P68: ON | T68: =IF(OR($A68="",$B68=""),"",$A68&"|"&$B68) -> SBA|OH | V68: =IF($T68="","",INDEX(calc_cylr_p,57)) -> 0.59708117 | W68: =IF($T68="","",(INDEX(calc_cylr_p,57)-INDEX(calc_lrcur,57))*100) -> 0.90811656 | X68: =IF($T68="","",INDEX(calc_arate_p,57)) -> 1 | Y68: =IF($T68="","",INDEX(calc_amod_p,57)) -> 1.0154442
A69: SBA | B69: PA | C69: 0.572 | D69: current | E69: 0.05 | F69: 0.92 | G69: 0.91 | H69: 46295 | I69: 0.915 | L69: 14400 | N69: 1 | P69: ON | T69: =IF(OR($A69="",$B69=""),"",$A69&"|"&$B69) -> SBA|PA | V69: =IF($T69="","",INDEX(calc_cylr_p,58)) -> 0.57441174 | W69: =IF($T69="","",(INDEX(calc_cylr_p,58)-INDEX(calc_lrcur,58))*100) -> 0.2411736 | X69: =IF($T69="","",INDEX(calc_arate_p,58)) -> 0.99547993 | Y69: =IF($T69="","",INDEX(calc_amod_p,58)) -> 1.0087761
A70: SBA | B70: SC | C70: 0.6 | D70: current | E70: 0.05 | F70: 0.92 | G70: 0.91 | H70: 46295 | I70: 0.93 | L70: 11200 | N70: 1 | P70: ON | T70: =IF(OR($A70="",$B70=""),"",$A70&"|"&$B70) -> SBA|SC | V70: =IF($T70="","",INDEX(calc_cylr_p,59)) -> 0.60451548 | W70: =IF($T70="","",(INDEX(calc_cylr_p,59)-INDEX(calc_lrcur,59))*100) -> 0.45154785 | X70: =IF($T70="","",INDEX(calc_arate_p,59)) -> 1.0053191 | Y70: =IF($T70="","",INDEX(calc_amod_p,59)) -> 1.002195
A71: SBA | B71: TN | C71: 0.584 | D71: current | E71: 0.05 | F71: 0.92 | G71: 0.91 | H71: 46295 | I71: 0.91 | L71: 8000 | N71: 1 | P71: ON | T71: =IF(OR($A71="",$B71=""),"",$A71&"|"&$B71) -> SBA|TN | V71: =IF($T71="","",INDEX(calc_cylr_p,60)) -> 0.59041758 | W71: =IF($T71="","",(INDEX(calc_cylr_p,60)-INDEX(calc_lrcur,60))*100) -> 0.64175824 | X71: =IF($T71="","",INDEX(calc_arate_p,60)) -> 1 | Y71: =IF($T71="","",INDEX(calc_amod_p,60)) -> 1.010989
A72: SBA | B72: VA | C72: 0.568 | D72: current | E72: 0.05 | F72: 0.92 | G72: 0.91 | H72: 46295 | I72: 0.925 | L72: 18400 | N72: 1 | P72: ON | T72: =IF(OR($A72="",$B72=""),"",$A72&"|"&$B72) -> SBA|VA | V72: =IF($T72="","",INDEX(calc_cylr_p,61)) -> 0.57048733 | W72: =IF($T72="","",(INDEX(calc_cylr_p,61)-INDEX(calc_lrcur,61))*100) -> 0.24873337 | X72: =IF($T72="","",INDEX(calc_arate_p,61)) -> 1 | Y72: =IF($T72="","",INDEX(calc_amod_p,61)) -> 1.0043791
A73: SBA | B73: WV | C73: 0.596 | D73: current | E73: 0.05 | F73: 0.92 | G73: 0.91 | H73: 46295 | I73: 0.905 | L73: 15200 | N73: 1 | P73: ON | T73: =IF(OR($A73="",$B73=""),"",$A73&"|"&$B73) -> SBA|WV | V73: =IF($T73="","",INDEX(calc_cylr_p,62)) -> 0.58818912 | W73: =IF($T73="","",(INDEX(calc_cylr_p,62)-INDEX(calc_lrcur,62))*100) -> -0.78108774 | X73: =IF($T73="","",INDEX(calc_arate_p,62)) -> 0.97402597 | Y73: =IF($T73="","",INDEX(calc_amod_p,62)) -> 1.0132117
A74: SBA | B74: WI | C74: 0.58 | D74: current | E74: 0.05 | F74: 0.92 | G74: 0.91 | H74: 46295 | I74: 0.92 | L74: 12000 | N74: 1 | P74: ON | T74: =IF(OR($A74="",$B74=""),"",$A74&"|"&$B74) -> SBA|WI | V74: =IF($T74="","",INDEX(calc_cylr_p,63)) -> 0.58381222 | W74: =IF($T74="","",(INDEX(calc_cylr_p,63)-INDEX(calc_lrcur,63))*100) -> 0.38122153 | X74: =IF($T74="","",INDEX(calc_arate_p,63)) -> 1 | Y74: =IF($T74="","",INDEX(calc_amod_p,63)) -> 1.0065728
T75: =IF(OR($A75="",$B75=""),"",$A75&"|"&$B75) | V75: =IF($T75="","",INDEX(calc_cylr_p,64)) | W75: =IF($T75="","",(INDEX(calc_cylr_p,64)-INDEX(calc_lrcur,64))*100) | X75: =IF($T75="","",INDEX(calc_arate_p,64)) | Y75: =IF($T75="","",INDEX(calc_amod_p,64))
T76: =IF(OR($A76="",$B76=""),"",$A76&"|"&$B76) | V76: =IF($T76="","",INDEX(calc_cylr_p,65)) | W76: =IF($T76="","",(INDEX(calc_cylr_p,65)-INDEX(calc_lrcur,65))*100) | X76: =IF($T76="","",INDEX(calc_arate_p,65)) | Y76: =IF($T76="","",INDEX(calc_amod_p,65))
T77: =IF(OR($A77="",$B77=""),"",$A77&"|"&$B77) | V77: =IF($T77="","",INDEX(calc_cylr_p,66)) | W77: =IF($T77="","",(INDEX(calc_cylr_p,66)-INDEX(calc_lrcur,66))*100) | X77: =IF($T77="","",INDEX(calc_arate_p,66)) | Y77: =IF($T77="","",INDEX(calc_amod_p,66))
T78: =IF(OR($A78="",$B78=""),"",$A78&"|"&$B78) | V78: =IF($T78="","",INDEX(calc_cylr_p,67)) | W78: =IF($T78="","",(INDEX(calc_cylr_p,67)-INDEX(calc_lrcur,67))*100) | X78: =IF($T78="","",INDEX(calc_arate_p,67)) | Y78: =IF($T78="","",INDEX(calc_amod_p,67))
T79: =IF(OR($A79="",$B79=""),"",$A79&"|"&$B79) | V79: =IF($T79="","",INDEX(calc_cylr_p,68)) | W79: =IF($T79="","",(INDEX(calc_cylr_p,68)-INDEX(calc_lrcur,68))*100) | X79: =IF($T79="","",INDEX(calc_arate_p,68)) | Y79: =IF($T79="","",INDEX(calc_amod_p,68))
T80: =IF(OR($A80="",$B80=""),"",$A80&"|"&$B80) | V80: =IF($T80="","",INDEX(calc_cylr_p,69)) | W80: =IF($T80="","",(INDEX(calc_cylr_p,69)-INDEX(calc_lrcur,69))*100) | X80: =IF($T80="","",INDEX(calc_arate_p,69)) | Y80: =IF($T80="","",INDEX(calc_amod_p,69))
A83: tbl_Seasonality — optional per-STATE monthly written weights (relative; blank row = uniform)
A84: State | B84: Jan | C84: Feb | D84: Mar | E84: Apr | F84: May | G84: Jun | H84: Jul | I84: Aug | J84: Sep | K84: Oct | L84: Nov | M84: Dec | N84: Row sum
A85: IL | B85: 2 | C85: 0.6 | D85: 0.6 | E85: 0.8 | F85: 0.8 | G85: 1 | H85: 2 | I85: 0.8 | J85: 0.6 | K85: 0.6 | L85: 0.6 | M85: 1.6 | N85: =IF($A85="","",SUM($B85:$M85)) -> 12
A86: IN | B86: 2 | C86: 0.6 | D86: 0.6 | E86: 0.8 | F86: 0.8 | G86: 1 | H86: 2 | I86: 0.8 | J86: 0.6 | K86: 0.6 | L86: 0.6 | M86: 1.6 | N86: =IF($A86="","",SUM($B86:$M86)) -> 12
N87: =IF($A87="","",SUM($B87:$M87))
N88: =IF($A88="","",SUM($B88:$M88))
N89: =IF($A89="","",SUM($B89:$M89))
N90: =IF($A90="","",SUM($B90:$M90))
N91: =IF($A91="","",SUM($B91:$M91))
N92: =IF($A92="","",SUM($B92:$M92))
N93: =IF($A93="","",SUM($B93:$M93))
N94: =IF($A94="","",SUM($B94:$M94))
N95: =IF($A95="","",SUM($B95:$M95))
N96: =IF($A96="","",SUM($B96:$M96))
N97: =IF($A97="","",SUM($B97:$M97))
N98: =IF($A98="","",SUM($B98:$M98))
... N108: =IF($A108="","",SUM($B108:$M108))

Sheet Rate Log
A1: Rate Change Log — Inland Marine
A2: One row per rate change per BU x state. Columns A:H are one contiguous paste block; planned rows earn filed % x achievement %. The live columns on the right show the impact of every edit on the same row.
A3: Go to: | C3: =HYPERLINK("#Control!A1","Control") -> Control | E3: =HYPERLINK("#Inputs!A1","Inputs") -> Inputs | G3: =HYPERLINK("#Bridge!A1","Bridge") -> Bridge | I3: =HYPERLINK("#Walkthrough!A1","Walkthrough") -> Walkthrough | K3: =HYPERLINK("#Checks!A1","Checks") -> Checks
A4: SAMPLE DATA: replace the populated rows with your own log. Do not insert or delete rows — spare capacity is provided below the sample.
J5: engine helpers (formulas — do not edit) | V5: live results (formulas — do not edit)
A6: BU | B6: State | C6: Effective date | D6: Filed chg % | E6: Status (taken / planned) | F6: In indication? (Y/N) | G6: Achievement % (planned) | H6: Comment | J6: Key | K6: r_eff | L6: ln(1+r) | M6: Eff month | N6: Days on/after | O6: Earlier cnt | P6: Same cnt | Q6: First? | R6: Dup month? | S6: Seq | T6: 1st planned | U6: 1st taken | V6: This combo's CY plan LR | W6: Chg vs projected (pts) | X6: % of plan yr this action earns (selected combo) | Y6: Warnings
A7: ABD | B7: AZ | C7: 45839 | D7: 0.04 | E7: taken | F7: Y | H7: Worked example (§9) | J7: =IF(OR($A7="",$B7=""),"",$A7&"|"&$B7) -> ABD|AZ | K7: =IF($C7="","",$D7*IF($E7="planned",IF($G7="",1,$G7),1)) -> 0.04 | L7: =IF($C7="",0,IF(1+$K7>0,LN(1+$K7),0)) -> 0.039220713 | M7: =IF($C7="","",DATE(YEAR($C7),MONTH($C7),1)) -> 45839 | N7: =IF($C7="",0,EOMONTH($C7,0)-$C7+1) -> 31 | O7: =IF($C7="",0,COUNTIFS(rl_key,$J7,rl_effmonth,$M7,rl_eff,"<"&$C7)) -> 0 | P7: =IF($C7="",0,COUNTIFS($J$7:$J7,$J7,$M$7:$M7,$M7,$C$7:$C7,$C7)) -> 1 | Q7: =IF($C7="",0,IF(AND($O7=0,$P7=1),1,0)) -> 1 | R7: =IF($C7="",0,IF(COUNTIFS(rl_key,$J7,rl_effmonth,$M7)>1,1,0)) -> 0 | S7: =IF($C7="",0,COUNTIFS(rl_key,$J7,rl_eff,"<"&$C7)+COUNTIFS($J$7:$J7,$J7,$C$7:$C7,$C7)) -> 1 | T7: =IF(OR($C7="",$E7<>"planned",$C7<DATE(nr_PlanYear,1,1),$C7>DATE(nr_PlanYear,12,31)),0,IF(AND(COUNTIFS(rl_key,$J7,rl_status,"planned",rl_eff,">="&DATE(nr_PlanYear,1,1),rl_eff,"<"&$C7)=0,COUNTIFS($J$7:$J7,$J7,$E$7:$E7,"planned",$C$7:$C7,$C7)=1),1,0)) -> 0 | U7: =IF(OR($C7="",$E7<>"taken"),0,IF(AND(COUNTIFS(rl_key,$J7,rl_effmonth,$M7,rl_eff,"<"&$C7,rl_status,"taken")=0,COUNTIFS($J$7:$J7,$J7,$M$7:$M7,$M7,$C$7:$C7,$C7,$E$7:$E7,"taken")=1),1,0)) -> 1 | V7: =IF($J7="","",IF(COUNTIF(lr_key,$J7)=0,"not in tbl_LR",INDEX(calc_cylr_p,MATCH($J7,lr_key,0)))) -> 0.61816314 | W7: =IF(OR($J7="",COUNTIF(lr_key,$J7)=0),"",(INDEX(calc_cylr_p,MATCH($J7,lr_key,0))-INDEX(calc_lrcur,MATCH($J7,lr_key,0)))*100) -> -3.1836864 | X7: =IF(OR($C7="",$J7<>nr_SelKey),"",(SUMPRODUCT(('Rate Engine'!$G$17:$G$64>YEAR($C7)*12+MONTH($C7)-1)*'Rate Engine'!$H$17:$H$64,'Rate Engine'!$Q$17:$Q$64)+(EOMONTH($C7,0)-$C7+1)/DAY(EOMONTH($C7,0))*SUMPRODUCT(('Rate Engine'!$G$17:$G$64=YEAR($C7)*12+MONTH($C7)-1)*'Rate Engine'!$H$17:$H$64,'Rate Engine'!$Q$17:$Q$64))/SUMPRODUCT('Rate Engine'!$H$17:$H$64,'Rate Engine'!$Q$17:$Q$64)) -> 1 | Y7: =IF($C7="","",IF(AND($E7="taken",$G7<>"",$G7<>1),"achievement ignored — restate Filed %",""))
A8: ABD | B8: AZ | C8: 46204 | D8: 0.06 | E8: taken | F8: Y | H8: Worked example (§9) | J8: =IF(OR($A8="",$B8=""),"",$A8&"|"&$B8) -> ABD|AZ | K8: =IF($C8="","",$D8*IF($E8="planned",IF($G8="",1,$G8),1)) -> 0.06 | L8: =IF($C8="",0,IF(1+$K8>0,LN(1+$K8),0)) -> 0.058268908 | M8: =IF($C8="","",DATE(YEAR($C8),MONTH($C8),1)) -> 46204 | N8: =IF($C8="",0,EOMONTH($C8,0)-$C8+1) -> 31 | O8: =IF($C8="",0,COUNTIFS(rl_key,$J8,rl_effmonth,$M8,rl_eff,"<"&$C8)) -> 0 | P8: =IF($C8="",0,COUNTIFS($J$7:$J8,$J8,$M$7:$M8,$M8,$C$7:$C8,$C8)) -> 1 | Q8: =IF($C8="",0,IF(AND($O8=0,$P8=1),1,0)) -> 1 | R8: =IF($C8="",0,IF(COUNTIFS(rl_key,$J8,rl_effmonth,$M8)>1,1,0)) -> 0 | S8: =IF($C8="",0,COUNTIFS(rl_key,$J8,rl_eff,"<"&$C8)+COUNTIFS($J$7:$J8,$J8,$C$7:$C8,$C8)) -> 2 | T8: =IF(OR($C8="",$E8<>"planned",$C8<DATE(nr_PlanYear,1,1),$C8>DATE(nr_PlanYear,12,31)),0,IF(AND(COUNTIFS(rl_key,$J8,rl_status,"planned",rl_eff,">="&DATE(nr_PlanYear,1,1),rl_eff,"<"&$C8)=0,COUNTIFS($J$7:$J8,$J8,$E$7:$E8,"planned",$C$7:$C8,$C8)=1),1,0)) -> 0 | U8: =IF(OR($C8="",$E8<>"taken"),0,IF(AND(COUNTIFS(rl_key,$J8,rl_effmonth,$M8,rl_eff,"<"&$C8,rl_status,"taken")=0,COUNTIFS($J$7:$J8,$J8,$M$7:$M8,$M8,$C$7:$C8,$C8,$E$7:$E8,"taken")=1),1,0)) -> 1 | V8: =IF($J8="","",IF(COUNTIF(lr_key,$J8)=0,"not in tbl_LR",INDEX(calc_cylr_p,MATCH($J8,lr_key,0)))) -> 0.61816314 | W8: =IF(OR($J8="",COUNTIF(lr_key,$J8)=0),"",(INDEX(calc_cylr_p,MATCH($J8,lr_key,0))-INDEX(calc_lrcur,MATCH($J8,lr_key,0)))*100) -> -3.1836864 | X8: =IF(OR($C8="",$J8<>nr_SelKey),"",(SUMPRODUCT(('Rate Engine'!$G$17:$G$64>YEAR($C8)*12+MONTH($C8)-1)*'Rate Engine'!$H$17:$H$64,'Rate Engine'!$Q$17:$Q$64)+(EOMONTH($C8,0)-$C8+1)/DAY(EOMONTH($C8,0))*SUMPRODUCT(('Rate Engine'!$G$17:$G$64=YEAR($C8)*12+MONTH($C8)-1)*'Rate Engine'!$H$17:$H$64,'Rate Engine'!$Q$17:$Q$64))/SUMPRODUCT('Rate Engine'!$H$17:$H$64,'Rate Engine'!$Q$17:$Q$64)) -> 1 | Y8: =IF($C8="","",IF(AND($E8="taken",$G8<>"",$G8<>1),"achievement ignored — restate Filed %",""))
A9: ABD | B9: AZ | C9: 46478 | D9: 0.05 | E9: planned | F9: N | G9: 1 | H9: Planned spring increase | J9: =IF(OR($A9="",$B9=""),"",$A9&"|"&$B9) -> ABD|AZ | K9: =IF($C9="","",$D9*IF($E9="planned",IF($G9="",1,$G9),1)) -> 0.05 | L9: =IF($C9="",0,IF(1+$K9>0,LN(1+$K9),0)) -> 0.048790164 | M9: =IF($C9="","",DATE(YEAR($C9),MONTH($C9),1)) -> 46478 | N9: =IF($C9="",0,EOMONTH($C9,0)-$C9+1) -> 30 | O9: =IF($C9="",0,COUNTIFS(rl_key,$J9,rl_effmonth,$M9,rl_eff,"<"&$C9)) -> 0 | P9: =IF($C9="",0,COUNTIFS($J$7:$J9,$J9,$M$7:$M9,$M9,$C$7:$C9,$C9)) -> 1 | Q9: =IF($C9="",0,IF(AND($O9=0,$P9=1),1,0)) -> 1 | R9: =IF($C9="",0,IF(COUNTIFS(rl_key,$J9,rl_effmonth,$M9)>1,1,0)) -> 0 | S9: =IF($C9="",0,COUNTIFS(rl_key,$J9,rl_eff,"<"&$C9)+COUNTIFS($J$7:$J9,$J9,$C$7:$C9,$C9)) -> 3 | T9: =IF(OR($C9="",$E9<>"planned",$C9<DATE(nr_PlanYear,1,1),$C9>DATE(nr_PlanYear,12,31)),0,IF(AND(COUNTIFS(rl_key,$J9,rl_status,"planned",rl_eff,">="&DATE(nr_PlanYear,1,1),rl_eff,"<"&$C9)=0,COUNTIFS($J$7:$J9,$J9,$E$7:$E9,"planned",$C$7:$C9,$C9)=1),1,0)) -> 1 | U9: =IF(OR($C9="",$E9<>"taken"),0,IF(AND(COUNTIFS(rl_key,$J9,rl_effmonth,$M9,rl_eff,"<"&$C9,rl_status,"taken")=0,COUNTIFS($J$7:$J9,$J9,$M$7:$M9,$M9,$C$7:$C9,$C9,$E$7:$E9,"taken")=1),1,0)) -> 0 | V9: =IF($J9="","",IF(COUNTIF(lr_key,$J9)=0,"not in tbl_LR",INDEX(calc_cylr_p,MATCH($J9,lr_key,0)))) -> 0.61816314 | W9: =IF(OR($J9="",COUNTIF(lr_key,$J9)=0),"",(INDEX(calc_cylr_p,MATCH($J9,lr_key,0))-INDEX(calc_lrcur,MATCH($J9,lr_key,0)))*100) -> -3.1836864 | X9: =IF(OR($C9="",$J9<>nr_SelKey),"",(SUMPRODUCT(('Rate Engine'!$G$17:$G$64>YEAR($C9)*12+MONTH($C9)-1)*'Rate Engine'!$H$17:$H$64,'Rate Engine'!$Q$17:$Q$64)+(EOMONTH($C9,0)-$C9+1)/DAY(EOMONTH($C9,0))*SUMPRODUCT(('Rate Engine'!$G$17:$G$64=YEAR($C9)*12+MONTH($C9)-1)*'Rate Engine'!$H$17:$H$64,'Rate Engine'!$Q$17:$Q$64))/SUMPRODUCT('Rate Engine'!$H$17:$H$64,'Rate Engine'!$Q$17:$Q$64)) -> 0.5 | Y9: =IF($C9="","",IF(AND($E9="taken",$G9<>"",$G9<>1),"achievement ignored — restate Filed %",""))
A10: SBA | B10: IL | C10: 46204 | D10: 0.065 | E10: planned | F10: N | G10: 1 | H10: Pattern: indication's selected change entered as a planned row | J10: =IF(OR($A10="",$B10=""),"",$A10&"|"&$B10) -> SBA|IL | K10: =IF($C10="","",$D10*IF($E10="planned",IF($G10="",1,$G10),1)) -> 0.065 | L10: =IF($C10="",0,IF(1+$K10>0,LN(1+$K10),0)) -> 0.062974799 | M10: =IF($C10="","",DATE(YEAR($C10),MONTH($C10),1)) -> 46204 | N10: =IF($C10="",0,EOMONTH($C10,0)-$C10+1) -> 31 | O10: =IF($C10="",0,COUNTIFS(rl_key,$J10,rl_effmonth,$M10,rl_eff,"<"&$C10)) -> 0 | P10: =IF($C10="",0,COUNTIFS($J$7:$J10,$J10,$M$7:$M10,$M10,$C$7:$C10,$C10)) -> 1 | Q10: =IF($C10="",0,IF(AND($O10=0,$P10=1),1,0)) -> 1 | R10: =IF($C10="",0,IF(COUNTIFS(rl_key,$J10,rl_effmonth,$M10)>1,1,0)) -> 0 | S10: =IF($C10="",0,COUNTIFS(rl_key,$J10,rl_eff,"<"&$C10)+COUNTIFS($J$7:$J10,$J10,$C$7:$C10,$C10)) -> 1 | T10: =IF(OR($C10="",$E10<>"planned",$C10<DATE(nr_PlanYear,1,1),$C10>DATE(nr_PlanYear,12,31)),0,IF(AND(COUNTIFS(rl_key,$J10,rl_status,"planned",rl_eff,">="&DATE(nr_PlanYear,1,1),rl_eff,"<"&$C10)=0,COUNTIFS($J$7:$J10,$J10,$E$7:$E10,"planned",$C$7:$C10,$C10)=1),1,0)) -> 0 | U10: =IF(OR($C10="",$E10<>"taken"),0,IF(AND(COUNTIFS(rl_key,$J10,rl_effmonth,$M10,rl_eff,"<"&$C10,rl_status,"taken")=0,COUNTIFS($J$7:$J10,$J10,$M$7:$M10,$M10,$C$7:$C10,$C10,$E$7:$E10,"taken")=1),1,0)) -> 0 | V10: =IF($J10="","",IF(COUNTIF(lr_key,$J10)=0,"not in tbl_LR",INDEX(calc_cylr_p,MATCH($J10,lr_key,0)))) -> 0.55196104 | W10: =IF(OR($J10="",COUNTIF(lr_key,$J10)=0),"",(INDEX(calc_cylr_p,MATCH($J10,lr_key,0))-INDEX(calc_lrcur,MATCH($J10,lr_key,0)))*100) -> -3.2038961 | X10: =IF(OR($C10="",$J10<>nr_SelKey),"",(SUMPRODUCT(('Rate Engine'!$G$17:$G$64>YEAR($C10)*12+MONTH($C10)-1)*'Rate Engine'!$H$17:$H$64,'Rate Engine'!$Q$17:$Q$64)+(EOMONTH($C10,0)-$C10+1)/DAY(EOMONTH($C10,0))*SUMPRODUCT(('Rate Engine'!$G$17:$G$64=YEAR($C10)*12+MONTH($C10)-1)*'Rate Engine'!$H$17:$H$64,'Rate Engine'!$Q$17:$Q$64))/SUMPRODUCT('Rate Engine'!$H$17:$H$64,'Rate Engine'!$Q$17:$Q$64)) | Y10: =IF($C10="","",IF(AND($E10="taken",$G10<>"",$G10<>1),"achievement ignored — restate Filed %",""))
A11: MM | B11: DE | C11: 46113 | D11: 0.05 | E11: taken | F11: Y | J11: =IF(OR($A11="",$B11=""),"",$A11&"|"&$B11) -> MM|DE | K11: =IF($C11="","",$D11*IF($E11="planned",IF($G11="",1,$G11),1)) -> 0.05 | L11: =IF($C11="",0,IF(1+$K11>0,LN(1+$K11),0)) -> 0.048790164 | M11: =IF($C11="","",DATE(YEAR($C11),MONTH($C11),1)) -> 46113 | N11: =IF($C11="",0,EOMONTH($C11,0)-$C11+1) -> 30 | O11: =IF($C11="",0,COUNTIFS(rl_key,$J11,rl_effmonth,$M11,rl_eff,"<"&$C11)) -> 0 | P11: =IF($C11="",0,COUNTIFS($J$7:$J11,$J11,$M$7:$M11,$M11,$C$7:$C11,$C11)) -> 1 | Q11: =IF($C11="",0,IF(AND($O11=0,$P11=1),1,0)) -> 1 | R11: =IF($C11="",0,IF(COUNTIFS(rl_key,$J11,rl_effmonth,$M11)>1,1,0)) -> 0 | S11: =IF($C11="",0,COUNTIFS(rl_key,$J11,rl_eff,"<"&$C11)+COUNTIFS($J$7:$J11,$J11,$C$7:$C11,$C11)) -> 1 | T11: =IF(OR($C11="",$E11<>"planned",$C11<DATE(nr_PlanYear,1,1),$C11>DATE(nr_PlanYear,12,31)),0,IF(AND(COUNTIFS(rl_key,$J11,rl_status,"planned",rl_eff,">="&DATE(nr_PlanYear,1,1),rl_eff,"<"&$C11)=0,COUNTIFS($J$7:$J11,$J11,$E$7:$E11,"planned",$C$7:$C11,$C11)=1),1,0)) -> 0 | U11: =IF(OR($C11="",$E11<>"taken"),0,IF(AND(COUNTIFS(rl_key,$J11,rl_effmonth,$M11,rl_eff,"<"&$C11,rl_status,"taken")=0,COUNTIFS($J$7:$J11,$J11,$M$7:$M11,$M11,$C$7:$C11,$C11,$E$7:$E11,"taken")=1),1,0)) -> 1 | V11: =IF($J11="","",IF(COUNTIF(lr_key,$J11)=0,"not in tbl_LR",INDEX(calc_cylr_p,MATCH($J11,lr_key,0)))) -> 0.59431848 | W11: =IF(OR($J11="",COUNTIF(lr_key,$J11)=0),"",(INDEX(calc_cylr_p,MATCH($J11,lr_key,0))-INDEX(calc_lrcur,MATCH($J11,lr_key,0)))*100) -> 0.63184809 | X11: =IF(OR($C11="",$J11<>nr_SelKey),"",(SUMPRODUCT(('Rate Engine'!$G$17:$G$64>YEAR($C11)*12+MONTH($C11)-1)*'Rate Engine'!$H$17:$H$64,'Rate Engine'!$Q$17:$Q$64)+(EOMONTH($C11,0)-$C11+1)/DAY(EOMONTH($C11,0))*SUMPRODUCT(('Rate Engine'!$G$17:$G$64=YEAR($C11)*12+MONTH($C11)-1)*'Rate Engine'!$H$17:$H$64,'Rate Engine'!$Q$17:$Q$64))/SUMPRODUCT('Rate Engine'!$H$17:$H$64,'Rate Engine'!$Q$17:$Q$64)) | Y11: =IF($C11="","",IF(AND($E11="taken",$G11<>"",$G11<>1),"achievement ignored — restate Filed %",""))
A12: MM | B12: DE | C12: 46522 | D12: 0.03 | E12: planned | F12: N | G12: 1 | H12: Mid-month effective date example | J12: =IF(OR($A12="",$B12=""),"",$A12&"|"&$B12) -> MM|DE | K12: =IF($C12="","",$D12*IF($E12="planned",IF($G12="",1,$G12),1)) -> 0.03 | L12: =IF($C12="",0,IF(1+$K12>0,LN(1+$K12),0)) -> 0.029558802 | M12: =IF($C12="","",DATE(YEAR($C12),MONTH($C12),1)) -> 46508 | N12: =IF($C12="",0,EOMONTH($C12,0)-$C12+1) -> 17 | O12: =IF($C12="",0,COUNTIFS(rl_key,$J12,rl_effmonth,$M12,rl_eff,"<"&$C12)) -> 0 | P12: =IF($C12="",0,COUNTIFS($J$7:$J12,$J12,$M$7:$M12,$M12,$C$7:$C12,$C12)) -> 1 | Q12: =IF($C12="",0,IF(AND($O12=0,$P12=1),1,0)) -> 1 | R12: =IF($C12="",0,IF(COUNTIFS(rl_key,$J12,rl_effmonth,$M12)>1,1,0)) -> 0 | S12: =IF($C12="",0,COUNTIFS(rl_key,$J12,rl_eff,"<"&$C12)+COUNTIFS($J$7:$J12,$J12,$C$7:$C12,$C12)) -> 2 | T12: =IF(OR($C12="",$E12<>"planned",$C12<DATE(nr_PlanYear,1,1),$C12>DATE(nr_PlanYear,12,31)),0,IF(AND(COUNTIFS(rl_key,$J12,rl_status,"planned",rl_eff,">="&DATE(nr_PlanYear,1,1),rl_eff,"<"&$C12)=0,COUNTIFS($J$7:$J12,$J12,$E$7:$E12,"planned",$C$7:$C12,$C12)=1),1,0)) -> 1 | U12: =IF(OR($C12="",$E12<>"taken"),0,IF(AND(COUNTIFS(rl_key,$J12,rl_effmonth,$M12,rl_eff,"<"&$C12,rl_status,"taken")=0,COUNTIFS($J$7:$J12,$J12,$M$7:$M12,$M12,$C$7:$C12,$C12,$E$7:$E12,"taken")=1),1,0)) -> 0 | V12: =IF($J12="","",IF(COUNTIF(lr_key,$J12)=0,"not in tbl_LR",INDEX(calc_cylr_p,MATCH($J12,lr_key,0)))) -> 0.59431848 | W12: =IF(OR($J12="",COUNTIF(lr_key,$J12)=0),"",(INDEX(calc_cylr_p,MATCH($J12,lr_key,0))-INDEX(calc_lrcur,MATCH($J12,lr_key,0)))*100) -> 0.63184809 | X12: =IF(OR($C12="",$J12<>nr_SelKey),"",(SUMPRODUCT(('Rate Engine'!$G$17:$G$64>YEAR($C12)*12+MONTH($C12)-1)*'Rate Engine'!$H$17:$H$64,'Rate Engine'!$Q$17:$Q$64)+(EOMONTH($C12,0)-$C12+1)/DAY(EOMONTH($C12,0))*SUMPRODUCT(('Rate Engine'!$G$17:$G$64=YEAR($C12)*12+MONTH($C12)-1)*'Rate Engine'!$H$17:$H$64,'Rate Engine'!$Q$17:$Q$64))/SUMPRODUCT('Rate Engine'!$H$17:$H$64,'Rate Engine'!$Q$17:$Q$64)) | Y12: =IF($C12="","",IF(AND($E12="taken",$G12<>"",$G12<>1),"achievement ignored — restate Filed %",""))
A13: MM | B13: FL | C13: 46296 | D13: 0.08 | E13: taken | F13: Y | J13: =IF(OR($A13="",$B13=""),"",$A13&"|"&$B13) -> MM|FL | K13: =IF($C13="","",$D13*IF($E13="planned",IF($G13="",1,$G13),1)) -> 0.08 | L13: =IF($C13="",0,IF(1+$K13>0,LN(1+$K13),0)) -> 0.076961041 | M13: =IF($C13="","",DATE(YEAR($C13),MONTH($C13),1)) -> 46296 | N13: =IF($C13="",0,EOMONTH($C13,0)-$C13+1) -> 31 | O13: =IF($C13="",0,COUNTIFS(rl_key,$J13,rl_effmonth,$M13,rl_eff,"<"&$C13)) -> 0 | P13: =IF($C13="",0,COUNTIFS($J$7:$J13,$J13,$M$7:$M13,$M13,$C$7:$C13,$C13)) -> 1 | Q13: =IF($C13="",0,IF(AND($O13=0,$P13=1),1,0)) -> 1 | R13: =IF($C13="",0,IF(COUNTIFS(rl_key,$J13,rl_effmonth,$M13)>1,1,0)) -> 0 | S13: =IF($C13="",0,COUNTIFS(rl_key,$J13,rl_eff,"<"&$C13)+COUNTIFS($J$7:$J13,$J13,$C$7:$C13,$C13)) -> 1 | T13: =IF(OR($C13="",$E13<>"planned",$C13<DATE(nr_PlanYear,1,1),$C13>DATE(nr_PlanYear,12,31)),0,IF(AND(COUNTIFS(rl_key,$J13,rl_status,"planned",rl_eff,">="&DATE(nr_PlanYear,1,1),rl_eff,"<"&$C13)=0,COUNTIFS($J$7:$J13,$J13,$E$7:$E13,"planned",$C$7:$C13,$C13)=1),1,0)) -> 0 | U13: =IF(OR($C13="",$E13<>"taken"),0,IF(AND(COUNTIFS(rl_key,$J13,rl_effmonth,$M13,rl_eff,"<"&$C13,rl_status,"taken")=0,COUNTIFS($J$7:$J13,$J13,$M$7:$M13,$M13,$C$7:$C13,$C13,$E$7:$E13,"taken")=1),1,0)) -> 1 | V13: =IF($J13="","",IF(COUNTIF(lr_key,$J13)=0,"not in tbl_LR",INDEX(calc_cylr_p,MATCH($J13,lr_key,0)))) -> 0.56507959 | W13: =IF(OR($J13="",COUNTIF(lr_key,$J13)=0),"",(INDEX(calc_cylr_p,MATCH($J13,lr_key,0))-INDEX(calc_lrcur,MATCH($J13,lr_key,0)))*100) -> -0.69204051 | X13: =IF(OR($C13="",$J13<>nr_SelKey),"",(SUMPRODUCT(('Rate Engine'!$G$17:$G$64>YEAR($C13)*12+MONTH($C13)-1)*'Rate Engine'!$H$17:$H$64,'Rate Engine'!$Q$17:$Q$64)+(EOMONTH($C13,0)-$C13+1)/DAY(EOMONTH($C13,0))*SUMPRODUCT(('Rate Engine'!$G$17:$G$64=YEAR($C13)*12+MONTH($C13)-1)*'Rate Engine'!$H$17:$H$64,'Rate Engine'!$Q$17:$Q$64))/SUMPRODUCT('Rate Engine'!$H$17:$H$64,'Rate Engine'!$Q$17:$Q$64)) | Y13: =IF($C13="","",IF(AND($E13="taken",$G13<>"",$G13<>1),"achievement ignored — restate Filed %",""))
A14: MM | B14: FL | C14: 46447 | D14: 0.06 | E14: planned | F14: N | G14: 0.8 | H14: 80% achievement assumed | J14: =IF(OR($A14="",$B14=""),"",$A14&"|"&$B14) -> MM|FL | K14: =IF($C14="","",$D14*IF($E14="planned",IF($G14="",1,$G14),1)) -> 0.048 | L14: =IF($C14="",0,IF(1+$K14>0,LN(1+$K14),0)) -> 0.046883586 | M14: =IF($C14="","",DATE(YEAR($C14),MONTH($C14),1)) -> 46447 | N14: =IF($C14="",0,EOMONTH($C14,0)-$C14+1) -> 31 | O14: =IF($C14="",0,COUNTIFS(rl_key,$J14,rl_effmonth,$M14,rl_eff,"<"&$C14)) -> 0 | P14: =IF($C14="",0,COUNTIFS($J$7:$J14,$J14,$M$7:$M14,$M14,$C$7:$C14,$C14)) -> 1 | Q14: =IF($C14="",0,IF(AND($O14=0,$P14=1),1,0)) -> 1 | R14: =IF($C14="",0,IF(COUNTIFS(rl_key,$J14,rl_effmonth,$M14)>1,1,0)) -> 0 | S14: =IF($C14="",0,COUNTIFS(rl_key,$J14,rl_eff,"<"&$C14)+COUNTIFS($J$7:$J14,$J14,$C$7:$C14,$C14)) -> 2 | T14: =IF(OR($C14="",$E14<>"planned",$C14<DATE(nr_PlanYear,1,1),$C14>DATE(nr_PlanYear,12,31)),0,IF(AND(COUNTIFS(rl_key,$J14,rl_status,"planned",rl_eff,">="&DATE(nr_PlanYear,1,1),rl_eff,"<"&$C14)=0,COUNTIFS($J$7:$J14,$J14,$E$7:$E14,"planned",$C$7:$C14,$C14)=1),1,0)) -> 1 | U14: =IF(OR($C14="",$E14<>"taken"),0,IF(AND(COUNTIFS(rl_key,$J14,rl_effmonth,$M14,rl_eff,"<"&$C14,rl_status,"taken")=0,COUNTIFS($J$7:$J14,$J14,$M$7:$M14,$M14,$C$7:$C14,$C14,$E$7:$E14,"taken")=1),1,0)) -> 0 | V14: =IF($J14="","",IF(COUNTIF(lr_key,$J14)=0,"not in tbl_LR",INDEX(calc_cylr_p,MATCH($J14,lr_key,0)))) -> 0.56507959 | W14: =IF(OR($J14="",COUNTIF(lr_key,$J14)=0),"",(INDEX(calc_cylr_p,MATCH($J14,lr_key,0))-INDEX(calc_lrcur,MATCH($J14,lr_key,0)))*100) -> -0.69204051 | X14: =IF(OR($C14="",$J14<>nr_SelKey),"",(SUMPRODUCT(('Rate Engine'!$G$17:$G$64>YEAR($C14)*12+MONTH($C14)-1)*'Rate Engine'!$H$17:$H$64,'Rate Engine'!$Q$17:$Q$64)+(EOMONTH($C14,0)-$C14+1)/DAY(EOMONTH($C14,0))*SUMPRODUCT(('Rate Engine'!$G$17:$G$64=YEAR($C14)*12+MONTH($C14)-1)*'Rate Engine'!$H$17:$H$64,'Rate Engine'!$Q$17:$Q$64))/SUMPRODUCT('Rate Engine'!$H$17:$H$64,'Rate Engine'!$Q$17:$Q$64)) | Y14: =IF($C14="","",IF(AND($E14="taken",$G14<>"",$G14<>1),"achievement ignored — restate Filed %",""))
A15: ABD | B15: IA | C15: 46174 | D15: 0.045 | E15: taken | F15: Y | J15: =IF(OR($A15="",$B15=""),"",$A15&"|"&$B15) -> ABD|IA | K15: =IF($C15="","",$D15*IF($E15="planned",IF($G15="",1,$G15),1)) -> 0.045 | L15: =IF($C15="",0,IF(1+$K15>0,LN(1+$K15),0)) -> 0.044016885 | M15: =IF($C15="","",DATE(YEAR($C15),MONTH($C15),1)) -> 46174 | N15: =IF($C15="",0,EOMONTH($C15,0)-$C15+1) -> 30 | O15: =IF($C15="",0,COUNTIFS(rl_key,$J15,rl_effmonth,$M15,rl_eff,"<"&$C15)) -> 0 | P15: =IF($C15="",0,COUNTIFS($J$7:$J15,$J15,$M$7:$M15,$M15,$C$7:$C15,$C15)) -> 1 | Q15: =IF($C15="",0,IF(AND($O15=0,$P15=1),1,0)) -> 1 | R15: =IF($C15="",0,IF(COUNTIFS(rl_key,$J15,rl_effmonth,$M15)>1,1,0)) -> 0 | S15: =IF($C15="",0,COUNTIFS(rl_key,$J15,rl_eff,"<"&$C15)+COUNTIFS($J$7:$J15,$J15,$C$7:$C15,$C15)) -> 1 | T15: =IF(OR($C15="",$E15<>"planned",$C15<DATE(nr_PlanYear,1,1),$C15>DATE(nr_PlanYear,12,31)),0,IF(AND(COUNTIFS(rl_key,$J15,rl_status,"planned",rl_eff,">="&DATE(nr_PlanYear,1,1),rl_eff,"<"&$C15)=0,COUNTIFS($J$7:$J15,$J15,$E$7:$E15,"planned",$C$7:$C15,$C15)=1),1,0)) -> 0 | U15: =IF(OR($C15="",$E15<>"taken"),0,IF(AND(COUNTIFS(rl_key,$J15,rl_effmonth,$M15,rl_eff,"<"&$C15,rl_status,"taken")=0,COUNTIFS($J$7:$J15,$J15,$M$7:$M15,$M15,$C$7:$C15,$C15,$E$7:$E15,"taken")=1),1,0)) -> 1 | V15: =IF($J15="","",IF(COUNTIF(lr_key,$J15)=0,"not in tbl_LR",INDEX(calc_cylr_p,MATCH($J15,lr_key,0)))) -> 0.56797978 | W15: =IF(OR($J15="",COUNTIF(lr_key,$J15)=0),"",(INDEX(calc_cylr_p,MATCH($J15,lr_key,0))-INDEX(calc_lrcur,MATCH($J15,lr_key,0)))*100) -> -0.0020222516 | X15: =IF(OR($C15="",$J15<>nr_SelKey),"",(SUMPRODUCT(('Rate Engine'!$G$17:$G$64>YEAR($C15)*12+MONTH($C15)-1)*'Rate Engine'!$H$17:$H$64,'Rate Engine'!$Q$17:$Q$64)+(EOMONTH($C15,0)-$C15+1)/DAY(EOMONTH($C15,0))*SUMPRODUCT(('Rate Engine'!$G$17:$G$64=YEAR($C15)*12+MONTH($C15)-1)*'Rate Engine'!$H$17:$H$64,'Rate Engine'!$Q$17:$Q$64))/SUMPRODUCT('Rate Engine'!$H$17:$H$64,'Rate Engine'!$Q$17:$Q$64)) | Y15: =IF($C15="","",IF(AND($E15="taken",$G15<>"",$G15<>1),"achievement ignored — restate Filed %",""))
A16: SBA | B16: KY | C16: 46296 | D16: 0.1 | E16: taken | F16: N | H16: Net-selection showcase: fall filing (after the indication) feeds the +10% net target | J16: =IF(OR($A16="",$B16=""),"",$A16&"|"&$B16) -> SBA|KY | K16: =IF($C16="","",$D16*IF($E16="planned",IF($G16="",1,$G16),1)) -> 0.1 | L16: =IF($C16="",0,IF(1+$K16>0,LN(1+$K16),0)) -> 0.09531018 | M16: =IF($C16="","",DATE(YEAR($C16),MONTH($C16),1)) -> 46296 | N16: =IF($C16="",0,EOMONTH($C16,0)-$C16+1) -> 31 | O16: =IF($C16="",0,COUNTIFS(rl_key,$J16,rl_effmonth,$M16,rl_eff,"<"&$C16)) -> 0 | P16: =IF($C16="",0,COUNTIFS($J$7:$J16,$J16,$M$7:$M16,$M16,$C$7:$C16,$C16)) -> 1 | Q16: =IF($C16="",0,IF(AND($O16=0,$P16=1),1,0)) -> 1 | R16: =IF($C16="",0,IF(COUNTIFS(rl_key,$J16,rl_effmonth,$M16)>1,1,0)) -> 0 | S16: =IF($C16="",0,COUNTIFS(rl_key,$J16,rl_eff,"<"&$C16)+COUNTIFS($J$7:$J16,$J16,$C$7:$C16,$C16)) -> 1 | T16: =IF(OR($C16="",$E16<>"planned",$C16<DATE(nr_PlanYear,1,1),$C16>DATE(nr_PlanYear,12,31)),0,IF(AND(COUNTIFS(rl_key,$J16,rl_status,"planned",rl_eff,">="&DATE(nr_PlanYear,1,1),rl_eff,"<"&$C16)=0,COUNTIFS($J$7:$J16,$J16,$E$7:$E16,"planned",$C$7:$C16,$C16)=1),1,0)) -> 0 | U16: =IF(OR($C16="",$E16<>"taken"),0,IF(AND(COUNTIFS(rl_key,$J16,rl_effmonth,$M16,rl_eff,"<"&$C16,rl_status,"taken")=0,COUNTIFS($J$7:$J16,$J16,$M$7:$M16,$M16,$C$7:$C16,$C16,$E$7:$E16,"taken")=1),1,0)) -> 1 | V16: =IF($J16="","",IF(COUNTIF(lr_key,$J16)=0,"not in tbl_LR",INDEX(calc_cylr_p,MATCH($J16,lr_key,0)))) -> 0.54805985 | W16: =IF(OR($J16="",COUNTIF(lr_key,$J16)=0),"",(INDEX(calc_cylr_p,MATCH($J16,lr_key,0))-INDEX(calc_lrcur,MATCH($J16,lr_key,0)))*100) -> -4.7940154 | X16: =IF(OR($C16="",$J16<>nr_SelKey),"",(SUMPRODUCT(('Rate Engine'!$G$17:$G$64>YEAR($C16)*12+MONTH($C16)-1)*'Rate Engine'!$H$17:$H$64,'Rate Engine'!$Q$17:$Q$64)+(EOMONTH($C16,0)-$C16+1)/DAY(EOMONTH($C16,0))*SUMPRODUCT(('Rate Engine'!$G$17:$G$64=YEAR($C16)*12+MONTH($C16)-1)*'Rate Engine'!$H$17:$H$64,'Rate Engine'!$Q$17:$Q$64))/SUMPRODUCT('Rate Engine'!$H$17:$H$64,'Rate Engine'!$Q$17:$Q$64)) | Y16: =IF($C16="","",IF(AND($E16="taken",$G16<>"",$G16<>1),"achievement ignored — restate Filed %",""))
A17: SBA | B17: KY | C17: 46478 | D17: 0.04 | E17: planned | F17: N | G17: 1 | H17: Planned filing the net-delivery default picks up | J17: =IF(OR($A17="",$B17=""),"",$A17&"|"&$B17) -> SBA|KY | K17: =IF($C17="","",$D17*IF($E17="planned",IF($G17="",1,$G17),1)) -> 0.04 | L17: =IF($C17="",0,IF(1+$K17>0,LN(1+$K17),0)) -> 0.039220713 | M17: =IF($C17="","",DATE(YEAR($C17),MONTH($C17),1)) -> 46478 | N17: =IF($C17="",0,EOMONTH($C17,0)-$C17+1) -> 30 | O17: =IF($C17="",0,COUNTIFS(rl_key,$J17,rl_effmonth,$M17,rl_eff,"<"&$C17)) -> 0 | P17: =IF($C17="",0,COUNTIFS($J$7:$J17,$J17,$M$7:$M17,$M17,$C$7:$C17,$C17)) -> 1 | Q17: =IF($C17="",0,IF(AND($O17=0,$P17=1),1,0)) -> 1 | R17: =IF($C17="",0,IF(COUNTIFS(rl_key,$J17,rl_effmonth,$M17)>1,1,0)) -> 0 | S17: =IF($C17="",0,COUNTIFS(rl_key,$J17,rl_eff,"<"&$C17)+COUNTIFS($J$7:$J17,$J17,$C$7:$C17,$C17)) -> 2 | T17: =IF(OR($C17="",$E17<>"planned",$C17<DATE(nr_PlanYear,1,1),$C17>DATE(nr_PlanYear,12,31)),0,IF(AND(COUNTIFS(rl_key,$J17,rl_status,"planned",rl_eff,">="&DATE(nr_PlanYear,1,1),rl_eff,"<"&$C17)=0,COUNTIFS($J$7:$J17,$J17,$E$7:$E17,"planned",$C$7:$C17,$C17)=1),1,0)) -> 1 | U17: =IF(OR($C17="",$E17<>"taken"),0,IF(AND(COUNTIFS(rl_key,$J17,rl_effmonth,$M17,rl_eff,"<"&$C17,rl_status,"taken")=0,COUNTIFS($J$7:$J17,$J17,$M$7:$M17,$M17,$C$7:$C17,$C17,$E$7:$E17,"taken")=1),1,0)) -> 0 | V17: =IF($J17="","",IF(COUNTIF(lr_key,$J17)=0,"not in tbl_LR",INDEX(calc_cylr_p,MATCH($J17,lr_key,0)))) -> 0.54805985 | W17: =IF(OR($J17="",COUNTIF(lr_key,$J17)=0),"",(INDEX(calc_cylr_p,MATCH($J17,lr_key,0))-INDEX(calc_lrcur,MATCH($J17,lr_key,0)))*100) -> -4.7940154 | X17: =IF(OR($C17="",$J17<>nr_SelKey),"",(SUMPRODUCT(('Rate Engine'!$G$17:$G$64>YEAR($C17)*12+MONTH($C17)-1)*'Rate Engine'!$H$17:$H$64,'Rate Engine'!$Q$17:$Q$64)+(EOMONTH($C17,0)-$C17+1)/DAY(EOMONTH($C17,0))*SUMPRODUCT(('Rate Engine'!$G$17:$G$64=YEAR($C17)*12+MONTH($C17)-1)*'Rate Engine'!$H$17:$H$64,'Rate Engine'!$Q$17:$Q$64))/SUMPRODUCT('Rate Engine'!$H$17:$H$64,'Rate Engine'!$Q$17:$Q$64)) | Y17: =IF($C17="","",IF(AND($E17="taken",$G17<>"",$G17<>1),"achievement ignored — restate Filed %",""))
A18: ABD | B18: CO | C18: 46054 | D18: 0.03 | E18: taken | F18: Y | J18: =IF(OR($A18="",$B18=""),"",$A18&"|"&$B18) -> ABD|CO | K18: =IF($C18="","",$D18*IF($E18="planned",IF($G18="",1,$G18),1)) -> 0.03 | L18: =IF($C18="",0,IF(1+$K18>0,LN(1+$K18),0)) -> 0.029558802 | M18: =IF($C18="","",DATE(YEAR($C18),MONTH($C18),1)) -> 46054 | N18: =IF($C18="",0,EOMONTH($C18,0)-$C18+1) -> 28 | O18: =IF($C18="",0,COUNTIFS(rl_key,$J18,rl_effmonth,$M18,rl_eff,"<"&$C18)) -> 0 | P18: =IF($C18="",0,COUNTIFS($J$7:$J18,$J18,$M$7:$M18,$M18,$C$7:$C18,$C18)) -> 1 | Q18: =IF($C18="",0,IF(AND($O18=0,$P18=1),1,0)) -> 1 | R18: =IF($C18="",0,IF(COUNTIFS(rl_key,$J18,rl_effmonth,$M18)>1,1,0)) -> 0 | S18: =IF($C18="",0,COUNTIFS(rl_key,$J18,rl_eff,"<"&$C18)+COUNTIFS($J$7:$J18,$J18,$C$7:$C18,$C18)) -> 1 | T18: =IF(OR($C18="",$E18<>"planned",$C18<DATE(nr_PlanYear,1,1),$C18>DATE(nr_PlanYear,12,31)),0,IF(AND(COUNTIFS(rl_key,$J18,rl_status,"planned",rl_eff,">="&DATE(nr_PlanYear,1,1),rl_eff,"<"&$C18)=0,COUNTIFS($J$7:$J18,$J18,$E$7:$E18,"planned",$C$7:$C18,$C18)=1),1,0)) -> 0 | U18: =IF(OR($C18="",$E18<>"taken"),0,IF(AND(COUNTIFS(rl_key,$J18,rl_effmonth,$M18,rl_eff,"<"&$C18,rl_status,"taken")=0,COUNTIFS($J$7:$J18,$J18,$M$7:$M18,$M18,$C$7:$C18,$C18,$E$7:$E18,"taken")=1),1,0)) -> 1 | V18: =IF($J18="","",IF(COUNTIF(lr_key,$J18)=0,"not in tbl_LR",INDEX(calc_cylr_p,MATCH($J18,lr_key,0)))) -> 0.57775356 | W18: =IF(OR($J18="",COUNTIF(lr_key,$J18)=0),"",(INDEX(calc_cylr_p,MATCH($J18,lr_key,0))-INDEX(calc_lrcur,MATCH($J18,lr_key,0)))*100) -> -1.0246436 | X18: =IF(OR($C18="",$J18<>nr_SelKey),"",(SUMPRODUCT(('Rate Engine'!$G$17:$G$64>YEAR($C18)*12+MONTH($C18)-1)*'Rate Engine'!$H$17:$H$64,'Rate Engine'!$Q$17:$Q$64)+(EOMONTH($C18,0)-$C18+1)/DAY(EOMONTH($C18,0))*SUMPRODUCT(('Rate Engine'!$G$17:$G$64=YEAR($C18)*12+MONTH($C18)-1)*'Rate Engine'!$H$17:$H$64,'Rate Engine'!$Q$17:$Q$64))/SUMPRODUCT('Rate Engine'!$H$17:$H$64,'Rate Engine'!$Q$17:$Q$64)) | Y18: =IF($C18="","",IF(AND($E18="taken",$G18<>"",$G18<>1),"achievement ignored — restate Filed %",""))
A19: ABD | B19: CO | C19: 46419 | D19: 0.04 | E19: planned | F19: N | G19: 1 | J19: =IF(OR($A19="",$B19=""),"",$A19&"|"&$B19) -> ABD|CO | K19: =IF($C19="","",$D19*IF($E19="planned",IF($G19="",1,$G19),1)) -> 0.04 | L19: =IF($C19="",0,IF(1+$K19>0,LN(1+$K19),0)) -> 0.039220713 | M19: =IF($C19="","",DATE(YEAR($C19),MONTH($C19),1)) -> 46419 | N19: =IF($C19="",0,EOMONTH($C19,0)-$C19+1) -> 28 | O19: =IF($C19="",0,COUNTIFS(rl_key,$J19,rl_effmonth,$M19,rl_eff,"<"&$C19)) -> 0 | P19: =IF($C19="",0,COUNTIFS($J$7:$J19,$J19,$M$7:$M19,$M19,$C$7:$C19,$C19)) -> 1 | Q19: =IF($C19="",0,IF(AND($O19=0,$P19=1),1,0)) -> 1 | R19: =IF($C19="",0,IF(COUNTIFS(rl_key,$J19,rl_effmonth,$M19)>1,1,0)) -> 0 | S19: =IF($C19="",0,COUNTIFS(rl_key,$J19,rl_eff,"<"&$C19)+COUNTIFS($J$7:$J19,$J19,$C$7:$C19,$C19)) -> 2 | T19: =IF(OR($C19="",$E19<>"planned",$C19<DATE(nr_PlanYear,1,1),$C19>DATE(nr_PlanYear,12,31)),0,IF(AND(COUNTIFS(rl_key,$J19,rl_status,"planned",rl_eff,">="&DATE(nr_PlanYear,1,1),rl_eff,"<"&$C19)=0,COUNTIFS($J$7:$J19,$J19,$E$7:$E19,"planned",$C$7:$C19,$C19)=1),1,0)) -> 1 | U19: =IF(OR($C19="",$E19<>"taken"),0,IF(AND(COUNTIFS(rl_key,$J19,rl_effmonth,$M19,rl_eff,"<"&$C19,rl_status,"taken")=0,COUNTIFS($J$7:$J19,$J19,$M$7:$M19,$M19,$C$7:$C19,$C19,$E$7:$E19,"taken")=1),1,0)) -> 0 | V19: =IF($J19="","",IF(COUNTIF(lr_key,$J19)=0,"not in tbl_LR",INDEX(calc_cylr_p,MATCH($J19,lr_key,0)))) -> 0.57775356 | W19: =IF(OR($J19="",COUNTIF(lr_key,$J19)=0),"",(INDEX(calc_cylr_p,MATCH($J19,lr_key,0))-INDEX(calc_lrcur,MATCH($J19,lr_key,0)))*100) -> -1.0246436 | X19: =IF(OR($C19="",$J19<>nr_SelKey),"",(SUMPRODUCT(('Rate Engine'!$G$17:$G$64>YEAR($C19)*12+MONTH($C19)-1)*'Rate Engine'!$H$17:$H$64,'Rate Engine'!$Q$17:$Q$64)+(EOMONTH($C19,0)-$C19+1)/DAY(EOMONTH($C19,0))*SUMPRODUCT(('Rate Engine'!$G$17:$G$64=YEAR($C19)*12+MONTH($C19)-1)*'Rate Engine'!$H$17:$H$64,'Rate Engine'!$Q$17:$Q$64))/SUMPRODUCT('Rate Engine'!$H$17:$H$64,'Rate Engine'!$Q$17:$Q$64)) | Y19: =IF($C19="","",IF(AND($E19="taken",$G19<>"",$G19<>1),"achievement ignored — restate Filed %",""))
A20: ABD | B20: FL | C20: 46113 | D20: 0.05 | E20: taken | F20: Y | J20: =IF(OR($A20="",$B20=""),"",$A20&"|"&$B20) -> ABD|FL | K20: =IF($C20="","",$D20*IF($E20="planned",IF($G20="",1,$G20),1)) -> 0.05 | L20: =IF($C20="",0,IF(1+$K20>0,LN(1+$K20),0)) -> 0.048790164 | M20: =IF($C20="","",DATE(YEAR($C20),MONTH($C20),1)) -> 46113 | N20: =IF($C20="",0,EOMONTH($C20,0)-$C20+1) -> 30 | O20: =IF($C20="",0,COUNTIFS(rl_key,$J20,rl_effmonth,$M20,rl_eff,"<"&$C20)) -> 0 | P20: =IF($C20="",0,COUNTIFS($J$7:$J20,$J20,$M$7:$M20,$M20,$C$7:$C20,$C20)) -> 1 | Q20: =IF($C20="",0,IF(AND($O20=0,$P20=1),1,0)) -> 1 | R20: =IF($C20="",0,IF(COUNTIFS(rl_key,$J20,rl_effmonth,$M20)>1,1,0)) -> 0 | S20: =IF($C20="",0,COUNTIFS(rl_key,$J20,rl_eff,"<"&$C20)+COUNTIFS($J$7:$J20,$J20,$C$7:$C20,$C20)) -> 1 | T20: =IF(OR($C20="",$E20<>"planned",$C20<DATE(nr_PlanYear,1,1),$C20>DATE(nr_PlanYear,12,31)),0,IF(AND(COUNTIFS(rl_key,$J20,rl_status,"planned",rl_eff,">="&DATE(nr_PlanYear,1,1),rl_eff,"<"&$C20)=0,COUNTIFS($J$7:$J20,$J20,$E$7:$E20,"planned",$C$7:$C20,$C20)=1),1,0)) -> 0 | U20: =IF(OR($C20="",$E20<>"taken"),0,IF(AND(COUNTIFS(rl_key,$J20,rl_effmonth,$M20,rl_eff,"<"&$C20,rl_status,"taken")=0,COUNTIFS($J$7:$J20,$J20,$M$7:$M20,$M20,$C$7:$C20,$C20,$E$7:$E20,"taken")=1),1,0)) -> 1 | V20: =IF($J20="","",IF(COUNTIF(lr_key,$J20)=0,"not in tbl_LR",INDEX(calc_cylr_p,MATCH($J20,lr_key,0)))) -> 0.6 | W20: =IF(OR($J20="",COUNTIF(lr_key,$J20)=0),"",(INDEX(calc_cylr_p,MATCH($J20,lr_key,0))-INDEX(calc_lrcur,MATCH($J20,lr_key,0)))*100) -> 0 | X20: =IF(OR($C20="",$J20<>nr_SelKey),"",(SUMPRODUCT(('Rate Engine'!$G$17:$G$64>YEAR($C20)*12+MONTH($C20)-1)*'Rate Engine'!$H$17:$H$64,'Rate Engine'!$Q$17:$Q$64)+(EOMONTH($C20,0)-$C20+1)/DAY(EOMONTH($C20,0))*SUMPRODUCT(('Rate Engine'!$G$17:$G$64=YEAR($C20)*12+MONTH($C20)-1)*'Rate Engine'!$H$17:$H$64,'Rate Engine'!$Q$17:$Q$64))/SUMPRODUCT('Rate Engine'!$H$17:$H$64,'Rate Engine'!$Q$17:$Q$64)) | Y20: =IF($C20="","",IF(AND($E20="taken",$G20<>"",$G20<>1),"achievement ignored — restate Filed %",""))
A21: ABD | B21: GA | C21: 46143 | D21: 0.06 | E21: taken | F21: Y | J21: =IF(OR($A21="",$B21=""),"",$A21&"|"&$B21) -> ABD|GA | K21: =IF($C21="","",$D21*IF($E21="planned",IF($G21="",1,$G21),1)) -> 0.06 | L21: =IF($C21="",0,IF(1+$K21>0,LN(1+$K21),0)) -> 0.058268908 | M21: =IF($C21="","",DATE(YEAR($C21),MONTH($C21),1)) -> 46143 | N21: =IF($C21="",0,EOMONTH($C21,0)-$C21+1) -> 31 | O21: =IF($C21="",0,COUNTIFS(rl_key,$J21,rl_effmonth,$M21,rl_eff,"<"&$C21)) -> 0 | P21: =IF($C21="",0,COUNTIFS($J$7:$J21,$J21,$M$7:$M21,$M21,$C$7:$C21,$C21)) -> 1 | Q21: =IF($C21="",0,IF(AND($O21=0,$P21=1),1,0)) -> 1 | R21: =IF($C21="",0,IF(COUNTIFS(rl_key,$J21,rl_effmonth,$M21)>1,1,0)) -> 0 | S21: =IF($C21="",0,COUNTIFS(rl_key,$J21,rl_eff,"<"&$C21)+COUNTIFS($J$7:$J21,$J21,$C$7:$C21,$C21)) -> 1 | T21: =IF(OR($C21="",$E21<>"planned",$C21<DATE(nr_PlanYear,1,1),$C21>DATE(nr_PlanYear,12,31)),0,IF(AND(COUNTIFS(rl_key,$J21,rl_status,"planned",rl_eff,">="&DATE(nr_PlanYear,1,1),rl_eff,"<"&$C21)=0,COUNTIFS($J$7:$J21,$J21,$E$7:$E21,"planned",$C$7:$C21,$C21)=1),1,0)) -> 0 | U21: =IF(OR($C21="",$E21<>"taken"),0,IF(AND(COUNTIFS(rl_key,$J21,rl_effmonth,$M21,rl_eff,"<"&$C21,rl_status,"taken")=0,COUNTIFS($J$7:$J21,$J21,$M$7:$M21,$M21,$C$7:$C21,$C21,$E$7:$E21,"taken")=1),1,0)) -> 1 | V21: =IF($J21="","",IF(COUNTIF(lr_key,$J21)=0,"not in tbl_LR",INDEX(calc_cylr_p,MATCH($J21,lr_key,0)))) -> 0.5865574 | W21: =IF(OR($J21="",COUNTIF(lr_key,$J21)=0),"",(INDEX(calc_cylr_p,MATCH($J21,lr_key,0))-INDEX(calc_lrcur,MATCH($J21,lr_key,0)))*100) -> 0.25573995 | X21: =IF(OR($C21="",$J21<>nr_SelKey),"",(SUMPRODUCT(('Rate Engine'!$G$17:$G$64>YEAR($C21)*12+MONTH($C21)-1)*'Rate Engine'!$H$17:$H$64,'Rate Engine'!$Q$17:$Q$64)+(EOMONTH($C21,0)-$C21+1)/DAY(EOMONTH($C21,0))*SUMPRODUCT(('Rate Engine'!$G$17:$G$64=YEAR($C21)*12+MONTH($C21)-1)*'Rate Engine'!$H$17:$H$64,'Rate Engine'!$Q$17:$Q$64))/SUMPRODUCT('Rate Engine'!$H$17:$H$64,'Rate Engine'!$Q$17:$Q$64)) | Y21: =IF($C21="","",IF(AND($E21="taken",$G21<>"",$G21<>1),"achievement ignored — restate Filed %",""))
A22: ABD | B22: IA | C22: 46539 | D22: 0.04 | E22: planned | F22: N | G22: 1 | J22: =IF(OR($A22="",$B22=""),"",$A22&"|"&$B22) -> ABD|IA | K22: =IF($C22="","",$D22*IF($E22="planned",IF($G22="",1,$G22),1)) -> 0.04 | L22: =IF($C22="",0,IF(1+$K22>0,LN(1+$K22),0)) -> 0.039220713 | M22: =IF($C22="","",DATE(YEAR($C22),MONTH($C22),1)) -> 46539 | N22: =IF($C22="",0,EOMONTH($C22,0)-$C22+1) -> 30 | O22: =IF($C22="",0,COUNTIFS(rl_key,$J22,rl_effmonth,$M22,rl_eff,"<"&$C22)) -> 0 | P22: =IF($C22="",0,COUNTIFS($J$7:$J22,$J22,$M$7:$M22,$M22,$C$7:$C22,$C22)) -> 1 | Q22: =IF($C22="",0,IF(AND($O22=0,$P22=1),1,0)) -> 1 | R22: =IF($C22="",0,IF(COUNTIFS(rl_key,$J22,rl_effmonth,$M22)>1,1,0)) -> 0 | S22: =IF($C22="",0,COUNTIFS(rl_key,$J22,rl_eff,"<"&$C22)+COUNTIFS($J$7:$J22,$J22,$C$7:$C22,$C22)) -> 2 | T22: =IF(OR($C22="",$E22<>"planned",$C22<DATE(nr_PlanYear,1,1),$C22>DATE(nr_PlanYear,12,31)),0,IF(AND(COUNTIFS(rl_key,$J22,rl_status,"planned",rl_eff,">="&DATE(nr_PlanYear,1,1),rl_eff,"<"&$C22)=0,COUNTIFS($J$7:$J22,$J22,$E$7:$E22,"planned",$C$7:$C22,$C22)=1),1,0)) -> 1 | U22: =IF(OR($C22="",$E22<>"taken"),0,IF(AND(COUNTIFS(rl_key,$J22,rl_effmonth,$M22,rl_eff,"<"&$C22,rl_status,"taken")=0,COUNTIFS($J$7:$J22,$J22,$M$7:$M22,$M22,$C$7:$C22,$C22,$E$7:$E22,"taken")=1),1,0)) -> 0 | V22: =IF($J22="","",IF(COUNTIF(lr_key,$J22)=0,"not in tbl_LR",INDEX(calc_cylr_p,MATCH($J22,lr_key,0)))) -> 0.56797978 | W22: =IF(OR($J22="",COUNTIF(lr_key,$J22)=0),"",(INDEX(calc_cylr_p,MATCH($J22,lr_key,0))-INDEX(calc_lrcur,MATCH($J22,lr_key,0)))*100) -> -0.0020222516 | X22: =IF(OR($C22="",$J22<>nr_SelKey),"",(SUMPRODUCT(('Rate Engine'!$G$17:$G$64>YEAR($C22)*12+MONTH($C22)-1)*'Rate Engine'!$H$17:$H$64,'Rate Engine'!$Q$17:$Q$64)+(EOMONTH($C22,0)-$C22+1)/DAY(EOMONTH($C22,0))*SUMPRODUCT(('Rate Engine'!$G$17:$G$64=YEAR($C22)*12+MONTH($C22)-1)*'Rate Engine'!$H$17:$H$64,'Rate Engine'!$Q$17:$Q$64))/SUMPRODUCT('Rate Engine'!$H$17:$H$64,'Rate Engine'!$Q$17:$Q$64)) | Y22: =IF($C22="","",IF(AND($E22="taken",$G22<>"",$G22<>1),"achievement ignored — restate Filed %",""))
A23: ABD | B23: IL | C23: 46204 | D23: 0.03 | E23: taken | F23: Y | J23: =IF(OR($A23="",$B23=""),"",$A23&"|"&$B23) -> ABD|IL | K23: =IF($C23="","",$D23*IF($E23="planned",IF($G23="",1,$G23),1)) -> 0.03 | L23: =IF($C23="",0,IF(1+$K23>0,LN(1+$K23),0)) -> 0.029558802 | M23: =IF($C23="","",DATE(YEAR($C23),MONTH($C23),1)) -> 46204 | N23: =IF($C23="",0,EOMONTH($C23,0)-$C23+1) -> 31 | O23: =IF($C23="",0,COUNTIFS(rl_key,$J23,rl_effmonth,$M23,rl_eff,"<"&$C23)) -> 0 | P23: =IF($C23="",0,COUNTIFS($J$7:$J23,$J23,$M$7:$M23,$M23,$C$7:$C23,$C23)) -> 1 | Q23: =IF($C23="",0,IF(AND($O23=0,$P23=1),1,0)) -> 1 | R23: =IF($C23="",0,IF(COUNTIFS(rl_key,$J23,rl_effmonth,$M23)>1,1,0)) -> 0 | S23: =IF($C23="",0,COUNTIFS(rl_key,$J23,rl_eff,"<"&$C23)+COUNTIFS($J$7:$J23,$J23,$C$7:$C23,$C23)) -> 1 | T23: =IF(OR($C23="",$E23<>"planned",$C23<DATE(nr_PlanYear,1,1),$C23>DATE(nr_PlanYear,12,31)),0,IF(AND(COUNTIFS(rl_key,$J23,rl_status,"planned",rl_eff,">="&DATE(nr_PlanYear,1,1),rl_eff,"<"&$C23)=0,COUNTIFS($J$7:$J23,$J23,$E$7:$E23,"planned",$C$7:$C23,$C23)=1),1,0)) -> 0 | U23: =IF(OR($C23="",$E23<>"taken"),0,IF(AND(COUNTIFS(rl_key,$J23,rl_effmonth,$M23,rl_eff,"<"&$C23,rl_status,"taken")=0,COUNTIFS($J$7:$J23,$J23,$M$7:$M23,$M23,$C$7:$C23,$C23,$E$7:$E23,"taken")=1),1,0)) -> 1 | V23: =IF($J23="","",IF(COUNTIF(lr_key,$J23)=0,"not in tbl_LR",INDEX(calc_cylr_p,MATCH($J23,lr_key,0)))) -> 0.59991738 | W23: =IF(OR($J23="",COUNTIF(lr_key,$J23)=0),"",(INDEX(calc_cylr_p,MATCH($J23,lr_key,0))-INDEX(calc_lrcur,MATCH($J23,lr_key,0)))*100) -> 0.39173798 | X23: =IF(OR($C23="",$J23<>nr_SelKey),"",(SUMPRODUCT(('Rate Engine'!$G$17:$G$64>YEAR($C23)*12+MONTH($C23)-1)*'Rate Engine'!$H$17:$H$64,'Rate Engine'!$Q$17:$Q$64)+(EOMONTH($C23,0)-$C23+1)/DAY(EOMONTH($C23,0))*SUMPRODUCT(('Rate Engine'!$G$17:$G$64=YEAR($C23)*12+MONTH($C23)-1)*'Rate Engine'!$H$17:$H$64,'Rate Engine'!$Q$17:$Q$64))/SUMPRODUCT('Rate Engine'!$H$17:$H$64,'Rate Engine'!$Q$17:$Q$64)) | Y23: =IF($C23="","",IF(AND($E23="taken",$G23<>"",$G23<>1),"achievement ignored — restate Filed %",""))
A24: ABD | B24: IN | C24: 46235 | D24: 0.04 | E24: taken | F24: Y | J24: =IF(OR($A24="",$B24=""),"",$A24&"|"&$B24) -> ABD|IN | K24: =IF($C24="","",$D24*IF($E24="planned",IF($G24="",1,$G24),1)) -> 0.04 | L24: =IF($C24="",0,IF(1+$K24>0,LN(1+$K24),0)) -> 0.039220713 | M24: =IF($C24="","",DATE(YEAR($C24),MONTH($C24),1)) -> 46235 | N24: =IF($C24="",0,EOMONTH($C24,0)-$C24+1) -> 31 | O24: =IF($C24="",0,COUNTIFS(rl_key,$J24,rl_effmonth,$M24,rl_eff,"<"&$C24)) -> 0 | P24: =IF($C24="",0,COUNTIFS($J$7:$J24,$J24,$M$7:$M24,$M24,$C$7:$C24,$C24)) -> 1 | Q24: =IF($C24="",0,IF(AND($O24=0,$P24=1),1,0)) -> 1 | R24: =IF($C24="",0,IF(COUNTIFS(rl_key,$J24,rl_effmonth,$M24)>1,1,0)) -> 0 | S24: =IF($C24="",0,COUNTIFS(rl_key,$J24,rl_eff,"<"&$C24)+COUNTIFS($J$7:$J24,$J24,$C$7:$C24,$C24)) -> 1 | T24: =IF(OR($C24="",$E24<>"planned",$C24<DATE(nr_PlanYear,1,1),$C24>DATE(nr_PlanYear,12,31)),0,IF(AND(COUNTIFS(rl_key,$J24,rl_status,"planned",rl_eff,">="&DATE(nr_PlanYear,1,1),rl_eff,"<"&$C24)=0,COUNTIFS($J$7:$J24,$J24,$E$7:$E24,"planned",$C$7:$C24,$C24)=1),1,0)) -> 0 | U24: =IF(OR($C24="",$E24<>"taken"),0,IF(AND(COUNTIFS(rl_key,$J24,rl_effmonth,$M24,rl_eff,"<"&$C24,rl_status,"taken")=0,COUNTIFS($J$7:$J24,$J24,$M$7:$M24,$M24,$C$7:$C24,$C24,$E$7:$E24,"taken")=1),1,0)) -> 1 | V24: =IF($J24="","",IF(COUNTIF(lr_key,$J24)=0,"not in tbl_LR",INDEX(calc_cylr_p,MATCH($J24,lr_key,0)))) -> 0.58911496 | W24: =IF(OR($J24="",COUNTIF(lr_key,$J24)=0),"",(INDEX(calc_cylr_p,MATCH($J24,lr_key,0))-INDEX(calc_lrcur,MATCH($J24,lr_key,0)))*100) -> 0.91149614 | X24: =IF(OR($C24="",$J24<>nr_SelKey),"",(SUMPRODUCT(('Rate Engine'!$G$17:$G$64>YEAR($C24)*12+MONTH($C24)-1)*'Rate Engine'!$H$17:$H$64,'Rate Engine'!$Q$17:$Q$64)+(EOMONTH($C24,0)-$C24+1)/DAY(EOMONTH($C24,0))*SUMPRODUCT(('Rate Engine'!$G$17:$G$64=YEAR($C24)*12+MONTH($C24)-1)*'Rate Engine'!$H$17:$H$64,'Rate Engine'!$Q$17:$Q$64))/SUMPRODUCT('Rate Engine'!$H$17:$H$64,'Rate Engine'!$Q$17:$Q$64)) | Y24: =IF($C24="","",IF(AND($E24="taken",$G24<>"",$G24<>1),"achievement ignored — restate Filed %",""))
A25: ABD | B25: MD | C25: 46296 | D25: 0.06 | E25: taken | F25: Y | J25: =IF(OR($A25="",$B25=""),"",$A25&"|"&$B25) -> ABD|MD | K25: =IF($C25="","",$D25*IF($E25="planned",IF($G25="",1,$G25),1)) -> 0.06 | L25: =IF($C25="",0,IF(1+$K25>0,LN(1+$K25),0)) -> 0.058268908 | M25: =IF($C25="","",DATE(YEAR($C25),MONTH($C25),1)) -> 46296 | N25: =IF($C25="",0,EOMONTH($C25,0)-$C25+1) -> 31 | O25: =IF($C25="",0,COUNTIFS(rl_key,$J25,rl_effmonth,$M25,rl_eff,"<"&$C25)) -> 0 | P25: =IF($C25="",0,COUNTIFS($J$7:$J25,$J25,$M$7:$M25,$M25,$C$7:$C25,$C25)) -> 1 | Q25: =IF($C25="",0,IF(AND($O25=0,$P25=1),1,0)) -> 1 | R25: =IF($C25="",0,IF(COUNTIFS(rl_key,$J25,rl_effmonth,$M25)>1,1,0)) -> 0 | S25: =IF($C25="",0,COUNTIFS(rl_key,$J25,rl_eff,"<"&$C25)+COUNTIFS($J$7:$J25,$J25,$C$7:$C25,$C25)) -> 1 | T25: =IF(OR($C25="",$E25<>"planned",$C25<DATE(nr_PlanYear,1,1),$C25>DATE(nr_PlanYear,12,31)),0,IF(AND(COUNTIFS(rl_key,$J25,rl_status,"planned",rl_eff,">="&DATE(nr_PlanYear,1,1),rl_eff,"<"&$C25)=0,COUNTIFS($J$7:$J25,$J25,$E$7:$E25,"planned",$C$7:$C25,$C25)=1),1,0)) -> 0 | U25: =IF(OR($C25="",$E25<>"taken"),0,IF(AND(COUNTIFS(rl_key,$J25,rl_effmonth,$M25,rl_eff,"<"&$C25,rl_status,"taken")=0,COUNTIFS($J$7:$J25,$J25,$M$7:$M25,$M25,$C$7:$C25,$C25,$E$7:$E25,"taken")=1),1,0)) -> 1 | V25: =IF($J25="","",IF(COUNTIF(lr_key,$J25)=0,"not in tbl_LR",INDEX(calc_cylr_p,MATCH($J25,lr_key,0)))) -> 0.59391575 | W25: =IF(OR($J25="",COUNTIF(lr_key,$J25)=0),"",(INDEX(calc_cylr_p,MATCH($J25,lr_key,0))-INDEX(calc_lrcur,MATCH($J25,lr_key,0)))*100) -> 0.19157518 | X25: =IF(OR($C25="",$J25<>nr_SelKey),"",(SUMPRODUCT(('Rate Engine'!$G$17:$G$64>YEAR($C25)*12+MONTH($C25)-1)*'Rate Engine'!$H$17:$H$64,'Rate Engine'!$Q$17:$Q$64)+(EOMONTH($C25,0)-$C25+1)/DAY(EOMONTH($C25,0))*SUMPRODUCT(('Rate Engine'!$G$17:$G$64=YEAR($C25)*12+MONTH($C25)-1)*'Rate Engine'!$H$17:$H$64,'Rate Engine'!$Q$17:$Q$64))/SUMPRODUCT('Rate Engine'!$H$17:$H$64,'Rate Engine'!$Q$17:$Q$64)) | Y25: =IF($C25="","",IF(AND($E25="taken",$G25<>"",$G25<>1),"achievement ignored — restate Filed %",""))
A26: ABD | B26: MD | C26: 46661 | D26: 0.04 | E26: planned | F26: N | G26: 1 | J26: =IF(OR($A26="",$B26=""),"",$A26&"|"&$B26) -> ABD|MD | K26: =IF($C26="","",$D26*IF($E26="planned",IF($G26="",1,$G26),1)) -> 0.04 | L26: =IF($C26="",0,IF(1+$K26>0,LN(1+$K26),0)) -> 0.039220713 | M26: =IF($C26="","",DATE(YEAR($C26),MONTH($C26),1)) -> 46661 | N26: =IF($C26="",0,EOMONTH($C26,0)-$C26+1) -> 31 | O26: =IF($C26="",0,COUNTIFS(rl_key,$J26,rl_effmonth,$M26,rl_eff,"<"&$C26)) -> 0 | P26: =IF($C26="",0,COUNTIFS($J$7:$J26,$J26,$M$7:$M26,$M26,$C$7:$C26,$C26)) -> 1 | Q26: =IF($C26="",0,IF(AND($O26=0,$P26=1),1,0)) -> 1 | R26: =IF($C26="",0,IF(COUNTIFS(rl_key,$J26,rl_effmonth,$M26)>1,1,0)) -> 0 | S26: =IF($C26="",0,COUNTIFS(rl_key,$J26,rl_eff,"<"&$C26)+COUNTIFS($J$7:$J26,$J26,$C$7:$C26,$C26)) -> 2 | T26: =IF(OR($C26="",$E26<>"planned",$C26<DATE(nr_PlanYear,1,1),$C26>DATE(nr_PlanYear,12,31)),0,IF(AND(COUNTIFS(rl_key,$J26,rl_status,"planned",rl_eff,">="&DATE(nr_PlanYear,1,1),rl_eff,"<"&$C26)=0,COUNTIFS($J$7:$J26,$J26,$E$7:$E26,"planned",$C$7:$C26,$C26)=1),1,0)) -> 1 | U26: =IF(OR($C26="",$E26<>"taken"),0,IF(AND(COUNTIFS(rl_key,$J26,rl_effmonth,$M26,rl_eff,"<"&$C26,rl_status,"taken")=0,COUNTIFS($J$7:$J26,$J26,$M$7:$M26,$M26,$C$7:$C26,$C26,$E$7:$E26,"taken")=1),1,0)) -> 0 | V26: =IF($J26="","",IF(COUNTIF(lr_key,$J26)=0,"not in tbl_LR",INDEX(calc_cylr_p,MATCH($J26,lr_key,0)))) -> 0.59391575 | W26: =IF(OR($J26="",COUNTIF(lr_key,$J26)=0),"",(INDEX(calc_cylr_p,MATCH($J26,lr_key,0))-INDEX(calc_lrcur,MATCH($J26,lr_key,0)))*100) -> 0.19157518 | X26: =IF(OR($C26="",$J26<>nr_SelKey),"",(SUMPRODUCT(('Rate Engine'!$G$17:$G$64>YEAR($C26)*12+MONTH($C26)-1)*'Rate Engine'!$H$17:$H$64,'Rate Engine'!$Q$17:$Q$64)+(EOMONTH($C26,0)-$C26+1)/DAY(EOMONTH($C26,0))*SUMPRODUCT(('Rate Engine'!$G$17:$G$64=YEAR($C26)*12+MONTH($C26)-1)*'Rate Engine'!$H$17:$H$64,'Rate Engine'!$Q$17:$Q$64))/SUMPRODUCT('Rate Engine'!$H$17:$H$64,'Rate Engine'!$Q$17:$Q$64)) | Y26: =IF($C26="","",IF(AND($E26="taken",$G26<>"",$G26<>1),"achievement ignored — restate Filed %",""))
A27: ABD | B27: MI | C27: 46327 | D27: 0.02 | E27: taken | F27: Y | J27: =IF(OR($A27="",$B27=""),"",$A27&"|"&$B27) -> ABD|MI | K27: =IF($C27="","",$D27*IF($E27="planned",IF($G27="",1,$G27),1)) -> 0.02 | L27: =IF($C27="",0,IF(1+$K27>0,LN(1+$K27),0)) -> 0.019802627 | M27: =IF($C27="","",DATE(YEAR($C27),MONTH($C27),1)) -> 46327 | N27: =IF($C27="",0,EOMONTH($C27,0)-$C27+1) -> 30 | O27: =IF($C27="",0,COUNTIFS(rl_key,$J27,rl_effmonth,$M27,rl_eff,"<"&$C27)) -> 0 | P27: =IF($C27="",0,COUNTIFS($J$7:$J27,$J27,$M$7:$M27,$M27,$C$7:$C27,$C27)) -> 1 | Q27: =IF($C27="",0,IF(AND($O27=0,$P27=1),1,0)) -> 1 | R27: =IF($C27="",0,IF(COUNTIFS(rl_key,$J27,rl_effmonth,$M27)>1,1,0)) -> 0 | S27: =IF($C27="",0,COUNTIFS(rl_key,$J27,rl_eff,"<"&$C27)+COUNTIFS($J$7:$J27,$J27,$C$7:$C27,$C27)) -> 1 | T27: =IF(OR($C27="",$E27<>"planned",$C27<DATE(nr_PlanYear,1,1),$C27>DATE(nr_PlanYear,12,31)),0,IF(AND(COUNTIFS(rl_key,$J27,rl_status,"planned",rl_eff,">="&DATE(nr_PlanYear,1,1),rl_eff,"<"&$C27)=0,COUNTIFS($J$7:$J27,$J27,$E$7:$E27,"planned",$C$7:$C27,$C27)=1),1,0)) -> 0 | U27: =IF(OR($C27="",$E27<>"taken"),0,IF(AND(COUNTIFS(rl_key,$J27,rl_effmonth,$M27,rl_eff,"<"&$C27,rl_status,"taken")=0,COUNTIFS($J$7:$J27,$J27,$M$7:$M27,$M27,$C$7:$C27,$C27,$E$7:$E27,"taken")=1),1,0)) -> 1 | V27: =IF($J27="","",IF(COUNTIF(lr_key,$J27)=0,"not in tbl_LR",INDEX(calc_cylr_p,MATCH($J27,lr_key,0)))) -> 0.58360113 | W27: =IF(OR($J27="",COUNTIF(lr_key,$J27)=0),"",(INDEX(calc_cylr_p,MATCH($J27,lr_key,0))-INDEX(calc_lrcur,MATCH($J27,lr_key,0)))*100) -> 0.76011325 | X27: =IF(OR($C27="",$J27<>nr_SelKey),"",(SUMPRODUCT(('Rate Engine'!$G$17:$G$64>YEAR($C27)*12+MONTH($C27)-1)*'Rate Engine'!$H$17:$H$64,'Rate Engine'!$Q$17:$Q$64)+(EOMONTH($C27,0)-$C27+1)/DAY(EOMONTH($C27,0))*SUMPRODUCT(('Rate Engine'!$G$17:$G$64=YEAR($C27)*12+MONTH($C27)-1)*'Rate Engine'!$H$17:$H$64,'Rate Engine'!$Q$17:$Q$64))/SUMPRODUCT('Rate Engine'!$H$17:$H$64,'Rate Engine'!$Q$17:$Q$64)) | Y27: =IF($C27="","",IF(AND($E27="taken",$G27<>"",$G27<>1),"achievement ignored — restate Filed %",""))
A28: ABD | B28: NM | C28: 46023 | D28: 0.04 | E28: taken | F28: Y | J28: =IF(OR($A28="",$B28=""),"",$A28&"|"&$B28) -> ABD|NM | K28: =IF($C28="","",$D28*IF($E28="planned",IF($G28="",1,$G28),1)) -> 0.04 | L28: =IF($C28="",0,IF(1+$K28>0,LN(1+$K28),0)) -> 0.039220713 | M28: =IF($C28="","",DATE(YEAR($C28),MONTH($C28),1)) -> 46023 | N28: =IF($C28="",0,EOMONTH($C28,0)-$C28+1) -> 31 | O28: =IF($C28="",0,COUNTIFS(rl_key,$J28,rl_effmonth,$M28,rl_eff,"<"&$C28)) -> 0 | P28: =IF($C28="",0,COUNTIFS($J$7:$J28,$J28,$M$7:$M28,$M28,$C$7:$C28,$C28)) -> 1 | Q28: =IF($C28="",0,IF(AND($O28=0,$P28=1),1,0)) -> 1 | R28: =IF($C28="",0,IF(COUNTIFS(rl_key,$J28,rl_effmonth,$M28)>1,1,0)) -> 0 | S28: =IF($C28="",0,COUNTIFS(rl_key,$J28,rl_eff,"<"&$C28)+COUNTIFS($J$7:$J28,$J28,$C$7:$C28,$C28)) -> 1 | T28: =IF(OR($C28="",$E28<>"planned",$C28<DATE(nr_PlanYear,1,1),$C28>DATE(nr_PlanYear,12,31)),0,IF(AND(COUNTIFS(rl_key,$J28,rl_status,"planned",rl_eff,">="&DATE(nr_PlanYear,1,1),rl_eff,"<"&$C28)=0,COUNTIFS($J$7:$J28,$J28,$E$7:$E28,"planned",$C$7:$C28,$C28)=1),1,0)) -> 0 | U28: =IF(OR($C28="",$E28<>"taken"),0,IF(AND(COUNTIFS(rl_key,$J28,rl_effmonth,$M28,rl_eff,"<"&$C28,rl_status,"taken")=0,COUNTIFS($J$7:$J28,$J28,$M$7:$M28,$M28,$C$7:$C28,$C28,$E$7:$E28,"taken")=1),1,0)) -> 1 | V28: =IF($J28="","",IF(COUNTIF(lr_key,$J28)=0,"not in tbl_LR",INDEX(calc_cylr_p,MATCH($J28,lr_key,0)))) -> 0.59576847 | W28: =IF(OR($J28="",COUNTIF(lr_key,$J28)=0),"",(INDEX(calc_cylr_p,MATCH($J28,lr_key,0))-INDEX(calc_lrcur,MATCH($J28,lr_key,0)))*100) -> 0.77684724 | X28: =IF(OR($C28="",$J28<>nr_SelKey),"",(SUMPRODUCT(('Rate Engine'!$G$17:$G$64>YEAR($C28)*12+MONTH($C28)-1)*'Rate Engine'!$H$17:$H$64,'Rate Engine'!$Q$17:$Q$64)+(EOMONTH($C28,0)-$C28+1)/DAY(EOMONTH($C28,0))*SUMPRODUCT(('Rate Engine'!$G$17:$G$64=YEAR($C28)*12+MONTH($C28)-1)*'Rate Engine'!$H$17:$H$64,'Rate Engine'!$Q$17:$Q$64))/SUMPRODUCT('Rate Engine'!$H$17:$H$64,'Rate Engine'!$Q$17:$Q$64)) | Y28: =IF($C28="","",IF(AND($E28="taken",$G28<>"",$G28<>1),"achievement ignored — restate Filed %",""))
A29: ABD | B29: NC | C29: 46054 | D29: 0.05 | E29: taken | F29: Y | J29: =IF(OR($A29="",$B29=""),"",$A29&"|"&$B29) -> ABD|NC | K29: =IF($C29="","",$D29*IF($E29="planned",IF($G29="",1,$G29),1)) -> 0.05 | L29: =IF($C29="",0,IF(1+$K29>0,LN(1+$K29),0)) -> 0.048790164 | M29: =IF($C29="","",DATE(YEAR($C29),MONTH($C29),1)) -> 46054 | N29: =IF($C29="",0,EOMONTH($C29,0)-$C29+1) -> 28 | O29: =IF($C29="",0,COUNTIFS(rl_key,$J29,rl_effmonth,$M29,rl_eff,"<"&$C29)) -> 0 | P29: =IF($C29="",0,COUNTIFS($J$7:$J29,$J29,$M$7:$M29,$M29,$C$7:$C29,$C29)) -> 1 | Q29: =IF($C29="",0,IF(AND($O29=0,$P29=1),1,0)) -> 1 | R29: =IF($C29="",0,IF(COUNTIFS(rl_key,$J29,rl_effmonth,$M29)>1,1,0)) -> 0 | S29: =IF($C29="",0,COUNTIFS(rl_key,$J29,rl_eff,"<"&$C29)+COUNTIFS($J$7:$J29,$J29,$C$7:$C29,$C29)) -> 1 | T29: =IF(OR($C29="",$E29<>"planned",$C29<DATE(nr_PlanYear,1,1),$C29>DATE(nr_PlanYear,12,31)),0,IF(AND(COUNTIFS(rl_key,$J29,rl_status,"planned",rl_eff,">="&DATE(nr_PlanYear,1,1),rl_eff,"<"&$C29)=0,COUNTIFS($J$7:$J29,$J29,$E$7:$E29,"planned",$C$7:$C29,$C29)=1),1,0)) -> 0 | U29: =IF(OR($C29="",$E29<>"taken"),0,IF(AND(COUNTIFS(rl_key,$J29,rl_effmonth,$M29,rl_eff,"<"&$C29,rl_status,"taken")=0,COUNTIFS($J$7:$J29,$J29,$M$7:$M29,$M29,$C$7:$C29,$C29,$E$7:$E29,"taken")=1),1,0)) -> 1 | V29: =IF($J29="","",IF(COUNTIF(lr_key,$J29)=0,"not in tbl_LR",INDEX(calc_cylr_p,MATCH($J29,lr_key,0)))) -> 0.56447023 | W29: =IF(OR($J29="",COUNTIF(lr_key,$J29)=0),"",(INDEX(calc_cylr_p,MATCH($J29,lr_key,0))-INDEX(calc_lrcur,MATCH($J29,lr_key,0)))*100) -> -0.75297716 | X29: =IF(OR($C29="",$J29<>nr_SelKey),"",(SUMPRODUCT(('Rate Engine'!$G$17:$G$64>YEAR($C29)*12+MONTH($C29)-1)*'Rate Engine'!$H$17:$H$64,'Rate Engine'!$Q$17:$Q$64)+(EOMONTH($C29,0)-$C29+1)/DAY(EOMONTH($C29,0))*SUMPRODUCT(('Rate Engine'!$G$17:$G$64=YEAR($C29)*12+MONTH($C29)-1)*'Rate Engine'!$H$17:$H$64,'Rate Engine'!$Q$17:$Q$64))/SUMPRODUCT('Rate Engine'!$H$17:$H$64,'Rate Engine'!$Q$17:$Q$64)) | Y29: =IF($C29="","",IF(AND($E29="taken",$G29<>"",$G29<>1),"achievement ignored — restate Filed %",""))
A30: ABD | B30: NC | C30: 46478 | D30: 0.04 | E30: planned | F30: N | G30: 1 | J30: =IF(OR($A30="",$B30=""),"",$A30&"|"&$B30) -> ABD|NC | K30: =IF($C30="","",$D30*IF($E30="planned",IF($G30="",1,$G30),1)) -> 0.04 | L30: =IF($C30="",0,IF(1+$K30>0,LN(1+$K30),0)) -> 0.039220713 | M30: =IF($C30="","",DATE(YEAR($C30),MONTH($C30),1)) -> 46478 | N30: =IF($C30="",0,EOMONTH($C30,0)-$C30+1) -> 30 | O30: =IF($C30="",0,COUNTIFS(rl_key,$J30,rl_effmonth,$M30,rl_eff,"<"&$C30)) -> 0 | P30: =IF($C30="",0,COUNTIFS($J$7:$J30,$J30,$M$7:$M30,$M30,$C$7:$C30,$C30)) -> 1 | Q30: =IF($C30="",0,IF(AND($O30=0,$P30=1),1,0)) -> 1 | R30: =IF($C30="",0,IF(COUNTIFS(rl_key,$J30,rl_effmonth,$M30)>1,1,0)) -> 0 | S30: =IF($C30="",0,COUNTIFS(rl_key,$J30,rl_eff,"<"&$C30)+COUNTIFS($J$7:$J30,$J30,$C$7:$C30,$C30)) -> 2 | T30: =IF(OR($C30="",$E30<>"planned",$C30<DATE(nr_PlanYear,1,1),$C30>DATE(nr_PlanYear,12,31)),0,IF(AND(COUNTIFS(rl_key,$J30,rl_status,"planned",rl_eff,">="&DATE(nr_PlanYear,1,1),rl_eff,"<"&$C30)=0,COUNTIFS($J$7:$J30,$J30,$E$7:$E30,"planned",$C$7:$C30,$C30)=1),1,0)) -> 1 | U30: =IF(OR($C30="",$E30<>"taken"),0,IF(AND(COUNTIFS(rl_key,$J30,rl_effmonth,$M30,rl_eff,"<"&$C30,rl_status,"taken")=0,COUNTIFS($J$7:$J30,$J30,$M$7:$M30,$M30,$C$7:$C30,$C30,$E$7:$E30,"taken")=1),1,0)) -> 0 | V30: =IF($J30="","",IF(COUNTIF(lr_key,$J30)=0,"not in tbl_LR",INDEX(calc_cylr_p,MATCH($J30,lr_key,0)))) -> 0.56447023 | W30: =IF(OR($J30="",COUNTIF(lr_key,$J30)=0),"",(INDEX(calc_cylr_p,MATCH($J30,lr_key,0))-INDEX(calc_lrcur,MATCH($J30,lr_key,0)))*100) -> -0.75297716 | X30: =IF(OR($C30="",$J30<>nr_SelKey),"",(SUMPRODUCT(('Rate Engine'!$G$17:$G$64>YEAR($C30)*12+MONTH($C30)-1)*'Rate Engine'!$H$17:$H$64,'Rate Engine'!$Q$17:$Q$64)+(EOMONTH($C30,0)-$C30+1)/DAY(EOMONTH($C30,0))*SUMPRODUCT(('Rate Engine'!$G$17:$G$64=YEAR($C30)*12+MONTH($C30)-1)*'Rate Engine'!$H$17:$H$64,'Rate Engine'!$Q$17:$Q$64))/SUMPRODUCT('Rate Engine'!$H$17:$H$64,'Rate Engine'!$Q$17:$Q$64)) | Y30: =IF($C30="","",IF(AND($E30="taken",$G30<>"",$G30<>1),"achievement ignored — restate Filed %",""))
A31: ABD | B31: PA | C31: 46113 | D31: 0.02 | E31: taken | F31: Y | J31: =IF(OR($A31="",$B31=""),"",$A31&"|"&$B31) -> ABD|PA | K31: =IF($C31="","",$D31*IF($E31="planned",IF($G31="",1,$G31),1)) -> 0.02 | L31: =IF($C31="",0,IF(1+$K31>0,LN(1+$K31),0)) -> 0.019802627 | M31: =IF($C31="","",DATE(YEAR($C31),MONTH($C31),1)) -> 46113 | N31: =IF($C31="",0,EOMONTH($C31,0)-$C31+1) -> 30 | O31: =IF($C31="",0,COUNTIFS(rl_key,$J31,rl_effmonth,$M31,rl_eff,"<"&$C31)) -> 0 | P31: =IF($C31="",0,COUNTIFS($J$7:$J31,$J31,$M$7:$M31,$M31,$C$7:$C31,$C31)) -> 1 | Q31: =IF($C31="",0,IF(AND($O31=0,$P31=1),1,0)) -> 1 | R31: =IF($C31="",0,IF(COUNTIFS(rl_key,$J31,rl_effmonth,$M31)>1,1,0)) -> 0 | S31: =IF($C31="",0,COUNTIFS(rl_key,$J31,rl_eff,"<"&$C31)+COUNTIFS($J$7:$J31,$J31,$C$7:$C31,$C31)) -> 1 | T31: =IF(OR($C31="",$E31<>"planned",$C31<DATE(nr_PlanYear,1,1),$C31>DATE(nr_PlanYear,12,31)),0,IF(AND(COUNTIFS(rl_key,$J31,rl_status,"planned",rl_eff,">="&DATE(nr_PlanYear,1,1),rl_eff,"<"&$C31)=0,COUNTIFS($J$7:$J31,$J31,$E$7:$E31,"planned",$C$7:$C31,$C31)=1),1,0)) -> 0 | U31: =IF(OR($C31="",$E31<>"taken"),0,IF(AND(COUNTIFS(rl_key,$J31,rl_effmonth,$M31,rl_eff,"<"&$C31,rl_status,"taken")=0,COUNTIFS($J$7:$J31,$J31,$M$7:$M31,$M31,$C$7:$C31,$C31,$E$7:$E31,"taken")=1),1,0)) -> 1 | V31: =IF($J31="","",IF(COUNTIF(lr_key,$J31)=0,"not in tbl_LR",INDEX(calc_cylr_p,MATCH($J31,lr_key,0)))) -> 0.58912522 | W31: =IF(OR($J31="",COUNTIF(lr_key,$J31)=0),"",(INDEX(calc_cylr_p,MATCH($J31,lr_key,0))-INDEX(calc_lrcur,MATCH($J31,lr_key,0)))*100) -> 0.51252218 | X31: =IF(OR($C31="",$J31<>nr_SelKey),"",(SUMPRODUCT(('Rate Engine'!$G$17:$G$64>YEAR($C31)*12+MONTH($C31)-1)*'Rate Engine'!$H$17:$H$64,'Rate Engine'!$Q$17:$Q$64)+(EOMONTH($C31,0)-$C31+1)/DAY(EOMONTH($C31,0))*SUMPRODUCT(('Rate Engine'!$G$17:$G$64=YEAR($C31)*12+MONTH($C31)-1)*'Rate Engine'!$H$17:$H$64,'Rate Engine'!$Q$17:$Q$64))/SUMPRODUCT('Rate Engine'!$H$17:$H$64,'Rate Engine'!$Q$17:$Q$64)) | Y31: =IF($C31="","",IF(AND($E31="taken",$G31<>"",$G31<>1),"achievement ignored — restate Filed %",""))
A32: ABD | B32: SC | C32: 46143 | D32: 0.03 | E32: taken | F32: Y | J32: =IF(OR($A32="",$B32=""),"",$A32&"|"&$B32) -> ABD|SC | K32: =IF($C32="","",$D32*IF($E32="planned",IF($G32="",1,$G32),1)) -> 0.03 | L32: =IF($C32="",0,IF(1+$K32>0,LN(1+$K32),0)) -> 0.029558802 | M32: =IF($C32="","",DATE(YEAR($C32),MONTH($C32),1)) -> 46143 | N32: =IF($C32="",0,EOMONTH($C32,0)-$C32+1) -> 31 | O32: =IF($C32="",0,COUNTIFS(rl_key,$J32,rl_effmonth,$M32,rl_eff,"<"&$C32)) -> 0 | P32: =IF($C32="",0,COUNTIFS($J$7:$J32,$J32,$M$7:$M32,$M32,$C$7:$C32,$C32)) -> 1 | Q32: =IF($C32="",0,IF(AND($O32=0,$P32=1),1,0)) -> 1 | R32: =IF($C32="",0,IF(COUNTIFS(rl_key,$J32,rl_effmonth,$M32)>1,1,0)) -> 0 | S32: =IF($C32="",0,COUNTIFS(rl_key,$J32,rl_eff,"<"&$C32)+COUNTIFS($J$7:$J32,$J32,$C$7:$C32,$C32)) -> 1 | T32: =IF(OR($C32="",$E32<>"planned",$C32<DATE(nr_PlanYear,1,1),$C32>DATE(nr_PlanYear,12,31)),0,IF(AND(COUNTIFS(rl_key,$J32,rl_status,"planned",rl_eff,">="&DATE(nr_PlanYear,1,1),rl_eff,"<"&$C32)=0,COUNTIFS($J$7:$J32,$J32,$E$7:$E32,"planned",$C$7:$C32,$C32)=1),1,0)) -> 0 | U32: =IF(OR($C32="",$E32<>"taken"),0,IF(AND(COUNTIFS(rl_key,$J32,rl_effmonth,$M32,rl_eff,"<"&$C32,rl_status,"taken")=0,COUNTIFS($J$7:$J32,$J32,$M$7:$M32,$M32,$C$7:$C32,$C32,$E$7:$E32,"taken")=1),1,0)) -> 1 | V32: =IF($J32="","",IF(COUNTIF(lr_key,$J32)=0,"not in tbl_LR",INDEX(calc_cylr_p,MATCH($J32,lr_key,0)))) -> 0.56924674 | W32: =IF(OR($J32="",COUNTIF(lr_key,$J32)=0),"",(INDEX(calc_cylr_p,MATCH($J32,lr_key,0))-INDEX(calc_lrcur,MATCH($J32,lr_key,0)))*100) -> 0.12467448 | X32: =IF(OR($C32="",$J32<>nr_SelKey),"",(SUMPRODUCT(('Rate Engine'!$G$17:$G$64>YEAR($C32)*12+MONTH($C32)-1)*'Rate Engine'!$H$17:$H$64,'Rate Engine'!$Q$17:$Q$64)+(EOMONTH($C32,0)-$C32+1)/DAY(EOMONTH($C32,0))*SUMPRODUCT(('Rate Engine'!$G$17:$G$64=YEAR($C32)*12+MONTH($C32)-1)*'Rate Engine'!$H$17:$H$64,'Rate Engine'!$Q$17:$Q$64))/SUMPRODUCT('Rate Engine'!$H$17:$H$64,'Rate Engine'!$Q$17:$Q$64)) | Y32: =IF($C32="","",IF(AND($E32="taken",$G32<>"",$G32<>1),"achievement ignored — restate Filed %",""))
A33: ABD | B33: TN | C33: 46600 | D33: 0.04 | E33: planned | F33: N | G33: 1 | J33: =IF(OR($A33="",$B33=""),"",$A33&"|"&$B33) -> ABD|TN | K33: =IF($C33="","",$D33*IF($E33="planned",IF($G33="",1,$G33),1)) -> 0.04 | L33: =IF($C33="",0,IF(1+$K33>0,LN(1+$K33),0)) -> 0.039220713 | M33: =IF($C33="","",DATE(YEAR($C33),MONTH($C33),1)) -> 46600 | N33: =IF($C33="",0,EOMONTH($C33,0)-$C33+1) -> 31 | O33: =IF($C33="",0,COUNTIFS(rl_key,$J33,rl_effmonth,$M33,rl_eff,"<"&$C33)) -> 0 | P33: =IF($C33="",0,COUNTIFS($J$7:$J33,$J33,$M$7:$M33,$M33,$C$7:$C33,$C33)) -> 1 | Q33: =IF($C33="",0,IF(AND($O33=0,$P33=1),1,0)) -> 1 | R33: =IF($C33="",0,IF(COUNTIFS(rl_key,$J33,rl_effmonth,$M33)>1,1,0)) -> 0 | S33: =IF($C33="",0,COUNTIFS(rl_key,$J33,rl_eff,"<"&$C33)+COUNTIFS($J$7:$J33,$J33,$C$7:$C33,$C33)) -> 1 | T33: =IF(OR($C33="",$E33<>"planned",$C33<DATE(nr_PlanYear,1,1),$C33>DATE(nr_PlanYear,12,31)),0,IF(AND(COUNTIFS(rl_key,$J33,rl_status,"planned",rl_eff,">="&DATE(nr_PlanYear,1,1),rl_eff,"<"&$C33)=0,COUNTIFS($J$7:$J33,$J33,$E$7:$E33,"planned",$C$7:$C33,$C33)=1),1,0)) -> 1 | U33: =IF(OR($C33="",$E33<>"taken"),0,IF(AND(COUNTIFS(rl_key,$J33,rl_effmonth,$M33,rl_eff,"<"&$C33,rl_status,"taken")=0,COUNTIFS($J$7:$J33,$J33,$M$7:$M33,$M33,$C$7:$C33,$C33,$E$7:$E33,"taken")=1),1,0)) -> 0 | V33: =IF($J33="","",IF(COUNTIF(lr_key,$J33)=0,"not in tbl_LR",INDEX(calc_cylr_p,MATCH($J33,lr_key,0)))) -> 0.59839394 | W33: =IF(OR($J33="",COUNTIF(lr_key,$J33)=0),"",(INDEX(calc_cylr_p,MATCH($J33,lr_key,0))-INDEX(calc_lrcur,MATCH($J33,lr_key,0)))*100) -> 0.23939371 | X33: =IF(OR($C33="",$J33<>nr_SelKey),"",(SUMPRODUCT(('Rate Engine'!$G$17:$G$64>YEAR($C33)*12+MONTH($C33)-1)*'Rate Engine'!$H$17:$H$64,'Rate Engine'!$Q$17:$Q$64)+(EOMONTH($C33,0)-$C33+1)/DAY(EOMONTH($C33,0))*SUMPRODUCT(('Rate Engine'!$G$17:$G$64=YEAR($C33)*12+MONTH($C33)-1)*'Rate Engine'!$H$17:$H$64,'Rate Engine'!$Q$17:$Q$64))/SUMPRODUCT('Rate Engine'!$H$17:$H$64,'Rate Engine'!$Q$17:$Q$64)) | Y33: =IF($C33="","",IF(AND($E33="taken",$G33<>"",$G33<>1),"achievement ignored — restate Filed %",""))
A34: ABD | B34: VA | C34: 46204 | D34: 0.05 | E34: taken | F34: Y | J34: =IF(OR($A34="",$B34=""),"",$A34&"|"&$B34) -> ABD|VA | K34: =IF($C34="","",$D34*IF($E34="planned",IF($G34="",1,$G34),1)) -> 0.05 | L34: =IF($C34="",0,IF(1+$K34>0,LN(1+$K34),0)) -> 0.048790164 | M34: =IF($C34="","",DATE(YEAR($C34),MONTH($C34),1)) -> 46204 | N34: =IF($C34="",0,EOMONTH($C34,0)-$C34+1) -> 31 | O34: =IF($C34="",0,COUNTIFS(rl_key,$J34,rl_effmonth,$M34,rl_eff,"<"&$C34)) -> 0 | P34: =IF($C34="",0,COUNTIFS($J$7:$J34,$J34,$M$7:$M34,$M34,$C$7:$C34,$C34)) -> 1 | Q34: =IF($C34="",0,IF(AND($O34=0,$P34=1),1,0)) -> 1 | R34: =IF($C34="",0,IF(COUNTIFS(rl_key,$J34,rl_effmonth,$M34)>1,1,0)) -> 0 | S34: =IF($C34="",0,COUNTIFS(rl_key,$J34,rl_eff,"<"&$C34)+COUNTIFS($J$7:$J34,$J34,$C$7:$C34,$C34)) -> 1 | T34: =IF(OR($C34="",$E34<>"planned",$C34<DATE(nr_PlanYear,1,1),$C34>DATE(nr_PlanYear,12,31)),0,IF(AND(COUNTIFS(rl_key,$J34,rl_status,"planned",rl_eff,">="&DATE(nr_PlanYear,1,1),rl_eff,"<"&$C34)=0,COUNTIFS($J$7:$J34,$J34,$E$7:$E34,"planned",$C$7:$C34,$C34)=1),1,0)) -> 0 | U34: =IF(OR($C34="",$E34<>"taken"),0,IF(AND(COUNTIFS(rl_key,$J34,rl_effmonth,$M34,rl_eff,"<"&$C34,rl_status,"taken")=0,COUNTIFS($J$7:$J34,$J34,$M$7:$M34,$M34,$C$7:$C34,$C34,$E$7:$E34,"taken")=1),1,0)) -> 1 | V34: =IF($J34="","",IF(COUNTIF(lr_key,$J34)=0,"not in tbl_LR",INDEX(calc_cylr_p,MATCH($J34,lr_key,0)))) -> 0.58253988 | W34: =IF(OR($J34="",COUNTIF(lr_key,$J34)=0),"",(INDEX(calc_cylr_p,MATCH($J34,lr_key,0))-INDEX(calc_lrcur,MATCH($J34,lr_key,0)))*100) -> 0.2539883 | X34: =IF(OR($C34="",$J34<>nr_SelKey),"",(SUMPRODUCT(('Rate Engine'!$G$17:$G$64>YEAR($C34)*12+MONTH($C34)-1)*'Rate Engine'!$H$17:$H$64,'Rate Engine'!$Q$17:$Q$64)+(EOMONTH($C34,0)-$C34+1)/DAY(EOMONTH($C34,0))*SUMPRODUCT(('Rate Engine'!$G$17:$G$64=YEAR($C34)*12+MONTH($C34)-1)*'Rate Engine'!$H$17:$H$64,'Rate Engine'!$Q$17:$Q$64))/SUMPRODUCT('Rate Engine'!$H$17:$H$64,'Rate Engine'!$Q$17:$Q$64)) | Y34: =IF($C34="","",IF(AND($E34="taken",$G34<>"",$G34<>1),"achievement ignored — restate Filed %",""))
A35: ABD | B35: WV | C35: 46235 | D35: 0.06 | E35: taken | F35: Y | J35: =IF(OR($A35="",$B35=""),"",$A35&"|"&$B35) -> ABD|WV | K35: =IF($C35="","",$D35*IF($E35="planned",IF($G35="",1,$G35),1)) -> 0.06 | L35: =IF($C35="",0,IF(1+$K35>0,LN(1+$K35),0)) -> 0.058268908 | M35: =IF($C35="","",DATE(YEAR($C35),MONTH($C35),1)) -> 46235 | N35: =IF($C35="",0,EOMONTH($C35,0)-$C35+1) -> 31 | O35: =IF($C35="",0,COUNTIFS(rl_key,$J35,rl_effmonth,$M35,rl_eff,"<"&$C35)) -> 0 | P35: =IF($C35="",0,COUNTIFS($J$7:$J35,$J35,$M$7:$M35,$M35,$C$7:$C35,$C35)) -> 1 | Q35: =IF($C35="",0,IF(AND($O35=0,$P35=1),1,0)) -> 1 | R35: =IF($C35="",0,IF(COUNTIFS(rl_key,$J35,rl_effmonth,$M35)>1,1,0)) -> 0 | S35: =IF($C35="",0,COUNTIFS(rl_key,$J35,rl_eff,"<"&$C35)+COUNTIFS($J$7:$J35,$J35,$C$7:$C35,$C35)) -> 1 | T35: =IF(OR($C35="",$E35<>"planned",$C35<DATE(nr_PlanYear,1,1),$C35>DATE(nr_PlanYear,12,31)),0,IF(AND(COUNTIFS(rl_key,$J35,rl_status,"planned",rl_eff,">="&DATE(nr_PlanYear,1,1),rl_eff,"<"&$C35)=0,COUNTIFS($J$7:$J35,$J35,$E$7:$E35,"planned",$C$7:$C35,$C35)=1),1,0)) -> 0 | U35: =IF(OR($C35="",$E35<>"taken"),0,IF(AND(COUNTIFS(rl_key,$J35,rl_effmonth,$M35,rl_eff,"<"&$C35,rl_status,"taken")=0,COUNTIFS($J$7:$J35,$J35,$M$7:$M35,$M35,$C$7:$C35,$C35,$E$7:$E35,"taken")=1),1,0)) -> 1 | V35: =IF($J35="","",IF(COUNTIF(lr_key,$J35)=0,"not in tbl_LR",INDEX(calc_cylr_p,MATCH($J35,lr_key,0)))) -> 0.57167611 | W35: =IF(OR($J35="",COUNTIF(lr_key,$J35)=0),"",(INDEX(calc_cylr_p,MATCH($J35,lr_key,0))-INDEX(calc_lrcur,MATCH($J35,lr_key,0)))*100) -> 0.76761073 | X35: =IF(OR($C35="",$J35<>nr_SelKey),"",(SUMPRODUCT(('Rate Engine'!$G$17:$G$64>YEAR($C35)*12+MONTH($C35)-1)*'Rate Engine'!$H$17:$H$64,'Rate Engine'!$Q$17:$Q$64)+(EOMONTH($C35,0)-$C35+1)/DAY(EOMONTH($C35,0))*SUMPRODUCT(('Rate Engine'!$G$17:$G$64=YEAR($C35)*12+MONTH($C35)-1)*'Rate Engine'!$H$17:$H$64,'Rate Engine'!$Q$17:$Q$64))/SUMPRODUCT('Rate Engine'!$H$17:$H$64,'Rate Engine'!$Q$17:$Q$64)) | Y35: =IF($C35="","",IF(AND($E35="taken",$G35<>"",$G35<>1),"achievement ignored — restate Filed %",""))
A36: MM | B36: AZ | C36: 46296 | D36: 0.03 | E36: taken | F36: Y | J36: =IF(OR($A36="",$B36=""),"",$A36&"|"&$B36) -> MM|AZ | K36: =IF($C36="","",$D36*IF($E36="planned",IF($G36="",1,$G36),1)) -> 0.03 | L36: =IF($C36="",0,IF(1+$K36>0,LN(1+$K36),0)) -> 0.029558802 | M36: =IF($C36="","",DATE(YEAR($C36),MONTH($C36),1)) -> 46296 | N36: =IF($C36="",0,EOMONTH($C36,0)-$C36+1) -> 31 | O36: =IF($C36="",0,COUNTIFS(rl_key,$J36,rl_effmonth,$M36,rl_eff,"<"&$C36)) -> 0 | P36: =IF($C36="",0,COUNTIFS($J$7:$J36,$J36,$M$7:$M36,$M36,$C$7:$C36,$C36)) -> 1 | Q36: =IF($C36="",0,IF(AND($O36=0,$P36=1),1,0)) -> 1 | R36: =IF($C36="",0,IF(COUNTIFS(rl_key,$J36,rl_effmonth,$M36)>1,1,0)) -> 0 | S36: =IF($C36="",0,COUNTIFS(rl_key,$J36,rl_eff,"<"&$C36)+COUNTIFS($J$7:$J36,$J36,$C$7:$C36,$C36)) -> 1 | T36: =IF(OR($C36="",$E36<>"planned",$C36<DATE(nr_PlanYear,1,1),$C36>DATE(nr_PlanYear,12,31)),0,IF(AND(COUNTIFS(rl_key,$J36,rl_status,"planned",rl_eff,">="&DATE(nr_PlanYear,1,1),rl_eff,"<"&$C36)=0,COUNTIFS($J$7:$J36,$J36,$E$7:$E36,"planned",$C$7:$C36,$C36)=1),1,0)) -> 0 | U36: =IF(OR($C36="",$E36<>"taken"),0,IF(AND(COUNTIFS(rl_key,$J36,rl_effmonth,$M36,rl_eff,"<"&$C36,rl_status,"taken")=0,COUNTIFS($J$7:$J36,$J36,$M$7:$M36,$M36,$C$7:$C36,$C36,$E$7:$E36,"taken")=1),1,0)) -> 1 | V36: =IF($J36="","",IF(COUNTIF(lr_key,$J36)=0,"not in tbl_LR",INDEX(calc_cylr_p,MATCH($J36,lr_key,0)))) -> 0.57071568 | W36: =IF(OR($J36="",COUNTIF(lr_key,$J36)=0),"",(INDEX(calc_cylr_p,MATCH($J36,lr_key,0))-INDEX(calc_lrcur,MATCH($J36,lr_key,0)))*100) -> -0.52843248 | X36: =IF(OR($C36="",$J36<>nr_SelKey),"",(SUMPRODUCT(('Rate Engine'!$G$17:$G$64>YEAR($C36)*12+MONTH($C36)-1)*'Rate Engine'!$H$17:$H$64,'Rate Engine'!$Q$17:$Q$64)+(EOMONTH($C36,0)-$C36+1)/DAY(EOMONTH($C36,0))*SUMPRODUCT(('Rate Engine'!$G$17:$G$64=YEAR($C36)*12+MONTH($C36)-1)*'Rate Engine'!$H$17:$H$64,'Rate Engine'!$Q$17:$Q$64))/SUMPRODUCT('Rate Engine'!$H$17:$H$64,'Rate Engine'!$Q$17:$Q$64)) | Y36: =IF($C36="","",IF(AND($E36="taken",$G36<>"",$G36<>1),"achievement ignored — restate Filed %",""))
A37: MM | B37: AZ | C37: 46419 | D37: 0.04 | E37: planned | F37: N | G37: 1 | J37: =IF(OR($A37="",$B37=""),"",$A37&"|"&$B37) -> MM|AZ | K37: =IF($C37="","",$D37*IF($E37="planned",IF($G37="",1,$G37),1)) -> 0.04 | L37: =IF($C37="",0,IF(1+$K37>0,LN(1+$K37),0)) -> 0.039220713 | M37: =IF($C37="","",DATE(YEAR($C37),MONTH($C37),1)) -> 46419 | N37: =IF($C37="",0,EOMONTH($C37,0)-$C37+1) -> 28 | O37: =IF($C37="",0,COUNTIFS(rl_key,$J37,rl_effmonth,$M37,rl_eff,"<"&$C37)) -> 0 | P37: =IF($C37="",0,COUNTIFS($J$7:$J37,$J37,$M$7:$M37,$M37,$C$7:$C37,$C37)) -> 1 | Q37: =IF($C37="",0,IF(AND($O37=0,$P37=1),1,0)) -> 1 | R37: =IF($C37="",0,IF(COUNTIFS(rl_key,$J37,rl_effmonth,$M37)>1,1,0)) -> 0 | S37: =IF($C37="",0,COUNTIFS(rl_key,$J37,rl_eff,"<"&$C37)+COUNTIFS($J$7:$J37,$J37,$C$7:$C37,$C37)) -> 2 | T37: =IF(OR($C37="",$E37<>"planned",$C37<DATE(nr_PlanYear,1,1),$C37>DATE(nr_PlanYear,12,31)),0,IF(AND(COUNTIFS(rl_key,$J37,rl_status,"planned",rl_eff,">="&DATE(nr_PlanYear,1,1),rl_eff,"<"&$C37)=0,COUNTIFS($J$7:$J37,$J37,$E$7:$E37,"planned",$C$7:$C37,$C37)=1),1,0)) -> 1 | U37: =IF(OR($C37="",$E37<>"taken"),0,IF(AND(COUNTIFS(rl_key,$J37,rl_effmonth,$M37,rl_eff,"<"&$C37,rl_status,"taken")=0,COUNTIFS($J$7:$J37,$J37,$M$7:$M37,$M37,$C$7:$C37,$C37,$E$7:$E37,"taken")=1),1,0)) -> 0 | V37: =IF($J37="","",IF(COUNTIF(lr_key,$J37)=0,"not in tbl_LR",INDEX(calc_cylr_p,MATCH($J37,lr_key,0)))) -> 0.57071568 | W37: =IF(OR($J37="",COUNTIF(lr_key,$J37)=0),"",(INDEX(calc_cylr_p,MATCH($J37,lr_key,0))-INDEX(calc_lrcur,MATCH($J37,lr_key,0)))*100) -> -0.52843248 | X37: =IF(OR($C37="",$J37<>nr_SelKey),"",(SUMPRODUCT(('Rate Engine'!$G$17:$G$64>YEAR($C37)*12+MONTH($C37)-1)*'Rate Engine'!$H$17:$H$64,'Rate Engine'!$Q$17:$Q$64)+(EOMONTH($C37,0)-$C37+1)/DAY(EOMONTH($C37,0))*SUMPRODUCT(('Rate Engine'!$G$17:$G$64=YEAR($C37)*12+MONTH($C37)-1)*'Rate Engine'!$H$17:$H$64,'Rate Engine'!$Q$17:$Q$64))/SUMPRODUCT('Rate Engine'!$H$17:$H$64,'Rate Engine'!$Q$17:$Q$64)) | Y37: =IF($C37="","",IF(AND($E37="taken",$G37<>"",$G37<>1),"achievement ignored — restate Filed %",""))
A38: MM | B38: CO | C38: 46327 | D38: 0.04 | E38: taken | F38: Y | J38: =IF(OR($A38="",$B38=""),"",$A38&"|"&$B38) -> MM|CO | K38: =IF($C38="","",$D38*IF($E38="planned",IF($G38="",1,$G38),1)) -> 0.04 | L38: =IF($C38="",0,IF(1+$K38>0,LN(1+$K38),0)) -> 0.039220713 | M38: =IF($C38="","",DATE(YEAR($C38),MONTH($C38),1)) -> 46327 | N38: =IF($C38="",0,EOMONTH($C38,0)-$C38+1) -> 30 | O38: =IF($C38="",0,COUNTIFS(rl_key,$J38,rl_effmonth,$M38,rl_eff,"<"&$C38)) -> 0 | P38: =IF($C38="",0,COUNTIFS($J$7:$J38,$J38,$M$7:$M38,$M38,$C$7:$C38,$C38)) -> 1 | Q38: =IF($C38="",0,IF(AND($O38=0,$P38=1),1,0)) -> 1 | R38: =IF($C38="",0,IF(COUNTIFS(rl_key,$J38,rl_effmonth,$M38)>1,1,0)) -> 0 | S38: =IF($C38="",0,COUNTIFS(rl_key,$J38,rl_eff,"<"&$C38)+COUNTIFS($J$7:$J38,$J38,$C$7:$C38,$C38)) -> 1 | T38: =IF(OR($C38="",$E38<>"planned",$C38<DATE(nr_PlanYear,1,1),$C38>DATE(nr_PlanYear,12,31)),0,IF(AND(COUNTIFS(rl_key,$J38,rl_status,"planned",rl_eff,">="&DATE(nr_PlanYear,1,1),rl_eff,"<"&$C38)=0,COUNTIFS($J$7:$J38,$J38,$E$7:$E38,"planned",$C$7:$C38,$C38)=1),1,0)) -> 0 | U38: =IF(OR($C38="",$E38<>"taken"),0,IF(AND(COUNTIFS(rl_key,$J38,rl_effmonth,$M38,rl_eff,"<"&$C38,rl_status,"taken")=0,COUNTIFS($J$7:$J38,$J38,$M$7:$M38,$M38,$C$7:$C38,$C38,$E$7:$E38,"taken")=1),1,0)) -> 1 | V38: =IF($J38="","",IF(COUNTIF(lr_key,$J38)=0,"not in tbl_LR",INDEX(calc_cylr_p,MATCH($J38,lr_key,0)))) -> 0.61272625 | W38: =IF(OR($J38="",COUNTIF(lr_key,$J38)=0),"",(INDEX(calc_cylr_p,MATCH($J38,lr_key,0))-INDEX(calc_lrcur,MATCH($J38,lr_key,0)))*100) -> 0.79262522 | X38: =IF(OR($C38="",$J38<>nr_SelKey),"",(SUMPRODUCT(('Rate Engine'!$G$17:$G$64>YEAR($C38)*12+MONTH($C38)-1)*'Rate Engine'!$H$17:$H$64,'Rate Engine'!$Q$17:$Q$64)+(EOMONTH($C38,0)-$C38+1)/DAY(EOMONTH($C38,0))*SUMPRODUCT(('Rate Engine'!$G$17:$G$64=YEAR($C38)*12+MONTH($C38)-1)*'Rate Engine'!$H$17:$H$64,'Rate Engine'!$Q$17:$Q$64))/SUMPRODUCT('Rate Engine'!$H$17:$H$64,'Rate Engine'!$Q$17:$Q$64)) | Y38: =IF($C38="","",IF(AND($E38="taken",$G38<>"",$G38<>1),"achievement ignored — restate Filed %",""))
A39: MM | B39: GA | C39: 46054 | D39: 0.02 | E39: taken | F39: Y | J39: =IF(OR($A39="",$B39=""),"",$A39&"|"&$B39) -> MM|GA | K39: =IF($C39="","",$D39*IF($E39="planned",IF($G39="",1,$G39),1)) -> 0.02 | L39: =IF($C39="",0,IF(1+$K39>0,LN(1+$K39),0)) -> 0.019802627 | M39: =IF($C39="","",DATE(YEAR($C39),MONTH($C39),1)) -> 46054 | N39: =IF($C39="",0,EOMONTH($C39,0)-$C39+1) -> 28 | O39: =IF($C39="",0,COUNTIFS(rl_key,$J39,rl_effmonth,$M39,rl_eff,"<"&$C39)) -> 0 | P39: =IF($C39="",0,COUNTIFS($J$7:$J39,$J39,$M$7:$M39,$M39,$C$7:$C39,$C39)) -> 1 | Q39: =IF($C39="",0,IF(AND($O39=0,$P39=1),1,0)) -> 1 | R39: =IF($C39="",0,IF(COUNTIFS(rl_key,$J39,rl_effmonth,$M39)>1,1,0)) -> 0 | S39: =IF($C39="",0,COUNTIFS(rl_key,$J39,rl_eff,"<"&$C39)+COUNTIFS($J$7:$J39,$J39,$C$7:$C39,$C39)) -> 1 | T39: =IF(OR($C39="",$E39<>"planned",$C39<DATE(nr_PlanYear,1,1),$C39>DATE(nr_PlanYear,12,31)),0,IF(AND(COUNTIFS(rl_key,$J39,rl_status,"planned",rl_eff,">="&DATE(nr_PlanYear,1,1),rl_eff,"<"&$C39)=0,COUNTIFS($J$7:$J39,$J39,$E$7:$E39,"planned",$C$7:$C39,$C39)=1),1,0)) -> 0 | U39: =IF(OR($C39="",$E39<>"taken"),0,IF(AND(COUNTIFS(rl_key,$J39,rl_effmonth,$M39,rl_eff,"<"&$C39,rl_status,"taken")=0,COUNTIFS($J$7:$J39,$J39,$M$7:$M39,$M39,$C$7:$C39,$C39,$E$7:$E39,"taken")=1),1,0)) -> 1 | V39: =IF($J39="","",IF(COUNTIF(lr_key,$J39)=0,"not in tbl_LR",INDEX(calc_cylr_p,MATCH($J39,lr_key,0)))) -> 0.59469816 | W39: =IF(OR($J39="",COUNTIF(lr_key,$J39)=0),"",(INDEX(calc_cylr_p,MATCH($J39,lr_key,0))-INDEX(calc_lrcur,MATCH($J39,lr_key,0)))*100) -> -0.53018435 | X39: =IF(OR($C39="",$J39<>nr_SelKey),"",(SUMPRODUCT(('Rate Engine'!$G$17:$G$64>YEAR($C39)*12+MONTH($C39)-1)*'Rate Engine'!$H$17:$H$64,'Rate Engine'!$Q$17:$Q$64)+(EOMONTH($C39,0)-$C39+1)/DAY(EOMONTH($C39,0))*SUMPRODUCT(('Rate Engine'!$G$17:$G$64=YEAR($C39)*12+MONTH($C39)-1)*'Rate Engine'!$H$17:$H$64,'Rate Engine'!$Q$17:$Q$64))/SUMPRODUCT('Rate Engine'!$H$17:$H$64,'Rate Engine'!$Q$17:$Q$64)) | Y39: =IF($C39="","",IF(AND($E39="taken",$G39<>"",$G39<>1),"achievement ignored — restate Filed %",""))
A40: MM | B40: GA | C40: 46539 | D40: 0.04 | E40: planned | F40: N | G40: 1 | J40: =IF(OR($A40="",$B40=""),"",$A40&"|"&$B40) -> MM|GA | K40: =IF($C40="","",$D40*IF($E40="planned",IF($G40="",1,$G40),1)) -> 0.04 | L40: =IF($C40="",0,IF(1+$K40>0,LN(1+$K40),0)) -> 0.039220713 | M40: =IF($C40="","",DATE(YEAR($C40),MONTH($C40),1)) -> 46539 | N40: =IF($C40="",0,EOMONTH($C40,0)-$C40+1) -> 30 | O40: =IF($C40="",0,COUNTIFS(rl_key,$J40,rl_effmonth,$M40,rl_eff,"<"&$C40)) -> 0 | P40: =IF($C40="",0,COUNTIFS($J$7:$J40,$J40,$M$7:$M40,$M40,$C$7:$C40,$C40)) -> 1 | Q40: =IF($C40="",0,IF(AND($O40=0,$P40=1),1,0)) -> 1 | R40: =IF($C40="",0,IF(COUNTIFS(rl_key,$J40,rl_effmonth,$M40)>1,1,0)) -> 0 | S40: =IF($C40="",0,COUNTIFS(rl_key,$J40,rl_eff,"<"&$C40)+COUNTIFS($J$7:$J40,$J40,$C$7:$C40,$C40)) -> 2 | T40: =IF(OR($C40="",$E40<>"planned",$C40<DATE(nr_PlanYear,1,1),$C40>DATE(nr_PlanYear,12,31)),0,IF(AND(COUNTIFS(rl_key,$J40,rl_status,"planned",rl_eff,">="&DATE(nr_PlanYear,1,1),rl_eff,"<"&$C40)=0,COUNTIFS($J$7:$J40,$J40,$E$7:$E40,"planned",$C$7:$C40,$C40)=1),1,0)) -> 1 | U40: =IF(OR($C40="",$E40<>"taken"),0,IF(AND(COUNTIFS(rl_key,$J40,rl_effmonth,$M40,rl_eff,"<"&$C40,rl_status,"taken")=0,COUNTIFS($J$7:$J40,$J40,$M$7:$M40,$M40,$C$7:$C40,$C40,$E$7:$E40,"taken")=1),1,0)) -> 0 | V40: =IF($J40="","",IF(COUNTIF(lr_key,$J40)=0,"not in tbl_LR",INDEX(calc_cylr_p,MATCH($J40,lr_key,0)))) -> 0.59469816 | W40: =IF(OR($J40="",COUNTIF(lr_key,$J40)=0),"",(INDEX(calc_cylr_p,MATCH($J40,lr_key,0))-INDEX(calc_lrcur,MATCH($J40,lr_key,0)))*100) -> -0.53018435 | X40: =IF(OR($C40="",$J40<>nr_SelKey),"",(SUMPRODUCT(('Rate Engine'!$G$17:$G$64>YEAR($C40)*12+MONTH($C40)-1)*'Rate Engine'!$H$17:$H$64,'Rate Engine'!$Q$17:$Q$64)+(EOMONTH($C40,0)-$C40+1)/DAY(EOMONTH($C40,0))*SUMPRODUCT(('Rate Engine'!$G$17:$G$64=YEAR($C40)*12+MONTH($C40)-1)*'Rate Engine'!$H$17:$H$64,'Rate Engine'!$Q$17:$Q$64))/SUMPRODUCT('Rate Engine'!$H$17:$H$64,'Rate Engine'!$Q$17:$Q$64)) | Y40: =IF($C40="","",IF(AND($E40="taken",$G40<>"",$G40<>1),"achievement ignored — restate Filed %",""))
A41: MM | B41: IL | C41: 46113 | D41: 0.04 | E41: taken | F41: Y | J41: =IF(OR($A41="",$B41=""),"",$A41&"|"&$B41) -> MM|IL | K41: =IF($C41="","",$D41*IF($E41="planned",IF($G41="",1,$G41),1)) -> 0.04 | L41: =IF($C41="",0,IF(1+$K41>0,LN(1+$K41),0)) -> 0.039220713 | M41: =IF($C41="","",DATE(YEAR($C41),MONTH($C41),1)) -> 46113 | N41: =IF($C41="",0,EOMONTH($C41,0)-$C41+1) -> 30 | O41: =IF($C41="",0,COUNTIFS(rl_key,$J41,rl_effmonth,$M41,rl_eff,"<"&$C41)) -> 0 | P41: =IF($C41="",0,COUNTIFS($J$7:$J41,$J41,$M$7:$M41,$M41,$C$7:$C41,$C41)) -> 1 | Q41: =IF($C41="",0,IF(AND($O41=0,$P41=1),1,0)) -> 1 | R41: =IF($C41="",0,IF(COUNTIFS(rl_key,$J41,rl_effmonth,$M41)>1,1,0)) -> 0 | S41: =IF($C41="",0,COUNTIFS(rl_key,$J41,rl_eff,"<"&$C41)+COUNTIFS($J$7:$J41,$J41,$C$7:$C41,$C41)) -> 1 | T41: =IF(OR($C41="",$E41<>"planned",$C41<DATE(nr_PlanYear,1,1),$C41>DATE(nr_PlanYear,12,31)),0,IF(AND(COUNTIFS(rl_key,$J41,rl_status,"planned",rl_eff,">="&DATE(nr_PlanYear,1,1),rl_eff,"<"&$C41)=0,COUNTIFS($J$7:$J41,$J41,$E$7:$E41,"planned",$C$7:$C41,$C41)=1),1,0)) -> 0 | U41: =IF(OR($C41="",$E41<>"taken"),0,IF(AND(COUNTIFS(rl_key,$J41,rl_effmonth,$M41,rl_eff,"<"&$C41,rl_status,"taken")=0,COUNTIFS($J$7:$J41,$J41,$M$7:$M41,$M41,$C$7:$C41,$C41,$E$7:$E41,"taken")=1),1,0)) -> 1 | V41: =IF($J41="","",IF(COUNTIF(lr_key,$J41)=0,"not in tbl_LR",INDEX(calc_cylr_p,MATCH($J41,lr_key,0)))) -> 0.57173334 | W41: =IF(OR($J41="",COUNTIF(lr_key,$J41)=0),"",(INDEX(calc_cylr_p,MATCH($J41,lr_key,0))-INDEX(calc_lrcur,MATCH($J41,lr_key,0)))*100) -> 0.37333418 | X41: =IF(OR($C41="",$J41<>nr_SelKey),"",(SUMPRODUCT(('Rate Engine'!$G$17:$G$64>YEAR($C41)*12+MONTH($C41)-1)*'Rate Engine'!$H$17:$H$64,'Rate Engine'!$Q$17:$Q$64)+(EOMONTH($C41,0)-$C41+1)/DAY(EOMONTH($C41,0))*SUMPRODUCT(('Rate Engine'!$G$17:$G$64=YEAR($C41)*12+MONTH($C41)-1)*'Rate Engine'!$H$17:$H$64,'Rate Engine'!$Q$17:$Q$64))/SUMPRODUCT('Rate Engine'!$H$17:$H$64,'Rate Engine'!$Q$17:$Q$64)) | Y41: =IF($C41="","",IF(AND($E41="taken",$G41<>"",$G41<>1),"achievement ignored — restate Filed %",""))
A42: MM | B42: IN | C42: 46143 | D42: 0.05 | E42: taken | F42: Y | J42: =IF(OR($A42="",$B42=""),"",$A42&"|"&$B42) -> MM|IN | K42: =IF($C42="","",$D42*IF($E42="planned",IF($G42="",1,$G42),1)) -> 0.05 | L42: =IF($C42="",0,IF(1+$K42>0,LN(1+$K42),0)) -> 0.048790164 | M42: =IF($C42="","",DATE(YEAR($C42),MONTH($C42),1)) -> 46143 | N42: =IF($C42="",0,EOMONTH($C42,0)-$C42+1) -> 31 | O42: =IF($C42="",0,COUNTIFS(rl_key,$J42,rl_effmonth,$M42,rl_eff,"<"&$C42)) -> 0 | P42: =IF($C42="",0,COUNTIFS($J$7:$J42,$J42,$M$7:$M42,$M42,$C$7:$C42,$C42)) -> 1 | Q42: =IF($C42="",0,IF(AND($O42=0,$P42=1),1,0)) -> 1 | R42: =IF($C42="",0,IF(COUNTIFS(rl_key,$J42,rl_effmonth,$M42)>1,1,0)) -> 0 | S42: =IF($C42="",0,COUNTIFS(rl_key,$J42,rl_eff,"<"&$C42)+COUNTIFS($J$7:$J42,$J42,$C$7:$C42,$C42)) -> 1 | T42: =IF(OR($C42="",$E42<>"planned",$C42<DATE(nr_PlanYear,1,1),$C42>DATE(nr_PlanYear,12,31)),0,IF(AND(COUNTIFS(rl_key,$J42,rl_status,"planned",rl_eff,">="&DATE(nr_PlanYear,1,1),rl_eff,"<"&$C42)=0,COUNTIFS($J$7:$J42,$J42,$E$7:$E42,"planned",$C$7:$C42,$C42)=1),1,0)) -> 0 | U42: =IF(OR($C42="",$E42<>"taken"),0,IF(AND(COUNTIFS(rl_key,$J42,rl_effmonth,$M42,rl_eff,"<"&$C42,rl_status,"taken")=0,COUNTIFS($J$7:$J42,$J42,$M$7:$M42,$M42,$C$7:$C42,$C42,$E$7:$E42,"taken")=1),1,0)) -> 1 | V42: =IF($J42="","",IF(COUNTIF(lr_key,$J42)=0,"not in tbl_LR",INDEX(calc_cylr_p,MATCH($J42,lr_key,0)))) -> 0.60520472 | W42: =IF(OR($J42="",COUNTIF(lr_key,$J42)=0),"",(INDEX(calc_cylr_p,MATCH($J42,lr_key,0))-INDEX(calc_lrcur,MATCH($J42,lr_key,0)))*100) -> 0.92047189 | X42: =IF(OR($C42="",$J42<>nr_SelKey),"",(SUMPRODUCT(('Rate Engine'!$G$17:$G$64>YEAR($C42)*12+MONTH($C42)-1)*'Rate Engine'!$H$17:$H$64,'Rate Engine'!$Q$17:$Q$64)+(EOMONTH($C42,0)-$C42+1)/DAY(EOMONTH($C42,0))*SUMPRODUCT(('Rate Engine'!$G$17:$G$64=YEAR($C42)*12+MONTH($C42)-1)*'Rate Engine'!$H$17:$H$64,'Rate Engine'!$Q$17:$Q$64))/SUMPRODUCT('Rate Engine'!$H$17:$H$64,'Rate Engine'!$Q$17:$Q$64)) | Y42: =IF($C42="","",IF(AND($E42="taken",$G42<>"",$G42<>1),"achievement ignored — restate Filed %",""))
A43: MM | B43: KY | C43: 46661 | D43: 0.04 | E43: planned | F43: N | G43: 1 | J43: =IF(OR($A43="",$B43=""),"",$A43&"|"&$B43) -> MM|KY | K43: =IF($C43="","",$D43*IF($E43="planned",IF($G43="",1,$G43),1)) -> 0.04 | L43: =IF($C43="",0,IF(1+$K43>0,LN(1+$K43),0)) -> 0.039220713 | M43: =IF($C43="","",DATE(YEAR($C43),MONTH($C43),1)) -> 46661 | N43: =IF($C43="",0,EOMONTH($C43,0)-$C43+1) -> 31 | O43: =IF($C43="",0,COUNTIFS(rl_key,$J43,rl_effmonth,$M43,rl_eff,"<"&$C43)) -> 0 | P43: =IF($C43="",0,COUNTIFS($J$7:$J43,$J43,$M$7:$M43,$M43,$C$7:$C43,$C43)) -> 1 | Q43: =IF($C43="",0,IF(AND($O43=0,$P43=1),1,0)) -> 1 | R43: =IF($C43="",0,IF(COUNTIFS(rl_key,$J43,rl_effmonth,$M43)>1,1,0)) -> 0 | S43: =IF($C43="",0,COUNTIFS(rl_key,$J43,rl_eff,"<"&$C43)+COUNTIFS($J$7:$J43,$J43,$C$7:$C43,$C43)) -> 1 | T43: =IF(OR($C43="",$E43<>"planned",$C43<DATE(nr_PlanYear,1,1),$C43>DATE(nr_PlanYear,12,31)),0,IF(AND(COUNTIFS(rl_key,$J43,rl_status,"planned",rl_eff,">="&DATE(nr_PlanYear,1,1),rl_eff,"<"&$C43)=0,COUNTIFS($J$7:$J43,$J43,$E$7:$E43,"planned",$C$7:$C43,$C43)=1),1,0)) -> 1 | U43: =IF(OR($C43="",$E43<>"taken"),0,IF(AND(COUNTIFS(rl_key,$J43,rl_effmonth,$M43,rl_eff,"<"&$C43,rl_status,"taken")=0,COUNTIFS($J$7:$J43,$J43,$M$7:$M43,$M43,$C$7:$C43,$C43,$E$7:$E43,"taken")=1),1,0)) -> 0 | V43: =IF($J43="","",IF(COUNTIF(lr_key,$J43)=0,"not in tbl_LR",INDEX(calc_cylr_p,MATCH($J43,lr_key,0)))) -> 0.58363104 | W43: =IF(OR($J43="",COUNTIF(lr_key,$J43)=0),"",(INDEX(calc_cylr_p,MATCH($J43,lr_key,0))-INDEX(calc_lrcur,MATCH($J43,lr_key,0)))*100) -> 0.36310399 | X43: =IF(OR($C43="",$J43<>nr_SelKey),"",(SUMPRODUCT(('Rate Engine'!$G$17:$G$64>YEAR($C43)*12+MONTH($C43)-1)*'Rate Engine'!$H$17:$H$64,'Rate Engine'!$Q$17:$Q$64)+(EOMONTH($C43,0)-$C43+1)/DAY(EOMONTH($C43,0))*SUMPRODUCT(('Rate Engine'!$G$17:$G$64=YEAR($C43)*12+MONTH($C43)-1)*'Rate Engine'!$H$17:$H$64,'Rate Engine'!$Q$17:$Q$64))/SUMPRODUCT('Rate Engine'!$H$17:$H$64,'Rate Engine'!$Q$17:$Q$64)) | Y43: =IF($C43="","",IF(AND($E43="taken",$G43<>"",$G43<>1),"achievement ignored — restate Filed %",""))
A44: MM | B44: MD | C44: 46204 | D44: 0.02 | E44: taken | F44: Y | J44: =IF(OR($A44="",$B44=""),"",$A44&"|"&$B44) -> MM|MD | K44: =IF($C44="","",$D44*IF($E44="planned",IF($G44="",1,$G44),1)) -> 0.02 | L44: =IF($C44="",0,IF(1+$K44>0,LN(1+$K44),0)) -> 0.019802627 | M44: =IF($C44="","",DATE(YEAR($C44),MONTH($C44),1)) -> 46204 | N44: =IF($C44="",0,EOMONTH($C44,0)-$C44+1) -> 31 | O44: =IF($C44="",0,COUNTIFS(rl_key,$J44,rl_effmonth,$M44,rl_eff,"<"&$C44)) -> 0 | P44: =IF($C44="",0,COUNTIFS($J$7:$J44,$J44,$M$7:$M44,$M44,$C$7:$C44,$C44)) -> 1 | Q44: =IF($C44="",0,IF(AND($O44=0,$P44=1),1,0)) -> 1 | R44: =IF($C44="",0,IF(COUNTIFS(rl_key,$J44,rl_effmonth,$M44)>1,1,0)) -> 0 | S44: =IF($C44="",0,COUNTIFS(rl_key,$J44,rl_eff,"<"&$C44)+COUNTIFS($J$7:$J44,$J44,$C$7:$C44,$C44)) -> 1 | T44: =IF(OR($C44="",$E44<>"planned",$C44<DATE(nr_PlanYear,1,1),$C44>DATE(nr_PlanYear,12,31)),0,IF(AND(COUNTIFS(rl_key,$J44,rl_status,"planned",rl_eff,">="&DATE(nr_PlanYear,1,1),rl_eff,"<"&$C44)=0,COUNTIFS($J$7:$J44,$J44,$E$7:$E44,"planned",$C$7:$C44,$C44)=1),1,0)) -> 0 | U44: =IF(OR($C44="",$E44<>"taken"),0,IF(AND(COUNTIFS(rl_key,$J44,rl_effmonth,$M44,rl_eff,"<"&$C44,rl_status,"taken")=0,COUNTIFS($J$7:$J44,$J44,$M$7:$M44,$M44,$C$7:$C44,$C44,$E$7:$E44,"taken")=1),1,0)) -> 1 | V44: =IF($J44="","",IF(COUNTIF(lr_key,$J44)=0,"not in tbl_LR",INDEX(calc_cylr_p,MATCH($J44,lr_key,0)))) -> 0.56523796 | W44: =IF(OR($J44="",COUNTIF(lr_key,$J44)=0),"",(INDEX(calc_cylr_p,MATCH($J44,lr_key,0))-INDEX(calc_lrcur,MATCH($J44,lr_key,0)))*100) -> 0.12379649 | X44: =IF(OR($C44="",$J44<>nr_SelKey),"",(SUMPRODUCT(('Rate Engine'!$G$17:$G$64>YEAR($C44)*12+MONTH($C44)-1)*'Rate Engine'!$H$17:$H$64,'Rate Engine'!$Q$17:$Q$64)+(EOMONTH($C44,0)-$C44+1)/DAY(EOMONTH($C44,0))*SUMPRODUCT(('Rate Engine'!$G$17:$G$64=YEAR($C44)*12+MONTH($C44)-1)*'Rate Engine'!$H$17:$H$64,'Rate Engine'!$Q$17:$Q$64))/SUMPRODUCT('Rate Engine'!$H$17:$H$64,'Rate Engine'!$Q$17:$Q$64)) | Y44: =IF($C44="","",IF(AND($E44="taken",$G44<>"",$G44<>1),"achievement ignored — restate Filed %",""))
A45: MM | B45: MI | C45: 46235 | D45: 0.03 | E45: taken | F45: Y | J45: =IF(OR($A45="",$B45=""),"",$A45&"|"&$B45) -> MM|MI | K45: =IF($C45="","",$D45*IF($E45="planned",IF($G45="",1,$G45),1)) -> 0.03 | L45: =IF($C45="",0,IF(1+$K45>0,LN(1+$K45),0)) -> 0.029558802 | M45: =IF($C45="","",DATE(YEAR($C45),MONTH($C45),1)) -> 46235 | N45: =IF($C45="",0,EOMONTH($C45,0)-$C45+1) -> 31 | O45: =IF($C45="",0,COUNTIFS(rl_key,$J45,rl_effmonth,$M45,rl_eff,"<"&$C45)) -> 0 | P45: =IF($C45="",0,COUNTIFS($J$7:$J45,$J45,$M$7:$M45,$M45,$C$7:$C45,$C45)) -> 1 | Q45: =IF($C45="",0,IF(AND($O45=0,$P45=1),1,0)) -> 1 | R45: =IF($C45="",0,IF(COUNTIFS(rl_key,$J45,rl_effmonth,$M45)>1,1,0)) -> 0 | S45: =IF($C45="",0,COUNTIFS(rl_key,$J45,rl_eff,"<"&$C45)+COUNTIFS($J$7:$J45,$J45,$C$7:$C45,$C45)) -> 1 | T45: =IF(OR($C45="",$E45<>"planned",$C45<DATE(nr_PlanYear,1,1),$C45>DATE(nr_PlanYear,12,31)),0,IF(AND(COUNTIFS(rl_key,$J45,rl_status,"planned",rl_eff,">="&DATE(nr_PlanYear,1,1),rl_eff,"<"&$C45)=0,COUNTIFS($J$7:$J45,$J45,$E$7:$E45,"planned",$C$7:$C45,$C45)=1),1,0)) -> 0 | U45: =IF(OR($C45="",$E45<>"taken"),0,IF(AND(COUNTIFS(rl_key,$J45,rl_effmonth,$M45,rl_eff,"<"&$C45,rl_status,"taken")=0,COUNTIFS($J$7:$J45,$J45,$M$7:$M45,$M45,$C$7:$C45,$C45,$E$7:$E45,"taken")=1),1,0)) -> 1 | V45: =IF($J45="","",IF(COUNTIF(lr_key,$J45)=0,"not in tbl_LR",INDEX(calc_cylr_p,MATCH($J45,lr_key,0)))) -> 0.59862658 | W45: =IF(OR($J45="",COUNTIF(lr_key,$J45)=0),"",(INDEX(calc_cylr_p,MATCH($J45,lr_key,0))-INDEX(calc_lrcur,MATCH($J45,lr_key,0)))*100) -> 0.66265759 | X45: =IF(OR($C45="",$J45<>nr_SelKey),"",(SUMPRODUCT(('Rate Engine'!$G$17:$G$64>YEAR($C45)*12+MONTH($C45)-1)*'Rate Engine'!$H$17:$H$64,'Rate Engine'!$Q$17:$Q$64)+(EOMONTH($C45,0)-$C45+1)/DAY(EOMONTH($C45,0))*SUMPRODUCT(('Rate Engine'!$G$17:$G$64=YEAR($C45)*12+MONTH($C45)-1)*'Rate Engine'!$H$17:$H$64,'Rate Engine'!$Q$17:$Q$64))/SUMPRODUCT('Rate Engine'!$H$17:$H$64,'Rate Engine'!$Q$17:$Q$64)) | Y45: =IF($C45="","",IF(AND($E45="taken",$G45<>"",$G45<>1),"achievement ignored — restate Filed %",""))
A46: MM | B46: NM | C46: 46296 | D46: 0.05 | E46: taken | F46: Y | J46: =IF(OR($A46="",$B46=""),"",$A46&"|"&$B46) -> MM|NM | K46: =IF($C46="","",$D46*IF($E46="planned",IF($G46="",1,$G46),1)) -> 0.05 | L46: =IF($C46="",0,IF(1+$K46>0,LN(1+$K46),0)) -> 0.048790164 | M46: =IF($C46="","",DATE(YEAR($C46),MONTH($C46),1)) -> 46296 | N46: =IF($C46="",0,EOMONTH($C46,0)-$C46+1) -> 31 | O46: =IF($C46="",0,COUNTIFS(rl_key,$J46,rl_effmonth,$M46,rl_eff,"<"&$C46)) -> 0 | P46: =IF($C46="",0,COUNTIFS($J$7:$J46,$J46,$M$7:$M46,$M46,$C$7:$C46,$C46)) -> 1 | Q46: =IF($C46="",0,IF(AND($O46=0,$P46=1),1,0)) -> 1 | R46: =IF($C46="",0,IF(COUNTIFS(rl_key,$J46,rl_effmonth,$M46)>1,1,0)) -> 0 | S46: =IF($C46="",0,COUNTIFS(rl_key,$J46,rl_eff,"<"&$C46)+COUNTIFS($J$7:$J46,$J46,$C$7:$C46,$C46)) -> 1 | T46: =IF(OR($C46="",$E46<>"planned",$C46<DATE(nr_PlanYear,1,1),$C46>DATE(nr_PlanYear,12,31)),0,IF(AND(COUNTIFS(rl_key,$J46,rl_status,"planned",rl_eff,">="&DATE(nr_PlanYear,1,1),rl_eff,"<"&$C46)=0,COUNTIFS($J$7:$J46,$J46,$E$7:$E46,"planned",$C$7:$C46,$C46)=1),1,0)) -> 0 | U46: =IF(OR($C46="",$E46<>"taken"),0,IF(AND(COUNTIFS(rl_key,$J46,rl_effmonth,$M46,rl_eff,"<"&$C46,rl_status,"taken")=0,COUNTIFS($J$7:$J46,$J46,$M$7:$M46,$M46,$C$7:$C46,$C46,$E$7:$E46,"taken")=1),1,0)) -> 1 | V46: =IF($J46="","",IF(COUNTIF(lr_key,$J46)=0,"not in tbl_LR",INDEX(calc_cylr_p,MATCH($J46,lr_key,0)))) -> 0.55790095 | W46: =IF(OR($J46="",COUNTIF(lr_key,$J46)=0),"",(INDEX(calc_cylr_p,MATCH($J46,lr_key,0))-INDEX(calc_lrcur,MATCH($J46,lr_key,0)))*100) -> -0.20990543 | X46: =IF(OR($C46="",$J46<>nr_SelKey),"",(SUMPRODUCT(('Rate Engine'!$G$17:$G$64>YEAR($C46)*12+MONTH($C46)-1)*'Rate Engine'!$H$17:$H$64,'Rate Engine'!$Q$17:$Q$64)+(EOMONTH($C46,0)-$C46+1)/DAY(EOMONTH($C46,0))*SUMPRODUCT(('Rate Engine'!$G$17:$G$64=YEAR($C46)*12+MONTH($C46)-1)*'Rate Engine'!$H$17:$H$64,'Rate Engine'!$Q$17:$Q$64))/SUMPRODUCT('Rate Engine'!$H$17:$H$64,'Rate Engine'!$Q$17:$Q$64)) | Y46: =IF($C46="","",IF(AND($E46="taken",$G46<>"",$G46<>1),"achievement ignored — restate Filed %",""))
A47: MM | B47: NM | C47: 46478 | D47: 0.04 | E47: planned | F47: N | G47: 1 | J47: =IF(OR($A47="",$B47=""),"",$A47&"|"&$B47) -> MM|NM | K47: =IF($C47="","",$D47*IF($E47="planned",IF($G47="",1,$G47),1)) -> 0.04 | L47: =IF($C47="",0,IF(1+$K47>0,LN(1+$K47),0)) -> 0.039220713 | M47: =IF($C47="","",DATE(YEAR($C47),MONTH($C47),1)) -> 46478 | N47: =IF($C47="",0,EOMONTH($C47,0)-$C47+1) -> 30 | O47: =IF($C47="",0,COUNTIFS(rl_key,$J47,rl_effmonth,$M47,rl_eff,"<"&$C47)) -> 0 | P47: =IF($C47="",0,COUNTIFS($J$7:$J47,$J47,$M$7:$M47,$M47,$C$7:$C47,$C47)) -> 1 | Q47: =IF($C47="",0,IF(AND($O47=0,$P47=1),1,0)) -> 1 | R47: =IF($C47="",0,IF(COUNTIFS(rl_key,$J47,rl_effmonth,$M47)>1,1,0)) -> 0 | S47: =IF($C47="",0,COUNTIFS(rl_key,$J47,rl_eff,"<"&$C47)+COUNTIFS($J$7:$J47,$J47,$C$7:$C47,$C47)) -> 2 | T47: =IF(OR($C47="",$E47<>"planned",$C47<DATE(nr_PlanYear,1,1),$C47>DATE(nr_PlanYear,12,31)),0,IF(AND(COUNTIFS(rl_key,$J47,rl_status,"planned",rl_eff,">="&DATE(nr_PlanYear,1,1),rl_eff,"<"&$C47)=0,COUNTIFS($J$7:$J47,$J47,$E$7:$E47,"planned",$C$7:$C47,$C47)=1),1,0)) -> 1 | U47: =IF(OR($C47="",$E47<>"taken"),0,IF(AND(COUNTIFS(rl_key,$J47,rl_effmonth,$M47,rl_eff,"<"&$C47,rl_status,"taken")=0,COUNTIFS($J$7:$J47,$J47,$M$7:$M47,$M47,$C$7:$C47,$C47,$E$7:$E47,"taken")=1),1,0)) -> 0 | V47: =IF($J47="","",IF(COUNTIF(lr_key,$J47)=0,"not in tbl_LR",INDEX(calc_cylr_p,MATCH($J47,lr_key,0)))) -> 0.55790095 | W47: =IF(OR($J47="",COUNTIF(lr_key,$J47)=0),"",(INDEX(calc_cylr_p,MATCH($J47,lr_key,0))-INDEX(calc_lrcur,MATCH($J47,lr_key,0)))*100) -> -0.20990543 | X47: =IF(OR($C47="",$J47<>nr_SelKey),"",(SUMPRODUCT(('Rate Engine'!$G$17:$G$64>YEAR($C47)*12+MONTH($C47)-1)*'Rate Engine'!$H$17:$H$64,'Rate Engine'!$Q$17:$Q$64)+(EOMONTH($C47,0)-$C47+1)/DAY(EOMONTH($C47,0))*SUMPRODUCT(('Rate Engine'!$G$17:$G$64=YEAR($C47)*12+MONTH($C47)-1)*'Rate Engine'!$H$17:$H$64,'Rate Engine'!$Q$17:$Q$64))/SUMPRODUCT('Rate Engine'!$H$17:$H$64,'Rate Engine'!$Q$17:$Q$64)) | Y47: =IF($C47="","",IF(AND($E47="taken",$G47<>"",$G47<>1),"achievement ignored — restate Filed %",""))
A48: MM | B48: NC | C48: 46327 | D48: 0.06 | E48: taken | F48: Y | J48: =IF(OR($A48="",$B48=""),"",$A48&"|"&$B48) -> MM|NC | K48: =IF($C48="","",$D48*IF($E48="planned",IF($G48="",1,$G48),1)) -> 0.06 | L48: =IF($C48="",0,IF(1+$K48>0,LN(1+$K48),0)) -> 0.058268908 | M48: =IF($C48="","",DATE(YEAR($C48),MONTH($C48),1)) -> 46327 | N48: =IF($C48="",0,EOMONTH($C48,0)-$C48+1) -> 30 | O48: =IF($C48="",0,COUNTIFS(rl_key,$J48,rl_effmonth,$M48,rl_eff,"<"&$C48)) -> 0 | P48: =IF($C48="",0,COUNTIFS($J$7:$J48,$J48,$M$7:$M48,$M48,$C$7:$C48,$C48)) -> 1 | Q48: =IF($C48="",0,IF(AND($O48=0,$P48=1),1,0)) -> 1 | R48: =IF($C48="",0,IF(COUNTIFS(rl_key,$J48,rl_effmonth,$M48)>1,1,0)) -> 0 | S48: =IF($C48="",0,COUNTIFS(rl_key,$J48,rl_eff,"<"&$C48)+COUNTIFS($J$7:$J48,$J48,$C$7:$C48,$C48)) -> 1 | T48: =IF(OR($C48="",$E48<>"planned",$C48<DATE(nr_PlanYear,1,1),$C48>DATE(nr_PlanYear,12,31)),0,IF(AND(COUNTIFS(rl_key,$J48,rl_status,"planned",rl_eff,">="&DATE(nr_PlanYear,1,1),rl_eff,"<"&$C48)=0,COUNTIFS($J$7:$J48,$J48,$E$7:$E48,"planned",$C$7:$C48,$C48)=1),1,0)) -> 0 | U48: =IF(OR($C48="",$E48<>"taken"),0,IF(AND(COUNTIFS(rl_key,$J48,rl_effmonth,$M48,rl_eff,"<"&$C48,rl_status,"taken")=0,COUNTIFS($J$7:$J48,$J48,$M$7:$M48,$M48,$C$7:$C48,$C48,$E$7:$E48,"taken")=1),1,0)) -> 1 | V48: =IF($J48="","",IF(COUNTIF(lr_key,$J48)=0,"not in tbl_LR",INDEX(calc_cylr_p,MATCH($J48,lr_key,0)))) -> 0.59561078 | W48: =IF(OR($J48="",COUNTIF(lr_key,$J48)=0),"",(INDEX(calc_cylr_p,MATCH($J48,lr_key,0))-INDEX(calc_lrcur,MATCH($J48,lr_key,0)))*100) -> 0.76107773 | X48: =IF(OR($C48="",$J48<>nr_SelKey),"",(SUMPRODUCT(('Rate Engine'!$G$17:$G$64>YEAR($C48)*12+MONTH($C48)-1)*'Rate Engine'!$H$17:$H$64,'Rate Engine'!$Q$17:$Q$64)+(EOMONTH($C48,0)-$C48+1)/DAY(EOMONTH($C48,0))*SUMPRODUCT(('Rate Engine'!$G$17:$G$64=YEAR($C48)*12+MONTH($C48)-1)*'Rate Engine'!$H$17:$H$64,'Rate Engine'!$Q$17:$Q$64))/SUMPRODUCT('Rate Engine'!$H$17:$H$64,'Rate Engine'!$Q$17:$Q$64)) | Y48: =IF($C48="","",IF(AND($E48="taken",$G48<>"",$G48<>1),"achievement ignored — restate Filed %",""))
A49: MM | B49: PA | C49: 46023 | D49: 0.03 | E49: taken | F49: Y | J49: =IF(OR($A49="",$B49=""),"",$A49&"|"&$B49) -> MM|PA | K49: =IF($C49="","",$D49*IF($E49="planned",IF($G49="",1,$G49),1)) -> 0.03 | L49: =IF($C49="",0,IF(1+$K49>0,LN(1+$K49),0)) -> 0.029558802 | M49: =IF($C49="","",DATE(YEAR($C49),MONTH($C49),1)) -> 46023 | N49: =IF($C49="",0,EOMONTH($C49,0)-$C49+1) -> 31 | O49: =IF($C49="",0,COUNTIFS(rl_key,$J49,rl_effmonth,$M49,rl_eff,"<"&$C49)) -> 0 | P49: =IF($C49="",0,COUNTIFS($J$7:$J49,$J49,$M$7:$M49,$M49,$C$7:$C49,$C49)) -> 1 | Q49: =IF($C49="",0,IF(AND($O49=0,$P49=1),1,0)) -> 1 | R49: =IF($C49="",0,IF(COUNTIFS(rl_key,$J49,rl_effmonth,$M49)>1,1,0)) -> 0 | S49: =IF($C49="",0,COUNTIFS(rl_key,$J49,rl_eff,"<"&$C49)+COUNTIFS($J$7:$J49,$J49,$C$7:$C49,$C49)) -> 1 | T49: =IF(OR($C49="",$E49<>"planned",$C49<DATE(nr_PlanYear,1,1),$C49>DATE(nr_PlanYear,12,31)),0,IF(AND(COUNTIFS(rl_key,$J49,rl_status,"planned",rl_eff,">="&DATE(nr_PlanYear,1,1),rl_eff,"<"&$C49)=0,COUNTIFS($J$7:$J49,$J49,$E$7:$E49,"planned",$C$7:$C49,$C49)=1),1,0)) -> 0 | U49: =IF(OR($C49="",$E49<>"taken"),0,IF(AND(COUNTIFS(rl_key,$J49,rl_effmonth,$M49,rl_eff,"<"&$C49,rl_status,"taken")=0,COUNTIFS($J$7:$J49,$J49,$M$7:$M49,$M49,$C$7:$C49,$C49,$E$7:$E49,"taken")=1),1,0)) -> 1 | V49: =IF($J49="","",IF(COUNTIF(lr_key,$J49)=0,"not in tbl_LR",INDEX(calc_cylr_p,MATCH($J49,lr_key,0)))) -> 0.60526564 | W49: =IF(OR($J49="",COUNTIF(lr_key,$J49)=0),"",(INDEX(calc_cylr_p,MATCH($J49,lr_key,0))-INDEX(calc_lrcur,MATCH($J49,lr_key,0)))*100) -> 0.52656388 | X49: =IF(OR($C49="",$J49<>nr_SelKey),"",(SUMPRODUCT(('Rate Engine'!$G$17:$G$64>YEAR($C49)*12+MONTH($C49)-1)*'Rate Engine'!$H$17:$H$64,'Rate Engine'!$Q$17:$Q$64)+(EOMONTH($C49,0)-$C49+1)/DAY(EOMONTH($C49,0))*SUMPRODUCT(('Rate Engine'!$G$17:$G$64=YEAR($C49)*12+MONTH($C49)-1)*'Rate Engine'!$H$17:$H$64,'Rate Engine'!$Q$17:$Q$64))/SUMPRODUCT('Rate Engine'!$H$17:$H$64,'Rate Engine'!$Q$17:$Q$64)) | Y49: =IF($C49="","",IF(AND($E49="taken",$G49<>"",$G49<>1),"achievement ignored — restate Filed %",""))
A50: MM | B50: SC | C50: 46054 | D50: 0.04 | E50: taken | F50: Y | J50: =IF(OR($A50="",$B50=""),"",$A50&"|"&$B50) -> MM|SC | K50: =IF($C50="","",$D50*IF($E50="planned",IF($G50="",1,$G50),1)) -> 0.04 | L50: =IF($C50="",0,IF(1+$K50>0,LN(1+$K50),0)) -> 0.039220713 | M50: =IF($C50="","",DATE(YEAR($C50),MONTH($C50),1)) -> 46054 | N50: =IF($C50="",0,EOMONTH($C50,0)-$C50+1) -> 28 | O50: =IF($C50="",0,COUNTIFS(rl_key,$J50,rl_effmonth,$M50,rl_eff,"<"&$C50)) -> 0 | P50: =IF($C50="",0,COUNTIFS($J$7:$J50,$J50,$M$7:$M50,$M50,$C$7:$C50,$C50)) -> 1 | Q50: =IF($C50="",0,IF(AND($O50=0,$P50=1),1,0)) -> 1 | R50: =IF($C50="",0,IF(COUNTIFS(rl_key,$J50,rl_effmonth,$M50)>1,1,0)) -> 0 | S50: =IF($C50="",0,COUNTIFS(rl_key,$J50,rl_eff,"<"&$C50)+COUNTIFS($J$7:$J50,$J50,$C$7:$C50,$C50)) -> 1 | T50: =IF(OR($C50="",$E50<>"planned",$C50<DATE(nr_PlanYear,1,1),$C50>DATE(nr_PlanYear,12,31)),0,IF(AND(COUNTIFS(rl_key,$J50,rl_status,"planned",rl_eff,">="&DATE(nr_PlanYear,1,1),rl_eff,"<"&$C50)=0,COUNTIFS($J$7:$J50,$J50,$E$7:$E50,"planned",$C$7:$C50,$C50)=1),1,0)) -> 0 | U50: =IF(OR($C50="",$E50<>"taken"),0,IF(AND(COUNTIFS(rl_key,$J50,rl_effmonth,$M50,rl_eff,"<"&$C50,rl_status,"taken")=0,COUNTIFS($J$7:$J50,$J50,$M$7:$M50,$M50,$C$7:$C50,$C50,$E$7:$E50,"taken")=1),1,0)) -> 1 | V50: =IF($J50="","",IF(COUNTIF(lr_key,$J50)=0,"not in tbl_LR",INDEX(calc_cylr_p,MATCH($J50,lr_key,0)))) -> 0.58124544 | W50: =IF(OR($J50="",COUNTIF(lr_key,$J50)=0),"",(INDEX(calc_cylr_p,MATCH($J50,lr_key,0))-INDEX(calc_lrcur,MATCH($J50,lr_key,0)))*100) -> -0.27545623 | X50: =IF(OR($C50="",$J50<>nr_SelKey),"",(SUMPRODUCT(('Rate Engine'!$G$17:$G$64>YEAR($C50)*12+MONTH($C50)-1)*'Rate Engine'!$H$17:$H$64,'Rate Engine'!$Q$17:$Q$64)+(EOMONTH($C50,0)-$C50+1)/DAY(EOMONTH($C50,0))*SUMPRODUCT(('Rate Engine'!$G$17:$G$64=YEAR($C50)*12+MONTH($C50)-1)*'Rate Engine'!$H$17:$H$64,'Rate Engine'!$Q$17:$Q$64))/SUMPRODUCT('Rate Engine'!$H$17:$H$64,'Rate Engine'!$Q$17:$Q$64)) | Y50: =IF($C50="","",IF(AND($E50="taken",$G50<>"",$G50<>1),"achievement ignored — restate Filed %",""))
A51: MM | B51: SC | C51: 46600 | D51: 0.04 | E51: planned | F51: N | G51: 1 | J51: =IF(OR($A51="",$B51=""),"",$A51&"|"&$B51) -> MM|SC | K51: =IF($C51="","",$D51*IF($E51="planned",IF($G51="",1,$G51),1)) -> 0.04 | L51: =IF($C51="",0,IF(1+$K51>0,LN(1+$K51),0)) -> 0.039220713 | M51: =IF($C51="","",DATE(YEAR($C51),MONTH($C51),1)) -> 46600 | N51: =IF($C51="",0,EOMONTH($C51,0)-$C51+1) -> 31 | O51: =IF($C51="",0,COUNTIFS(rl_key,$J51,rl_effmonth,$M51,rl_eff,"<"&$C51)) -> 0 | P51: =IF($C51="",0,COUNTIFS($J$7:$J51,$J51,$M$7:$M51,$M51,$C$7:$C51,$C51)) -> 1 | Q51: =IF($C51="",0,IF(AND($O51=0,$P51=1),1,0)) -> 1 | R51: =IF($C51="",0,IF(COUNTIFS(rl_key,$J51,rl_effmonth,$M51)>1,1,0)) -> 0 | S51: =IF($C51="",0,COUNTIFS(rl_key,$J51,rl_eff,"<"&$C51)+COUNTIFS($J$7:$J51,$J51,$C$7:$C51,$C51)) -> 2 | T51: =IF(OR($C51="",$E51<>"planned",$C51<DATE(nr_PlanYear,1,1),$C51>DATE(nr_PlanYear,12,31)),0,IF(AND(COUNTIFS(rl_key,$J51,rl_status,"planned",rl_eff,">="&DATE(nr_PlanYear,1,1),rl_eff,"<"&$C51)=0,COUNTIFS($J$7:$J51,$J51,$E$7:$E51,"planned",$C$7:$C51,$C51)=1),1,0)) -> 1 | U51: =IF(OR($C51="",$E51<>"taken"),0,IF(AND(COUNTIFS(rl_key,$J51,rl_effmonth,$M51,rl_eff,"<"&$C51,rl_status,"taken")=0,COUNTIFS($J$7:$J51,$J51,$M$7:$M51,$M51,$C$7:$C51,$C51,$E$7:$E51,"taken")=1),1,0)) -> 0 | V51: =IF($J51="","",IF(COUNTIF(lr_key,$J51)=0,"not in tbl_LR",INDEX(calc_cylr_p,MATCH($J51,lr_key,0)))) -> 0.58124544 | W51: =IF(OR($J51="",COUNTIF(lr_key,$J51)=0),"",(INDEX(calc_cylr_p,MATCH($J51,lr_key,0))-INDEX(calc_lrcur,MATCH($J51,lr_key,0)))*100) -> -0.27545623 | X51: =IF(OR($C51="",$J51<>nr_SelKey),"",(SUMPRODUCT(('Rate Engine'!$G$17:$G$64>YEAR($C51)*12+MONTH($C51)-1)*'Rate Engine'!$H$17:$H$64,'Rate Engine'!$Q$17:$Q$64)+(EOMONTH($C51,0)-$C51+1)/DAY(EOMONTH($C51,0))*SUMPRODUCT(('Rate Engine'!$G$17:$G$64=YEAR($C51)*12+MONTH($C51)-1)*'Rate Engine'!$H$17:$H$64,'Rate Engine'!$Q$17:$Q$64))/SUMPRODUCT('Rate Engine'!$H$17:$H$64,'Rate Engine'!$Q$17:$Q$64)) | Y51: =IF($C51="","",IF(AND($E51="taken",$G51<>"",$G51<>1),"achievement ignored — restate Filed %",""))
A52: MM | B52: VA | C52: 46113 | D52: 0.06 | E52: taken | F52: Y | J52: =IF(OR($A52="",$B52=""),"",$A52&"|"&$B52) -> MM|VA | K52: =IF($C52="","",$D52*IF($E52="planned",IF($G52="",1,$G52),1)) -> 0.06 | L52: =IF($C52="",0,IF(1+$K52>0,LN(1+$K52),0)) -> 0.058268908 | M52: =IF($C52="","",DATE(YEAR($C52),MONTH($C52),1)) -> 46113 | N52: =IF($C52="",0,EOMONTH($C52,0)-$C52+1) -> 30 | O52: =IF($C52="",0,COUNTIFS(rl_key,$J52,rl_effmonth,$M52,rl_eff,"<"&$C52)) -> 0 | P52: =IF($C52="",0,COUNTIFS($J$7:$J52,$J52,$M$7:$M52,$M52,$C$7:$C52,$C52)) -> 1 | Q52: =IF($C52="",0,IF(AND($O52=0,$P52=1),1,0)) -> 1 | R52: =IF($C52="",0,IF(COUNTIFS(rl_key,$J52,rl_effmonth,$M52)>1,1,0)) -> 0 | S52: =IF($C52="",0,COUNTIFS(rl_key,$J52,rl_eff,"<"&$C52)+COUNTIFS($J$7:$J52,$J52,$C$7:$C52,$C52)) -> 1 | T52: =IF(OR($C52="",$E52<>"planned",$C52<DATE(nr_PlanYear,1,1),$C52>DATE(nr_PlanYear,12,31)),0,IF(AND(COUNTIFS(rl_key,$J52,rl_status,"planned",rl_eff,">="&DATE(nr_PlanYear,1,1),rl_eff,"<"&$C52)=0,COUNTIFS($J$7:$J52,$J52,$E$7:$E52,"planned",$C$7:$C52,$C52)=1),1,0)) -> 0 | U52: =IF(OR($C52="",$E52<>"taken"),0,IF(AND(COUNTIFS(rl_key,$J52,rl_effmonth,$M52,rl_eff,"<"&$C52,rl_status,"taken")=0,COUNTIFS($J$7:$J52,$J52,$M$7:$M52,$M52,$C$7:$C52,$C52,$E$7:$E52,"taken")=1),1,0)) -> 1 | V52: =IF($J52="","",IF(COUNTIF(lr_key,$J52)=0,"not in tbl_LR",INDEX(calc_cylr_p,MATCH($J52,lr_key,0)))) -> 0.59860995 | W52: =IF(OR($J52="",COUNTIF(lr_key,$J52)=0),"",(INDEX(calc_cylr_p,MATCH($J52,lr_key,0))-INDEX(calc_lrcur,MATCH($J52,lr_key,0)))*100) -> 0.26099488 | X52: =IF(OR($C52="",$J52<>nr_SelKey),"",(SUMPRODUCT(('Rate Engine'!$G$17:$G$64>YEAR($C52)*12+MONTH($C52)-1)*'Rate Engine'!$H$17:$H$64,'Rate Engine'!$Q$17:$Q$64)+(EOMONTH($C52,0)-$C52+1)/DAY(EOMONTH($C52,0))*SUMPRODUCT(('Rate Engine'!$G$17:$G$64=YEAR($C52)*12+MONTH($C52)-1)*'Rate Engine'!$H$17:$H$64,'Rate Engine'!$Q$17:$Q$64))/SUMPRODUCT('Rate Engine'!$H$17:$H$64,'Rate Engine'!$Q$17:$Q$64)) | Y52: =IF($C52="","",IF(AND($E52="taken",$G52<>"",$G52<>1),"achievement ignored — restate Filed %",""))
A53: MM | B53: WV | C53: 46143 | D53: 0.02 | E53: taken | F53: Y | J53: =IF(OR($A53="",$B53=""),"",$A53&"|"&$B53) -> MM|WV | K53: =IF($C53="","",$D53*IF($E53="planned",IF($G53="",1,$G53),1)) -> 0.02 | L53: =IF($C53="",0,IF(1+$K53>0,LN(1+$K53),0)) -> 0.019802627 | M53: =IF($C53="","",DATE(YEAR($C53),MONTH($C53),1)) -> 46143 | N53: =IF($C53="",0,EOMONTH($C53,0)-$C53+1) -> 31 | O53: =IF($C53="",0,COUNTIFS(rl_key,$J53,rl_effmonth,$M53,rl_eff,"<"&$C53)) -> 0 | P53: =IF($C53="",0,COUNTIFS($J$7:$J53,$J53,$M$7:$M53,$M53,$C$7:$C53,$C53)) -> 1 | Q53: =IF($C53="",0,IF(AND($O53=0,$P53=1),1,0)) -> 1 | R53: =IF($C53="",0,IF(COUNTIFS(rl_key,$J53,rl_effmonth,$M53)>1,1,0)) -> 0 | S53: =IF($C53="",0,COUNTIFS(rl_key,$J53,rl_eff,"<"&$C53)+COUNTIFS($J$7:$J53,$J53,$C$7:$C53,$C53)) -> 1 | T53: =IF(OR($C53="",$E53<>"planned",$C53<DATE(nr_PlanYear,1,1),$C53>DATE(nr_PlanYear,12,31)),0,IF(AND(COUNTIFS(rl_key,$J53,rl_status,"planned",rl_eff,">="&DATE(nr_PlanYear,1,1),rl_eff,"<"&$C53)=0,COUNTIFS($J$7:$J53,$J53,$E$7:$E53,"planned",$C$7:$C53,$C53)=1),1,0)) -> 0 | U53: =IF(OR($C53="",$E53<>"taken"),0,IF(AND(COUNTIFS(rl_key,$J53,rl_effmonth,$M53,rl_eff,"<"&$C53,rl_status,"taken")=0,COUNTIFS($J$7:$J53,$J53,$M$7:$M53,$M53,$C$7:$C53,$C53,$E$7:$E53,"taken")=1),1,0)) -> 1 | V53: =IF($J53="","",IF(COUNTIF(lr_key,$J53)=0,"not in tbl_LR",INDEX(calc_cylr_p,MATCH($J53,lr_key,0)))) -> 0.58766278 | W53: =IF(OR($J53="",COUNTIF(lr_key,$J53)=0),"",(INDEX(calc_cylr_p,MATCH($J53,lr_key,0))-INDEX(calc_lrcur,MATCH($J53,lr_key,0)))*100) -> 0.76627789 | X53: =IF(OR($C53="",$J53<>nr_SelKey),"",(SUMPRODUCT(('Rate Engine'!$G$17:$G$64>YEAR($C53)*12+MONTH($C53)-1)*'Rate Engine'!$H$17:$H$64,'Rate Engine'!$Q$17:$Q$64)+(EOMONTH($C53,0)-$C53+1)/DAY(EOMONTH($C53,0))*SUMPRODUCT(('Rate Engine'!$G$17:$G$64=YEAR($C53)*12+MONTH($C53)-1)*'Rate Engine'!$H$17:$H$64,'Rate Engine'!$Q$17:$Q$64))/SUMPRODUCT('Rate Engine'!$H$17:$H$64,'Rate Engine'!$Q$17:$Q$64)) | Y53: =IF($C53="","",IF(AND($E53="taken",$G53<>"",$G53<>1),"achievement ignored — restate Filed %",""))
A54: MM | B54: WI | C54: 46419 | D54: 0.04 | E54: planned | F54: N | G54: 1 | J54: =IF(OR($A54="",$B54=""),"",$A54&"|"&$B54) -> MM|WI | K54: =IF($C54="","",$D54*IF($E54="planned",IF($G54="",1,$G54),1)) -> 0.04 | L54: =IF($C54="",0,IF(1+$K54>0,LN(1+$K54),0)) -> 0.039220713 | M54: =IF($C54="","",DATE(YEAR($C54),MONTH($C54),1)) -> 46419 | N54: =IF($C54="",0,EOMONTH($C54,0)-$C54+1) -> 28 | O54: =IF($C54="",0,COUNTIFS(rl_key,$J54,rl_effmonth,$M54,rl_eff,"<"&$C54)) -> 0 | P54: =IF($C54="",0,COUNTIFS($J$7:$J54,$J54,$M$7:$M54,$M54,$C$7:$C54,$C54)) -> 1 | Q54: =IF($C54="",0,IF(AND($O54=0,$P54=1),1,0)) -> 1 | R54: =IF($C54="",0,IF(COUNTIFS(rl_key,$J54,rl_effmonth,$M54)>1,1,0)) -> 0 | S54: =IF($C54="",0,COUNTIFS(rl_key,$J54,rl_eff,"<"&$C54)+COUNTIFS($J$7:$J54,$J54,$C$7:$C54,$C54)) -> 1 | T54: =IF(OR($C54="",$E54<>"planned",$C54<DATE(nr_PlanYear,1,1),$C54>DATE(nr_PlanYear,12,31)),0,IF(AND(COUNTIFS(rl_key,$J54,rl_status,"planned",rl_eff,">="&DATE(nr_PlanYear,1,1),rl_eff,"<"&$C54)=0,COUNTIFS($J$7:$J54,$J54,$E$7:$E54,"planned",$C$7:$C54,$C54)=1),1,0)) -> 1 | U54: =IF(OR($C54="",$E54<>"taken"),0,IF(AND(COUNTIFS(rl_key,$J54,rl_effmonth,$M54,rl_eff,"<"&$C54,rl_status,"taken")=0,COUNTIFS($J$7:$J54,$J54,$M$7:$M54,$M54,$C$7:$C54,$C54,$E$7:$E54,"taken")=1),1,0)) -> 0 | V54: =IF($J54="","",IF(COUNTIF(lr_key,$J54)=0,"not in tbl_LR",INDEX(calc_cylr_p,MATCH($J54,lr_key,0)))) -> 0.55296141 | W54: =IF(OR($J54="",COUNTIF(lr_key,$J54)=0),"",(INDEX(calc_cylr_p,MATCH($J54,lr_key,0))-INDEX(calc_lrcur,MATCH($J54,lr_key,0)))*100) -> -1.1038587 | X54: =IF(OR($C54="",$J54<>nr_SelKey),"",(SUMPRODUCT(('Rate Engine'!$G$17:$G$64>YEAR($C54)*12+MONTH($C54)-1)*'Rate Engine'!$H$17:$H$64,'Rate Engine'!$Q$17:$Q$64)+(EOMONTH($C54,0)-$C54+1)/DAY(EOMONTH($C54,0))*SUMPRODUCT(('Rate Engine'!$G$17:$G$64=YEAR($C54)*12+MONTH($C54)-1)*'Rate Engine'!$H$17:$H$64,'Rate Engine'!$Q$17:$Q$64))/SUMPRODUCT('Rate Engine'!$H$17:$H$64,'Rate Engine'!$Q$17:$Q$64)) | Y54: =IF($C54="","",IF(AND($E54="taken",$G54<>"",$G54<>1),"achievement ignored — restate Filed %",""))
A55: SBA | B55: AZ | C55: 46204 | D55: 0.04 | E55: taken | F55: Y | J55: =IF(OR($A55="",$B55=""),"",$A55&"|"&$B55) -> SBA|AZ | K55: =IF($C55="","",$D55*IF($E55="planned",IF($G55="",1,$G55),1)) -> 0.04 | L55: =IF($C55="",0,IF(1+$K55>0,LN(1+$K55),0)) -> 0.039220713 | M55: =IF($C55="","",DATE(YEAR($C55),MONTH($C55),1)) -> 46204 | N55: =IF($C55="",0,EOMONTH($C55,0)-$C55+1) -> 31 | O55: =IF($C55="",0,COUNTIFS(rl_key,$J55,rl_effmonth,$M55,rl_eff,"<"&$C55)) -> 0 | P55: =IF($C55="",0,COUNTIFS($J$7:$J55,$J55,$M$7:$M55,$M55,$C$7:$C55,$C55)) -> 1 | Q55: =IF($C55="",0,IF(AND($O55=0,$P55=1),1,0)) -> 1 | R55: =IF($C55="",0,IF(COUNTIFS(rl_key,$J55,rl_effmonth,$M55)>1,1,0)) -> 0 | S55: =IF($C55="",0,COUNTIFS(rl_key,$J55,rl_eff,"<"&$C55)+COUNTIFS($J$7:$J55,$J55,$C$7:$C55,$C55)) -> 1 | T55: =IF(OR($C55="",$E55<>"planned",$C55<DATE(nr_PlanYear,1,1),$C55>DATE(nr_PlanYear,12,31)),0,IF(AND(COUNTIFS(rl_key,$J55,rl_status,"planned",rl_eff,">="&DATE(nr_PlanYear,1,1),rl_eff,"<"&$C55)=0,COUNTIFS($J$7:$J55,$J55,$E$7:$E55,"planned",$C$7:$C55,$C55)=1),1,0)) -> 0 | U55: =IF(OR($C55="",$E55<>"taken"),0,IF(AND(COUNTIFS(rl_key,$J55,rl_effmonth,$M55,rl_eff,"<"&$C55,rl_status,"taken")=0,COUNTIFS($J$7:$J55,$J55,$M$7:$M55,$M55,$C$7:$C55,$C55,$E$7:$E55,"taken")=1),1,0)) -> 1 | V55: =IF($J55="","",IF(COUNTIF(lr_key,$J55)=0,"not in tbl_LR",INDEX(calc_cylr_p,MATCH($J55,lr_key,0)))) -> 0.60114294 | W55: =IF(OR($J55="",COUNTIF(lr_key,$J55)=0),"",(INDEX(calc_cylr_p,MATCH($J55,lr_key,0))-INDEX(calc_lrcur,MATCH($J55,lr_key,0)))*100) -> 0.91429422 | X55: =IF(OR($C55="",$J55<>nr_SelKey),"",(SUMPRODUCT(('Rate Engine'!$G$17:$G$64>YEAR($C55)*12+MONTH($C55)-1)*'Rate Engine'!$H$17:$H$64,'Rate Engine'!$Q$17:$Q$64)+(EOMONTH($C55,0)-$C55+1)/DAY(EOMONTH($C55,0))*SUMPRODUCT(('Rate Engine'!$G$17:$G$64=YEAR($C55)*12+MONTH($C55)-1)*'Rate Engine'!$H$17:$H$64,'Rate Engine'!$Q$17:$Q$64))/SUMPRODUCT('Rate Engine'!$H$17:$H$64,'Rate Engine'!$Q$17:$Q$64)) | Y55: =IF($C55="","",IF(AND($E55="taken",$G55<>"",$G55<>1),"achievement ignored — restate Filed %",""))
A56: SBA | B56: CO | C56: 46235 | D56: 0.05 | E56: taken | F56: Y | J56: =IF(OR($A56="",$B56=""),"",$A56&"|"&$B56) -> SBA|CO | K56: =IF($C56="","",$D56*IF($E56="planned",IF($G56="",1,$G56),1)) -> 0.05 | L56: =IF($C56="",0,IF(1+$K56>0,LN(1+$K56),0)) -> 0.048790164 | M56: =IF($C56="","",DATE(YEAR($C56),MONTH($C56),1)) -> 46235 | N56: =IF($C56="",0,EOMONTH($C56,0)-$C56+1) -> 31 | O56: =IF($C56="",0,COUNTIFS(rl_key,$J56,rl_effmonth,$M56,rl_eff,"<"&$C56)) -> 0 | P56: =IF($C56="",0,COUNTIFS($J$7:$J56,$J56,$M$7:$M56,$M56,$C$7:$C56,$C56)) -> 1 | Q56: =IF($C56="",0,IF(AND($O56=0,$P56=1),1,0)) -> 1 | R56: =IF($C56="",0,IF(COUNTIFS(rl_key,$J56,rl_effmonth,$M56)>1,1,0)) -> 0 | S56: =IF($C56="",0,COUNTIFS(rl_key,$J56,rl_eff,"<"&$C56)+COUNTIFS($J$7:$J56,$J56,$C$7:$C56,$C56)) -> 1 | T56: =IF(OR($C56="",$E56<>"planned",$C56<DATE(nr_PlanYear,1,1),$C56>DATE(nr_PlanYear,12,31)),0,IF(AND(COUNTIFS(rl_key,$J56,rl_status,"planned",rl_eff,">="&DATE(nr_PlanYear,1,1),rl_eff,"<"&$C56)=0,COUNTIFS($J$7:$J56,$J56,$E$7:$E56,"planned",$C$7:$C56,$C56)=1),1,0)) -> 0 | U56: =IF(OR($C56="",$E56<>"taken"),0,IF(AND(COUNTIFS(rl_key,$J56,rl_effmonth,$M56,rl_eff,"<"&$C56,rl_status,"taken")=0,COUNTIFS($J$7:$J56,$J56,$M$7:$M56,$M56,$C$7:$C56,$C56,$E$7:$E56,"taken")=1),1,0)) -> 1 | V56: =IF($J56="","",IF(COUNTIF(lr_key,$J56)=0,"not in tbl_LR",INDEX(calc_cylr_p,MATCH($J56,lr_key,0)))) -> 0.58124722 | W56: =IF(OR($J56="",COUNTIF(lr_key,$J56)=0),"",(INDEX(calc_cylr_p,MATCH($J56,lr_key,0))-INDEX(calc_lrcur,MATCH($J56,lr_key,0)))*100) -> 0.52472246 | X56: =IF(OR($C56="",$J56<>nr_SelKey),"",(SUMPRODUCT(('Rate Engine'!$G$17:$G$64>YEAR($C56)*12+MONTH($C56)-1)*'Rate Engine'!$H$17:$H$64,'Rate Engine'!$Q$17:$Q$64)+(EOMONTH($C56,0)-$C56+1)/DAY(EOMONTH($C56,0))*SUMPRODUCT(('Rate Engine'!$G$17:$G$64=YEAR($C56)*12+MONTH($C56)-1)*'Rate Engine'!$H$17:$H$64,'Rate Engine'!$Q$17:$Q$64))/SUMPRODUCT('Rate Engine'!$H$17:$H$64,'Rate Engine'!$Q$17:$Q$64)) | Y56: =IF($C56="","",IF(AND($E56="taken",$G56<>"",$G56<>1),"achievement ignored — restate Filed %",""))
A57: SBA | B57: FL | C57: 46296 | D57: 0.02 | E57: taken | F57: Y | J57: =IF(OR($A57="",$B57=""),"",$A57&"|"&$B57) -> SBA|FL | K57: =IF($C57="","",$D57*IF($E57="planned",IF($G57="",1,$G57),1)) -> 0.02 | L57: =IF($C57="",0,IF(1+$K57>0,LN(1+$K57),0)) -> 0.019802627 | M57: =IF($C57="","",DATE(YEAR($C57),MONTH($C57),1)) -> 46296 | N57: =IF($C57="",0,EOMONTH($C57,0)-$C57+1) -> 31 | O57: =IF($C57="",0,COUNTIFS(rl_key,$J57,rl_effmonth,$M57,rl_eff,"<"&$C57)) -> 0 | P57: =IF($C57="",0,COUNTIFS($J$7:$J57,$J57,$M$7:$M57,$M57,$C$7:$C57,$C57)) -> 1 | Q57: =IF($C57="",0,IF(AND($O57=0,$P57=1),1,0)) -> 1 | R57: =IF($C57="",0,IF(COUNTIFS(rl_key,$J57,rl_effmonth,$M57)>1,1,0)) -> 0 | S57: =IF($C57="",0,COUNTIFS(rl_key,$J57,rl_eff,"<"&$C57)+COUNTIFS($J$7:$J57,$J57,$C$7:$C57,$C57)) -> 1 | T57: =IF(OR($C57="",$E57<>"planned",$C57<DATE(nr_PlanYear,1,1),$C57>DATE(nr_PlanYear,12,31)),0,IF(AND(COUNTIFS(rl_key,$J57,rl_status,"planned",rl_eff,">="&DATE(nr_PlanYear,1,1),rl_eff,"<"&$C57)=0,COUNTIFS($J$7:$J57,$J57,$E$7:$E57,"planned",$C$7:$C57,$C57)=1),1,0)) -> 0 | U57: =IF(OR($C57="",$E57<>"taken"),0,IF(AND(COUNTIFS(rl_key,$J57,rl_effmonth,$M57,rl_eff,"<"&$C57,rl_status,"taken")=0,COUNTIFS($J$7:$J57,$J57,$M$7:$M57,$M57,$C$7:$C57,$C57,$E$7:$E57,"taken")=1),1,0)) -> 1 | V57: =IF($J57="","",IF(COUNTIF(lr_key,$J57)=0,"not in tbl_LR",INDEX(calc_cylr_p,MATCH($J57,lr_key,0)))) -> 0.58735 | W57: =IF(OR($J57="",COUNTIF(lr_key,$J57)=0),"",(INDEX(calc_cylr_p,MATCH($J57,lr_key,0))-INDEX(calc_lrcur,MATCH($J57,lr_key,0)))*100) -> -0.065000317 | X57: =IF(OR($C57="",$J57<>nr_SelKey),"",(SUMPRODUCT(('Rate Engine'!$G$17:$G$64>YEAR($C57)*12+MONTH($C57)-1)*'Rate Engine'!$H$17:$H$64,'Rate Engine'!$Q$17:$Q$64)+(EOMONTH($C57,0)-$C57+1)/DAY(EOMONTH($C57,0))*SUMPRODUCT(('Rate Engine'!$G$17:$G$64=YEAR($C57)*12+MONTH($C57)-1)*'Rate Engine'!$H$17:$H$64,'Rate Engine'!$Q$17:$Q$64))/SUMPRODUCT('Rate Engine'!$H$17:$H$64,'Rate Engine'!$Q$17:$Q$64)) | Y57: =IF($C57="","",IF(AND($E57="taken",$G57<>"",$G57<>1),"achievement ignored — restate Filed %",""))
A58: SBA | B58: FL | C58: 46539 | D58: 0.04 | E58: planned | F58: N | G58: 1 | J58: =IF(OR($A58="",$B58=""),"",$A58&"|"&$B58) -> SBA|FL | K58: =IF($C58="","",$D58*IF($E58="planned",IF($G58="",1,$G58),1)) -> 0.04 | L58: =IF($C58="",0,IF(1+$K58>0,LN(1+$K58),0)) -> 0.039220713 | M58: =IF($C58="","",DATE(YEAR($C58),MONTH($C58),1)) -> 46539 | N58: =IF($C58="",0,EOMONTH($C58,0)-$C58+1) -> 30 | O58: =IF($C58="",0,COUNTIFS(rl_key,$J58,rl_effmonth,$M58,rl_eff,"<"&$C58)) -> 0 | P58: =IF($C58="",0,COUNTIFS($J$7:$J58,$J58,$M$7:$M58,$M58,$C$7:$C58,$C58)) -> 1 | Q58: =IF($C58="",0,IF(AND($O58=0,$P58=1),1,0)) -> 1 | R58: =IF($C58="",0,IF(COUNTIFS(rl_key,$J58,rl_effmonth,$M58)>1,1,0)) -> 0 | S58: =IF($C58="",0,COUNTIFS(rl_key,$J58,rl_eff,"<"&$C58)+COUNTIFS($J$7:$J58,$J58,$C$7:$C58,$C58)) -> 2 | T58: =IF(OR($C58="",$E58<>"planned",$C58<DATE(nr_PlanYear,1,1),$C58>DATE(nr_PlanYear,12,31)),0,IF(AND(COUNTIFS(rl_key,$J58,rl_status,"planned",rl_eff,">="&DATE(nr_PlanYear,1,1),rl_eff,"<"&$C58)=0,COUNTIFS($J$7:$J58,$J58,$E$7:$E58,"planned",$C$7:$C58,$C58)=1),1,0)) -> 1 | U58: =IF(OR($C58="",$E58<>"taken"),0,IF(AND(COUNTIFS(rl_key,$J58,rl_effmonth,$M58,rl_eff,"<"&$C58,rl_status,"taken")=0,COUNTIFS($J$7:$J58,$J58,$M$7:$M58,$M58,$C$7:$C58,$C58,$E$7:$E58,"taken")=1),1,0)) -> 0 | V58: =IF($J58="","",IF(COUNTIF(lr_key,$J58)=0,"not in tbl_LR",INDEX(calc_cylr_p,MATCH($J58,lr_key,0)))) -> 0.58735 | W58: =IF(OR($J58="",COUNTIF(lr_key,$J58)=0),"",(INDEX(calc_cylr_p,MATCH($J58,lr_key,0))-INDEX(calc_lrcur,MATCH($J58,lr_key,0)))*100) -> -0.065000317 | X58: =IF(OR($C58="",$J58<>nr_SelKey),"",(SUMPRODUCT(('Rate Engine'!$G$17:$G$64>YEAR($C58)*12+MONTH($C58)-1)*'Rate Engine'!$H$17:$H$64,'Rate Engine'!$Q$17:$Q$64)+(EOMONTH($C58,0)-$C58+1)/DAY(EOMONTH($C58,0))*SUMPRODUCT(('Rate Engine'!$G$17:$G$64=YEAR($C58)*12+MONTH($C58)-1)*'Rate Engine'!$H$17:$H$64,'Rate Engine'!$Q$17:$Q$64))/SUMPRODUCT('Rate Engine'!$H$17:$H$64,'Rate Engine'!$Q$17:$Q$64)) | Y58: =IF($C58="","",IF(AND($E58="taken",$G58<>"",$G58<>1),"achievement ignored — restate Filed %",""))
A59: SBA | B59: IN | C59: 46054 | D59: 0.06 | E59: taken | F59: Y | J59: =IF(OR($A59="",$B59=""),"",$A59&"|"&$B59) -> SBA|IN | K59: =IF($C59="","",$D59*IF($E59="planned",IF($G59="",1,$G59),1)) -> 0.06 | L59: =IF($C59="",0,IF(1+$K59>0,LN(1+$K59),0)) -> 0.058268908 | M59: =IF($C59="","",DATE(YEAR($C59),MONTH($C59),1)) -> 46054 | N59: =IF($C59="",0,EOMONTH($C59,0)-$C59+1) -> 28 | O59: =IF($C59="",0,COUNTIFS(rl_key,$J59,rl_effmonth,$M59,rl_eff,"<"&$C59)) -> 0 | P59: =IF($C59="",0,COUNTIFS($J$7:$J59,$J59,$M$7:$M59,$M59,$C$7:$C59,$C59)) -> 1 | Q59: =IF($C59="",0,IF(AND($O59=0,$P59=1),1,0)) -> 1 | R59: =IF($C59="",0,IF(COUNTIFS(rl_key,$J59,rl_effmonth,$M59)>1,1,0)) -> 0 | S59: =IF($C59="",0,COUNTIFS(rl_key,$J59,rl_eff,"<"&$C59)+COUNTIFS($J$7:$J59,$J59,$C$7:$C59,$C59)) -> 1 | T59: =IF(OR($C59="",$E59<>"planned",$C59<DATE(nr_PlanYear,1,1),$C59>DATE(nr_PlanYear,12,31)),0,IF(AND(COUNTIFS(rl_key,$J59,rl_status,"planned",rl_eff,">="&DATE(nr_PlanYear,1,1),rl_eff,"<"&$C59)=0,COUNTIFS($J$7:$J59,$J59,$E$7:$E59,"planned",$C$7:$C59,$C59)=1),1,0)) -> 0 | U59: =IF(OR($C59="",$E59<>"taken"),0,IF(AND(COUNTIFS(rl_key,$J59,rl_effmonth,$M59,rl_eff,"<"&$C59,rl_status,"taken")=0,COUNTIFS($J$7:$J59,$J59,$M$7:$M59,$M59,$C$7:$C59,$C59,$E$7:$E59,"taken")=1),1,0)) -> 1 | V59: =IF($J59="","",IF(COUNTIF(lr_key,$J59)=0,"not in tbl_LR",INDEX(calc_cylr_p,MATCH($J59,lr_key,0)))) -> 0.57533395 | W59: =IF(OR($J59="",COUNTIF(lr_key,$J59)=0),"",(INDEX(calc_cylr_p,MATCH($J59,lr_key,0))-INDEX(calc_lrcur,MATCH($J59,lr_key,0)))*100) -> 0.73339476 | X59: =IF(OR($C59="",$J59<>nr_SelKey),"",(SUMPRODUCT(('Rate Engine'!$G$17:$G$64>YEAR($C59)*12+MONTH($C59)-1)*'Rate Engine'!$H$17:$H$64,'Rate Engine'!$Q$17:$Q$64)+(EOMONTH($C59,0)-$C59+1)/DAY(EOMONTH($C59,0))*SUMPRODUCT(('Rate Engine'!$G$17:$G$64=YEAR($C59)*12+MONTH($C59)-1)*'Rate Engine'!$H$17:$H$64,'Rate Engine'!$Q$17:$Q$64))/SUMPRODUCT('Rate Engine'!$H$17:$H$64,'Rate Engine'!$Q$17:$Q$64)) | Y59: =IF($C59="","",IF(AND($E59="taken",$G59<>"",$G59<>1),"achievement ignored — restate Filed %",""))
A60: SBA | B60: IN | C60: 46661 | D60: 0.04 | E60: planned | F60: N | G60: 1 | J60: =IF(OR($A60="",$B60=""),"",$A60&"|"&$B60) -> SBA|IN | K60: =IF($C60="","",$D60*IF($E60="planned",IF($G60="",1,$G60),1)) -> 0.04 | L60: =IF($C60="",0,IF(1+$K60>0,LN(1+$K60),0)) -> 0.039220713 | M60: =IF($C60="","",DATE(YEAR($C60),MONTH($C60),1)) -> 46661 | N60: =IF($C60="",0,EOMONTH($C60,0)-$C60+1) -> 31 | O60: =IF($C60="",0,COUNTIFS(rl_key,$J60,rl_effmonth,$M60,rl_eff,"<"&$C60)) -> 0 | P60: =IF($C60="",0,COUNTIFS($J$7:$J60,$J60,$M$7:$M60,$M60,$C$7:$C60,$C60)) -> 1 | Q60: =IF($C60="",0,IF(AND($O60=0,$P60=1),1,0)) -> 1 | R60: =IF($C60="",0,IF(COUNTIFS(rl_key,$J60,rl_effmonth,$M60)>1,1,0)) -> 0 | S60: =IF($C60="",0,COUNTIFS(rl_key,$J60,rl_eff,"<"&$C60)+COUNTIFS($J$7:$J60,$J60,$C$7:$C60,$C60)) -> 2 | T60: =IF(OR($C60="",$E60<>"planned",$C60<DATE(nr_PlanYear,1,1),$C60>DATE(nr_PlanYear,12,31)),0,IF(AND(COUNTIFS(rl_key,$J60,rl_status,"planned",rl_eff,">="&DATE(nr_PlanYear,1,1),rl_eff,"<"&$C60)=0,COUNTIFS($J$7:$J60,$J60,$E$7:$E60,"planned",$C$7:$C60,$C60)=1),1,0)) -> 1 | U60: =IF(OR($C60="",$E60<>"taken"),0,IF(AND(COUNTIFS(rl_key,$J60,rl_effmonth,$M60,rl_eff,"<"&$C60,rl_status,"taken")=0,COUNTIFS($J$7:$J60,$J60,$M$7:$M60,$M60,$C$7:$C60,$C60,$E$7:$E60,"taken")=1),1,0)) -> 0 | V60: =IF($J60="","",IF(COUNTIF(lr_key,$J60)=0,"not in tbl_LR",INDEX(calc_cylr_p,MATCH($J60,lr_key,0)))) -> 0.57533395 | W60: =IF(OR($J60="",COUNTIF(lr_key,$J60)=0),"",(INDEX(calc_cylr_p,MATCH($J60,lr_key,0))-INDEX(calc_lrcur,MATCH($J60,lr_key,0)))*100) -> 0.73339476 | X60: =IF(OR($C60="",$J60<>nr_SelKey),"",(SUMPRODUCT(('Rate Engine'!$G$17:$G$64>YEAR($C60)*12+MONTH($C60)-1)*'Rate Engine'!$H$17:$H$64,'Rate Engine'!$Q$17:$Q$64)+(EOMONTH($C60,0)-$C60+1)/DAY(EOMONTH($C60,0))*SUMPRODUCT(('Rate Engine'!$G$17:$G$64=YEAR($C60)*12+MONTH($C60)-1)*'Rate Engine'!$H$17:$H$64,'Rate Engine'!$Q$17:$Q$64))/SUMPRODUCT('Rate Engine'!$H$17:$H$64,'Rate Engine'!$Q$17:$Q$64)) | Y60: =IF($C60="","",IF(AND($E60="taken",$G60<>"",$G60<>1),"achievement ignored — restate Filed %",""))
A61: SBA | B61: MD | C61: 46113 | D61: 0.03 | E61: taken | F61: Y | J61: =IF(OR($A61="",$B61=""),"",$A61&"|"&$B61) -> SBA|MD | K61: =IF($C61="","",$D61*IF($E61="planned",IF($G61="",1,$G61),1)) -> 0.03 | L61: =IF($C61="",0,IF(1+$K61>0,LN(1+$K61),0)) -> 0.029558802 | M61: =IF($C61="","",DATE(YEAR($C61),MONTH($C61),1)) -> 46113 | N61: =IF($C61="",0,EOMONTH($C61,0)-$C61+1) -> 30 | O61: =IF($C61="",0,COUNTIFS(rl_key,$J61,rl_effmonth,$M61,rl_eff,"<"&$C61)) -> 0 | P61: =IF($C61="",0,COUNTIFS($J$7:$J61,$J61,$M$7:$M61,$M61,$C$7:$C61,$C61)) -> 1 | Q61: =IF($C61="",0,IF(AND($O61=0,$P61=1),1,0)) -> 1 | R61: =IF($C61="",0,IF(COUNTIFS(rl_key,$J61,rl_effmonth,$M61)>1,1,0)) -> 0 | S61: =IF($C61="",0,COUNTIFS(rl_key,$J61,rl_eff,"<"&$C61)+COUNTIFS($J$7:$J61,$J61,$C$7:$C61,$C61)) -> 1 | T61: =IF(OR($C61="",$E61<>"planned",$C61<DATE(nr_PlanYear,1,1),$C61>DATE(nr_PlanYear,12,31)),0,IF(AND(COUNTIFS(rl_key,$J61,rl_status,"planned",rl_eff,">="&DATE(nr_PlanYear,1,1),rl_eff,"<"&$C61)=0,COUNTIFS($J$7:$J61,$J61,$E$7:$E61,"planned",$C$7:$C61,$C61)=1),1,0)) -> 0 | U61: =IF(OR($C61="",$E61<>"taken"),0,IF(AND(COUNTIFS(rl_key,$J61,rl_effmonth,$M61,rl_eff,"<"&$C61,rl_status,"taken")=0,COUNTIFS($J$7:$J61,$J61,$M$7:$M61,$M61,$C$7:$C61,$C61,$E$7:$E61,"taken")=1),1,0)) -> 1 | V61: =IF($J61="","",IF(COUNTIF(lr_key,$J61)=0,"not in tbl_LR",INDEX(calc_cylr_p,MATCH($J61,lr_key,0)))) -> 0.58127308 | W61: =IF(OR($J61="",COUNTIF(lr_key,$J61)=0),"",(INDEX(calc_cylr_p,MATCH($J61,lr_key,0))-INDEX(calc_lrcur,MATCH($J61,lr_key,0)))*100) -> 0.12730845 | X61: =IF(OR($C61="",$J61<>nr_SelKey),"",(SUMPRODUCT(('Rate Engine'!$G$17:$G$64>YEAR($C61)*12+MONTH($C61)-1)*'Rate Engine'!$H$17:$H$64,'Rate Engine'!$Q$17:$Q$64)+(EOMONTH($C61,0)-$C61+1)/DAY(EOMONTH($C61,0))*SUMPRODUCT(('Rate Engine'!$G$17:$G$64=YEAR($C61)*12+MONTH($C61)-1)*'Rate Engine'!$H$17:$H$64,'Rate Engine'!$Q$17:$Q$64))/SUMPRODUCT('Rate Engine'!$H$17:$H$64,'Rate Engine'!$Q$17:$Q$64)) | Y61: =IF($C61="","",IF(AND($E61="taken",$G61<>"",$G61<>1),"achievement ignored — restate Filed %",""))
A62: SBA | B62: MI | C62: 46143 | D62: 0.04 | E62: taken | F62: Y | J62: =IF(OR($A62="",$B62=""),"",$A62&"|"&$B62) -> SBA|MI | K62: =IF($C62="","",$D62*IF($E62="planned",IF($G62="",1,$G62),1)) -> 0.04 | L62: =IF($C62="",0,IF(1+$K62>0,LN(1+$K62),0)) -> 0.039220713 | M62: =IF($C62="","",DATE(YEAR($C62),MONTH($C62),1)) -> 46143 | N62: =IF($C62="",0,EOMONTH($C62,0)-$C62+1) -> 31 | O62: =IF($C62="",0,COUNTIFS(rl_key,$J62,rl_effmonth,$M62,rl_eff,"<"&$C62)) -> 0 | P62: =IF($C62="",0,COUNTIFS($J$7:$J62,$J62,$M$7:$M62,$M62,$C$7:$C62,$C62)) -> 1 | Q62: =IF($C62="",0,IF(AND($O62=0,$P62=1),1,0)) -> 1 | R62: =IF($C62="",0,IF(COUNTIFS(rl_key,$J62,rl_effmonth,$M62)>1,1,0)) -> 0 | S62: =IF($C62="",0,COUNTIFS(rl_key,$J62,rl_eff,"<"&$C62)+COUNTIFS($J$7:$J62,$J62,$C$7:$C62,$C62)) -> 1 | T62: =IF(OR($C62="",$E62<>"planned",$C62<DATE(nr_PlanYear,1,1),$C62>DATE(nr_PlanYear,12,31)),0,IF(AND(COUNTIFS(rl_key,$J62,rl_status,"planned",rl_eff,">="&DATE(nr_PlanYear,1,1),rl_eff,"<"&$C62)=0,COUNTIFS($J$7:$J62,$J62,$E$7:$E62,"planned",$C$7:$C62,$C62)=1),1,0)) -> 0 | U62: =IF(OR($C62="",$E62<>"taken"),0,IF(AND(COUNTIFS(rl_key,$J62,rl_effmonth,$M62,rl_eff,"<"&$C62,rl_status,"taken")=0,COUNTIFS($J$7:$J62,$J62,$M$7:$M62,$M62,$C$7:$C62,$C62,$E$7:$E62,"taken")=1),1,0)) -> 1 | V62: =IF($J62="","",IF(COUNTIF(lr_key,$J62)=0,"not in tbl_LR",INDEX(calc_cylr_p,MATCH($J62,lr_key,0)))) -> 0.5701978 | W62: =IF(OR($J62="",COUNTIF(lr_key,$J62)=0),"",(INDEX(calc_cylr_p,MATCH($J62,lr_key,0))-INDEX(calc_lrcur,MATCH($J62,lr_key,0)))*100) -> 0.61978022 | X62: =IF(OR($C62="",$J62<>nr_SelKey),"",(SUMPRODUCT(('Rate Engine'!$G$17:$G$64>YEAR($C62)*12+MONTH($C62)-1)*'Rate Engine'!$H$17:$H$64,'Rate Engine'!$Q$17:$Q$64)+(EOMONTH($C62,0)-$C62+1)/DAY(EOMONTH($C62,0))*SUMPRODUCT(('Rate Engine'!$G$17:$G$64=YEAR($C62)*12+MONTH($C62)-1)*'Rate Engine'!$H$17:$H$64,'Rate Engine'!$Q$17:$Q$64))/SUMPRODUCT('Rate Engine'!$H$17:$H$64,'Rate Engine'!$Q$17:$Q$64)) | Y62: =IF($C62="","",IF(AND($E62="taken",$G62<>"",$G62<>1),"achievement ignored — restate Filed %",""))
A63: SBA | B63: MN | C63: 46478 | D63: 0.04 | E63: planned | F63: N | G63: 1 | J63: =IF(OR($A63="",$B63=""),"",$A63&"|"&$B63) -> SBA|MN | K63: =IF($C63="","",$D63*IF($E63="planned",IF($G63="",1,$G63),1)) -> 0.04 | L63: =IF($C63="",0,IF(1+$K63>0,LN(1+$K63),0)) -> 0.039220713 | M63: =IF($C63="","",DATE(YEAR($C63),MONTH($C63),1)) -> 46478 | N63: =IF($C63="",0,EOMONTH($C63,0)-$C63+1) -> 30 | O63: =IF($C63="",0,COUNTIFS(rl_key,$J63,rl_effmonth,$M63,rl_eff,"<"&$C63)) -> 0 | P63: =IF($C63="",0,COUNTIFS($J$7:$J63,$J63,$M$7:$M63,$M63,$C$7:$C63,$C63)) -> 1 | Q63: =IF($C63="",0,IF(AND($O63=0,$P63=1),1,0)) -> 1 | R63: =IF($C63="",0,IF(COUNTIFS(rl_key,$J63,rl_effmonth,$M63)>1,1,0)) -> 0 | S63: =IF($C63="",0,COUNTIFS(rl_key,$J63,rl_eff,"<"&$C63)+COUNTIFS($J$7:$J63,$J63,$C$7:$C63,$C63)) -> 1 | T63: =IF(OR($C63="",$E63<>"planned",$C63<DATE(nr_PlanYear,1,1),$C63>DATE(nr_PlanYear,12,31)),0,IF(AND(COUNTIFS(rl_key,$J63,rl_status,"planned",rl_eff,">="&DATE(nr_PlanYear,1,1),rl_eff,"<"&$C63)=0,COUNTIFS($J$7:$J63,$J63,$E$7:$E63,"planned",$C$7:$C63,$C63)=1),1,0)) -> 1 | U63: =IF(OR($C63="",$E63<>"taken"),0,IF(AND(COUNTIFS(rl_key,$J63,rl_effmonth,$M63,rl_eff,"<"&$C63,rl_status,"taken")=0,COUNTIFS($J$7:$J63,$J63,$M$7:$M63,$M63,$C$7:$C63,$C63,$E$7:$E63,"taken")=1),1,0)) -> 0 | V63: =IF($J63="","",IF(COUNTIF(lr_key,$J63)=0,"not in tbl_LR",INDEX(calc_cylr_p,MATCH($J63,lr_key,0)))) -> 0.58293376 | W63: =IF(OR($J63="",COUNTIF(lr_key,$J63)=0),"",(INDEX(calc_cylr_p,MATCH($J63,lr_key,0))-INDEX(calc_lrcur,MATCH($J63,lr_key,0)))*100) -> -0.90662428 | X63: =IF(OR($C63="",$J63<>nr_SelKey),"",(SUMPRODUCT(('Rate Engine'!$G$17:$G$64>YEAR($C63)*12+MONTH($C63)-1)*'Rate Engine'!$H$17:$H$64,'Rate Engine'!$Q$17:$Q$64)+(EOMONTH($C63,0)-$C63+1)/DAY(EOMONTH($C63,0))*SUMPRODUCT(('Rate Engine'!$G$17:$G$64=YEAR($C63)*12+MONTH($C63)-1)*'Rate Engine'!$H$17:$H$64,'Rate Engine'!$Q$17:$Q$64))/SUMPRODUCT('Rate Engine'!$H$17:$H$64,'Rate Engine'!$Q$17:$Q$64)) | Y63: =IF($C63="","",IF(AND($E63="taken",$G63<>"",$G63<>1),"achievement ignored — restate Filed %",""))
A64: SBA | B64: NM | C64: 46204 | D64: 0.06 | E64: taken | F64: Y | J64: =IF(OR($A64="",$B64=""),"",$A64&"|"&$B64) -> SBA|NM | K64: =IF($C64="","",$D64*IF($E64="planned",IF($G64="",1,$G64),1)) -> 0.06 | L64: =IF($C64="",0,IF(1+$K64>0,LN(1+$K64),0)) -> 0.058268908 | M64: =IF($C64="","",DATE(YEAR($C64),MONTH($C64),1)) -> 46204 | N64: =IF($C64="",0,EOMONTH($C64,0)-$C64+1) -> 31 | O64: =IF($C64="",0,COUNTIFS(rl_key,$J64,rl_effmonth,$M64,rl_eff,"<"&$C64)) -> 0 | P64: =IF($C64="",0,COUNTIFS($J$7:$J64,$J64,$M$7:$M64,$M64,$C$7:$C64,$C64)) -> 1 | Q64: =IF($C64="",0,IF(AND($O64=0,$P64=1),1,0)) -> 1 | R64: =IF($C64="",0,IF(COUNTIFS(rl_key,$J64,rl_effmonth,$M64)>1,1,0)) -> 0 | S64: =IF($C64="",0,COUNTIFS(rl_key,$J64,rl_eff,"<"&$C64)+COUNTIFS($J$7:$J64,$J64,$C$7:$C64,$C64)) -> 1 | T64: =IF(OR($C64="",$E64<>"planned",$C64<DATE(nr_PlanYear,1,1),$C64>DATE(nr_PlanYear,12,31)),0,IF(AND(COUNTIFS(rl_key,$J64,rl_status,"planned",rl_eff,">="&DATE(nr_PlanYear,1,1),rl_eff,"<"&$C64)=0,COUNTIFS($J$7:$J64,$J64,$E$7:$E64,"planned",$C$7:$C64,$C64)=1),1,0)) -> 0 | U64: =IF(OR($C64="",$E64<>"taken"),0,IF(AND(COUNTIFS(rl_key,$J64,rl_effmonth,$M64,rl_eff,"<"&$C64,rl_status,"taken")=0,COUNTIFS($J$7:$J64,$J64,$M$7:$M64,$M64,$C$7:$C64,$C64,$E$7:$E64,"taken")=1),1,0)) -> 1 | V64: =IF($J64="","",IF(COUNTIF(lr_key,$J64)=0,"not in tbl_LR",INDEX(calc_cylr_p,MATCH($J64,lr_key,0)))) -> 0.58360993 | W64: =IF(OR($J64="",COUNTIF(lr_key,$J64)=0),"",(INDEX(calc_cylr_p,MATCH($J64,lr_key,0))-INDEX(calc_lrcur,MATCH($J64,lr_key,0)))*100) -> 0.76099321 | X64: =IF(OR($C64="",$J64<>nr_SelKey),"",(SUMPRODUCT(('Rate Engine'!$G$17:$G$64>YEAR($C64)*12+MONTH($C64)-1)*'Rate Engine'!$H$17:$H$64,'Rate Engine'!$Q$17:$Q$64)+(EOMONTH($C64,0)-$C64+1)/DAY(EOMONTH($C64,0))*SUMPRODUCT(('Rate Engine'!$G$17:$G$64=YEAR($C64)*12+MONTH($C64)-1)*'Rate Engine'!$H$17:$H$64,'Rate Engine'!$Q$17:$Q$64))/SUMPRODUCT('Rate Engine'!$H$17:$H$64,'Rate Engine'!$Q$17:$Q$64)) | Y64: =IF($C64="","",IF(AND($E64="taken",$G64<>"",$G64<>1),"achievement ignored — restate Filed %",""))
A65: SBA | B65: NC | C65: 46235 | D65: 0.02 | E65: taken | F65: Y | J65: =IF(OR($A65="",$B65=""),"",$A65&"|"&$B65) -> SBA|NC | K65: =IF($C65="","",$D65*IF($E65="planned",IF($G65="",1,$G65),1)) -> 0.02 | L65: =IF($C65="",0,IF(1+$K65>0,LN(1+$K65),0)) -> 0.019802627 | M65: =IF($C65="","",DATE(YEAR($C65),MONTH($C65),1)) -> 46235 | N65: =IF($C65="",0,EOMONTH($C65,0)-$C65+1) -> 31 | O65: =IF($C65="",0,COUNTIFS(rl_key,$J65,rl_effmonth,$M65,rl_eff,"<"&$C65)) -> 0 | P65: =IF($C65="",0,COUNTIFS($J$7:$J65,$J65,$M$7:$M65,$M65,$C$7:$C65,$C65)) -> 1 | Q65: =IF($C65="",0,IF(AND($O65=0,$P65=1),1,0)) -> 1 | R65: =IF($C65="",0,IF(COUNTIFS(rl_key,$J65,rl_effmonth,$M65)>1,1,0)) -> 0 | S65: =IF($C65="",0,COUNTIFS(rl_key,$J65,rl_eff,"<"&$C65)+COUNTIFS($J$7:$J65,$J65,$C$7:$C65,$C65)) -> 1 | T65: =IF(OR($C65="",$E65<>"planned",$C65<DATE(nr_PlanYear,1,1),$C65>DATE(nr_PlanYear,12,31)),0,IF(AND(COUNTIFS(rl_key,$J65,rl_status,"planned",rl_eff,">="&DATE(nr_PlanYear,1,1),rl_eff,"<"&$C65)=0,COUNTIFS($J$7:$J65,$J65,$E$7:$E65,"planned",$C$7:$C65,$C65)=1),1,0)) -> 0 | U65: =IF(OR($C65="",$E65<>"taken"),0,IF(AND(COUNTIFS(rl_key,$J65,rl_effmonth,$M65,rl_eff,"<"&$C65,rl_status,"taken")=0,COUNTIFS($J$7:$J65,$J65,$M$7:$M65,$M65,$C$7:$C65,$C65,$E$7:$E65,"taken")=1),1,0)) -> 1 | V65: =IF($J65="","",IF(COUNTIF(lr_key,$J65)=0,"not in tbl_LR",INDEX(calc_cylr_p,MATCH($J65,lr_key,0)))) -> 0.56375752 | W65: =IF(OR($J65="",COUNTIF(lr_key,$J65)=0),"",(INDEX(calc_cylr_p,MATCH($J65,lr_key,0))-INDEX(calc_lrcur,MATCH($J65,lr_key,0)))*100) -> 0.37575239 | X65: =IF(OR($C65="",$J65<>nr_SelKey),"",(SUMPRODUCT(('Rate Engine'!$G$17:$G$64>YEAR($C65)*12+MONTH($C65)-1)*'Rate Engine'!$H$17:$H$64,'Rate Engine'!$Q$17:$Q$64)+(EOMONTH($C65,0)-$C65+1)/DAY(EOMONTH($C65,0))*SUMPRODUCT(('Rate Engine'!$G$17:$G$64=YEAR($C65)*12+MONTH($C65)-1)*'Rate Engine'!$H$17:$H$64,'Rate Engine'!$Q$17:$Q$64))/SUMPRODUCT('Rate Engine'!$H$17:$H$64,'Rate Engine'!$Q$17:$Q$64)) | Y65: =IF($C65="","",IF(AND($E65="taken",$G65<>"",$G65<>1),"achievement ignored — restate Filed %",""))
A66: SBA | B66: PA | C66: 46296 | D66: 0.04 | E66: taken | F66: Y | J66: =IF(OR($A66="",$B66=""),"",$A66&"|"&$B66) -> SBA|PA | K66: =IF($C66="","",$D66*IF($E66="planned",IF($G66="",1,$G66),1)) -> 0.04 | L66: =IF($C66="",0,IF(1+$K66>0,LN(1+$K66),0)) -> 0.039220713 | M66: =IF($C66="","",DATE(YEAR($C66),MONTH($C66),1)) -> 46296 | N66: =IF($C66="",0,EOMONTH($C66,0)-$C66+1) -> 31 | O66: =IF($C66="",0,COUNTIFS(rl_key,$J66,rl_effmonth,$M66,rl_eff,"<"&$C66)) -> 0 | P66: =IF($C66="",0,COUNTIFS($J$7:$J66,$J66,$M$7:$M66,$M66,$C$7:$C66,$C66)) -> 1 | Q66: =IF($C66="",0,IF(AND($O66=0,$P66=1),1,0)) -> 1 | R66: =IF($C66="",0,IF(COUNTIFS(rl_key,$J66,rl_effmonth,$M66)>1,1,0)) -> 0 | S66: =IF($C66="",0,COUNTIFS(rl_key,$J66,rl_eff,"<"&$C66)+COUNTIFS($J$7:$J66,$J66,$C$7:$C66,$C66)) -> 1 | T66: =IF(OR($C66="",$E66<>"planned",$C66<DATE(nr_PlanYear,1,1),$C66>DATE(nr_PlanYear,12,31)),0,IF(AND(COUNTIFS(rl_key,$J66,rl_status,"planned",rl_eff,">="&DATE(nr_PlanYear,1,1),rl_eff,"<"&$C66)=0,COUNTIFS($J$7:$J66,$J66,$E$7:$E66,"planned",$C$7:$C66,$C66)=1),1,0)) -> 0 | U66: =IF(OR($C66="",$E66<>"taken"),0,IF(AND(COUNTIFS(rl_key,$J66,rl_effmonth,$M66,rl_eff,"<"&$C66,rl_status,"taken")=0,COUNTIFS($J$7:$J66,$J66,$M$7:$M66,$M66,$C$7:$C66,$C66,$E$7:$E66,"taken")=1),1,0)) -> 1 | V66: =IF($J66="","",IF(COUNTIF(lr_key,$J66)=0,"not in tbl_LR",INDEX(calc_cylr_p,MATCH($J66,lr_key,0)))) -> 0.57441174 | W66: =IF(OR($J66="",COUNTIF(lr_key,$J66)=0),"",(INDEX(calc_cylr_p,MATCH($J66,lr_key,0))-INDEX(calc_lrcur,MATCH($J66,lr_key,0)))*100) -> 0.2411736 | X66: =IF(OR($C66="",$J66<>nr_SelKey),"",(SUMPRODUCT(('Rate Engine'!$G$17:$G$64>YEAR($C66)*12+MONTH($C66)-1)*'Rate Engine'!$H$17:$H$64,'Rate Engine'!$Q$17:$Q$64)+(EOMONTH($C66,0)-$C66+1)/DAY(EOMONTH($C66,0))*SUMPRODUCT(('Rate Engine'!$G$17:$G$64=YEAR($C66)*12+MONTH($C66)-1)*'Rate Engine'!$H$17:$H$64,'Rate Engine'!$Q$17:$Q$64))/SUMPRODUCT('Rate Engine'!$H$17:$H$64,'Rate Engine'!$Q$17:$Q$64)) | Y66: =IF($C66="","",IF(AND($E66="taken",$G66<>"",$G66<>1),"achievement ignored — restate Filed %",""))
A67: SBA | B67: PA | C67: 46600 | D67: 0.04 | E67: planned | F67: N | G67: 1 | J67: =IF(OR($A67="",$B67=""),"",$A67&"|"&$B67) -> SBA|PA | K67: =IF($C67="","",$D67*IF($E67="planned",IF($G67="",1,$G67),1)) -> 0.04 | L67: =IF($C67="",0,IF(1+$K67>0,LN(1+$K67),0)) -> 0.039220713 | M67: =IF($C67="","",DATE(YEAR($C67),MONTH($C67),1)) -> 46600 | N67: =IF($C67="",0,EOMONTH($C67,0)-$C67+1) -> 31 | O67: =IF($C67="",0,COUNTIFS(rl_key,$J67,rl_effmonth,$M67,rl_eff,"<"&$C67)) -> 0 | P67: =IF($C67="",0,COUNTIFS($J$7:$J67,$J67,$M$7:$M67,$M67,$C$7:$C67,$C67)) -> 1 | Q67: =IF($C67="",0,IF(AND($O67=0,$P67=1),1,0)) -> 1 | R67: =IF($C67="",0,IF(COUNTIFS(rl_key,$J67,rl_effmonth,$M67)>1,1,0)) -> 0 | S67: =IF($C67="",0,COUNTIFS(rl_key,$J67,rl_eff,"<"&$C67)+COUNTIFS($J$7:$J67,$J67,$C$7:$C67,$C67)) -> 2 | T67: =IF(OR($C67="",$E67<>"planned",$C67<DATE(nr_PlanYear,1,1),$C67>DATE(nr_PlanYear,12,31)),0,IF(AND(COUNTIFS(rl_key,$J67,rl_status,"planned",rl_eff,">="&DATE(nr_PlanYear,1,1),rl_eff,"<"&$C67)=0,COUNTIFS($J$7:$J67,$J67,$E$7:$E67,"planned",$C$7:$C67,$C67)=1),1,0)) -> 1 | U67: =IF(OR($C67="",$E67<>"taken"),0,IF(AND(COUNTIFS(rl_key,$J67,rl_effmonth,$M67,rl_eff,"<"&$C67,rl_status,"taken")=0,COUNTIFS($J$7:$J67,$J67,$M$7:$M67,$M67,$C$7:$C67,$C67,$E$7:$E67,"taken")=1),1,0)) -> 0 | V67: =IF($J67="","",IF(COUNTIF(lr_key,$J67)=0,"not in tbl_LR",INDEX(calc_cylr_p,MATCH($J67,lr_key,0)))) -> 0.57441174 | W67: =IF(OR($J67="",COUNTIF(lr_key,$J67)=0),"",(INDEX(calc_cylr_p,MATCH($J67,lr_key,0))-INDEX(calc_lrcur,MATCH($J67,lr_key,0)))*100) -> 0.2411736 | X67: =IF(OR($C67="",$J67<>nr_SelKey),"",(SUMPRODUCT(('Rate Engine'!$G$17:$G$64>YEAR($C67)*12+MONTH($C67)-1)*'Rate Engine'!$H$17:$H$64,'Rate Engine'!$Q$17:$Q$64)+(EOMONTH($C67,0)-$C67+1)/DAY(EOMONTH($C67,0))*SUMPRODUCT(('Rate Engine'!$G$17:$G$64=YEAR($C67)*12+MONTH($C67)-1)*'Rate Engine'!$H$17:$H$64,'Rate Engine'!$Q$17:$Q$64))/SUMPRODUCT('Rate Engine'!$H$17:$H$64,'Rate Engine'!$Q$17:$Q$64)) | Y67: =IF($C67="","",IF(AND($E67="taken",$G67<>"",$G67<>1),"achievement ignored — restate Filed %",""))
A68: SBA | B68: SC | C68: 46327 | D68: 0.05 | E68: taken | F68: Y | J68: =IF(OR($A68="",$B68=""),"",$A68&"|"&$B68) -> SBA|SC | K68: =IF($C68="","",$D68*IF($E68="planned",IF($G68="",1,$G68),1)) -> 0.05 | L68: =IF($C68="",0,IF(1+$K68>0,LN(1+$K68),0)) -> 0.048790164 | M68: =IF($C68="","",DATE(YEAR($C68),MONTH($C68),1)) -> 46327 | N68: =IF($C68="",0,EOMONTH($C68,0)-$C68+1) -> 30 | O68: =IF($C68="",0,COUNTIFS(rl_key,$J68,rl_effmonth,$M68,rl_eff,"<"&$C68)) -> 0 | P68: =IF($C68="",0,COUNTIFS($J$7:$J68,$J68,$M$7:$M68,$M68,$C$7:$C68,$C68)) -> 1 | Q68: =IF($C68="",0,IF(AND($O68=0,$P68=1),1,0)) -> 1 | R68: =IF($C68="",0,IF(COUNTIFS(rl_key,$J68,rl_effmonth,$M68)>1,1,0)) -> 0 | S68: =IF($C68="",0,COUNTIFS(rl_key,$J68,rl_eff,"<"&$C68)+COUNTIFS($J$7:$J68,$J68,$C$7:$C68,$C68)) -> 1 | T68: =IF(OR($C68="",$E68<>"planned",$C68<DATE(nr_PlanYear,1,1),$C68>DATE(nr_PlanYear,12,31)),0,IF(AND(COUNTIFS(rl_key,$J68,rl_status,"planned",rl_eff,">="&DATE(nr_PlanYear,1,1),rl_eff,"<"&$C68)=0,COUNTIFS($J$7:$J68,$J68,$E$7:$E68,"planned",$C$7:$C68,$C68)=1),1,0)) -> 0 | U68: =IF(OR($C68="",$E68<>"taken"),0,IF(AND(COUNTIFS(rl_key,$J68,rl_effmonth,$M68,rl_eff,"<"&$C68,rl_status,"taken")=0,COUNTIFS($J$7:$J68,$J68,$M$7:$M68,$M68,$C$7:$C68,$C68,$E$7:$E68,"taken")=1),1,0)) -> 1 | V68: =IF($J68="","",IF(COUNTIF(lr_key,$J68)=0,"not in tbl_LR",INDEX(calc_cylr_p,MATCH($J68,lr_key,0)))) -> 0.60451548 | W68: =IF(OR($J68="",COUNTIF(lr_key,$J68)=0),"",(INDEX(calc_cylr_p,MATCH($J68,lr_key,0))-INDEX(calc_lrcur,MATCH($J68,lr_key,0)))*100) -> 0.45154785 | X68: =IF(OR($C68="",$J68<>nr_SelKey),"",(SUMPRODUCT(('Rate Engine'!$G$17:$G$64>YEAR($C68)*12+MONTH($C68)-1)*'Rate Engine'!$H$17:$H$64,'Rate Engine'!$Q$17:$Q$64)+(EOMONTH($C68,0)-$C68+1)/DAY(EOMONTH($C68,0))*SUMPRODUCT(('Rate Engine'!$G$17:$G$64=YEAR($C68)*12+MONTH($C68)-1)*'Rate Engine'!$H$17:$H$64,'Rate Engine'!$Q$17:$Q$64))/SUMPRODUCT('Rate Engine'!$H$17:$H$64,'Rate Engine'!$Q$17:$Q$64)) | Y68: =IF($C68="","",IF(AND($E68="taken",$G68<>"",$G68<>1),"achievement ignored — restate Filed %",""))
A69: SBA | B69: VA | C69: 46023 | D69: 0.02 | E69: taken | F69: Y | J69: =IF(OR($A69="",$B69=""),"",$A69&"|"&$B69) -> SBA|VA | K69: =IF($C69="","",$D69*IF($E69="planned",IF($G69="",1,$G69),1)) -> 0.02 | L69: =IF($C69="",0,IF(1+$K69>0,LN(1+$K69),0)) -> 0.019802627 | M69: =IF($C69="","",DATE(YEAR($C69),MONTH($C69),1)) -> 46023 | N69: =IF($C69="",0,EOMONTH($C69,0)-$C69+1) -> 31 | O69: =IF($C69="",0,COUNTIFS(rl_key,$J69,rl_effmonth,$M69,rl_eff,"<"&$C69)) -> 0 | P69: =IF($C69="",0,COUNTIFS($J$7:$J69,$J69,$M$7:$M69,$M69,$C$7:$C69,$C69)) -> 1 | Q69: =IF($C69="",0,IF(AND($O69=0,$P69=1),1,0)) -> 1 | R69: =IF($C69="",0,IF(COUNTIFS(rl_key,$J69,rl_effmonth,$M69)>1,1,0)) -> 0 | S69: =IF($C69="",0,COUNTIFS(rl_key,$J69,rl_eff,"<"&$C69)+COUNTIFS($J$7:$J69,$J69,$C$7:$C69,$C69)) -> 1 | T69: =IF(OR($C69="",$E69<>"planned",$C69<DATE(nr_PlanYear,1,1),$C69>DATE(nr_PlanYear,12,31)),0,IF(AND(COUNTIFS(rl_key,$J69,rl_status,"planned",rl_eff,">="&DATE(nr_PlanYear,1,1),rl_eff,"<"&$C69)=0,COUNTIFS($J$7:$J69,$J69,$E$7:$E69,"planned",$C$7:$C69,$C69)=1),1,0)) -> 0 | U69: =IF(OR($C69="",$E69<>"taken"),0,IF(AND(COUNTIFS(rl_key,$J69,rl_effmonth,$M69,rl_eff,"<"&$C69,rl_status,"taken")=0,COUNTIFS($J$7:$J69,$J69,$M$7:$M69,$M69,$C$7:$C69,$C69,$E$7:$E69,"taken")=1),1,0)) -> 1 | V69: =IF($J69="","",IF(COUNTIF(lr_key,$J69)=0,"not in tbl_LR",INDEX(calc_cylr_p,MATCH($J69,lr_key,0)))) -> 0.57048733 | W69: =IF(OR($J69="",COUNTIF(lr_key,$J69)=0),"",(INDEX(calc_cylr_p,MATCH($J69,lr_key,0))-INDEX(calc_lrcur,MATCH($J69,lr_key,0)))*100) -> 0.24873337 | X69: =IF(OR($C69="",$J69<>nr_SelKey),"",(SUMPRODUCT(('Rate Engine'!$G$17:$G$64>YEAR($C69)*12+MONTH($C69)-1)*'Rate Engine'!$H$17:$H$64,'Rate Engine'!$Q$17:$Q$64)+(EOMONTH($C69,0)-$C69+1)/DAY(EOMONTH($C69,0))*SUMPRODUCT(('Rate Engine'!$G$17:$G$64=YEAR($C69)*12+MONTH($C69)-1)*'Rate Engine'!$H$17:$H$64,'Rate Engine'!$Q$17:$Q$64))/SUMPRODUCT('Rate Engine'!$H$17:$H$64,'Rate Engine'!$Q$17:$Q$64)) | Y69: =IF($C69="","",IF(AND($E69="taken",$G69<>"",$G69<>1),"achievement ignored — restate Filed %",""))
A70: SBA | B70: WV | C70: 46054 | D70: 0.03 | E70: taken | F70: Y | J70: =IF(OR($A70="",$B70=""),"",$A70&"|"&$B70) -> SBA|WV | K70: =IF($C70="","",$D70*IF($E70="planned",IF($G70="",1,$G70),1)) -> 0.03 | L70: =IF($C70="",0,IF(1+$K70>0,LN(1+$K70),0)) -> 0.029558802 | M70: =IF($C70="","",DATE(YEAR($C70),MONTH($C70),1)) -> 46054 | N70: =IF($C70="",0,EOMONTH($C70,0)-$C70+1) -> 28 | O70: =IF($C70="",0,COUNTIFS(rl_key,$J70,rl_effmonth,$M70,rl_eff,"<"&$C70)) -> 0 | P70: =IF($C70="",0,COUNTIFS($J$7:$J70,$J70,$M$7:$M70,$M70,$C$7:$C70,$C70)) -> 1 | Q70: =IF($C70="",0,IF(AND($O70=0,$P70=1),1,0)) -> 1 | R70: =IF($C70="",0,IF(COUNTIFS(rl_key,$J70,rl_effmonth,$M70)>1,1,0)) -> 0 | S70: =IF($C70="",0,COUNTIFS(rl_key,$J70,rl_eff,"<"&$C70)+COUNTIFS($J$7:$J70,$J70,$C$7:$C70,$C70)) -> 1 | T70: =IF(OR($C70="",$E70<>"planned",$C70<DATE(nr_PlanYear,1,1),$C70>DATE(nr_PlanYear,12,31)),0,IF(AND(COUNTIFS(rl_key,$J70,rl_status,"planned",rl_eff,">="&DATE(nr_PlanYear,1,1),rl_eff,"<"&$C70)=0,COUNTIFS($J$7:$J70,$J70,$E$7:$E70,"planned",$C$7:$C70,$C70)=1),1,0)) -> 0 | U70: =IF(OR($C70="",$E70<>"taken"),0,IF(AND(COUNTIFS(rl_key,$J70,rl_effmonth,$M70,rl_eff,"<"&$C70,rl_status,"taken")=0,COUNTIFS($J$7:$J70,$J70,$M$7:$M70,$M70,$C$7:$C70,$C70,$E$7:$E70,"taken")=1),1,0)) -> 1 | V70: =IF($J70="","",IF(COUNTIF(lr_key,$J70)=0,"not in tbl_LR",INDEX(calc_cylr_p,MATCH($J70,lr_key,0)))) -> 0.58818912 | W70: =IF(OR($J70="",COUNTIF(lr_key,$J70)=0),"",(INDEX(calc_cylr_p,MATCH($J70,lr_key,0))-INDEX(calc_lrcur,MATCH($J70,lr_key,0)))*100) -> -0.78108774 | X70: =IF(OR($C70="",$J70<>nr_SelKey),"",(SUMPRODUCT(('Rate Engine'!$G$17:$G$64>YEAR($C70)*12+MONTH($C70)-1)*'Rate Engine'!$H$17:$H$64,'Rate Engine'!$Q$17:$Q$64)+(EOMONTH($C70,0)-$C70+1)/DAY(EOMONTH($C70,0))*SUMPRODUCT(('Rate Engine'!$G$17:$G$64=YEAR($C70)*12+MONTH($C70)-1)*'Rate Engine'!$H$17:$H$64,'Rate Engine'!$Q$17:$Q$64))/SUMPRODUCT('Rate Engine'!$H$17:$H$64,'Rate Engine'!$Q$17:$Q$64)) | Y70: =IF($C70="","",IF(AND($E70="taken",$G70<>"",$G70<>1),"achievement ignored — restate Filed %",""))
A71: SBA | B71: WV | C71: 46419 | D71: 0.04 | E71: planned | F71: N | G71: 1 | J71: =IF(OR($A71="",$B71=""),"",$A71&"|"&$B71) -> SBA|WV | K71: =IF($C71="","",$D71*IF($E71="planned",IF($G71="",1,$G71),1)) -> 0.04 | L71: =IF($C71="",0,IF(1+$K71>0,LN(1+$K71),0)) -> 0.039220713 | M71: =IF($C71="","",DATE(YEAR($C71),MONTH($C71),1)) -> 46419 | N71: =IF($C71="",0,EOMONTH($C71,0)-$C71+1) -> 28 | O71: =IF($C71="",0,COUNTIFS(rl_key,$J71,rl_effmonth,$M71,rl_eff,"<"&$C71)) -> 0 | P71: =IF($C71="",0,COUNTIFS($J$7:$J71,$J71,$M$7:$M71,$M71,$C$7:$C71,$C71)) -> 1 | Q71: =IF($C71="",0,IF(AND($O71=0,$P71=1),1,0)) -> 1 | R71: =IF($C71="",0,IF(COUNTIFS(rl_key,$J71,rl_effmonth,$M71)>1,1,0)) -> 0 | S71: =IF($C71="",0,COUNTIFS(rl_key,$J71,rl_eff,"<"&$C71)+COUNTIFS($J$7:$J71,$J71,$C$7:$C71,$C71)) -> 2 | T71: =IF(OR($C71="",$E71<>"planned",$C71<DATE(nr_PlanYear,1,1),$C71>DATE(nr_PlanYear,12,31)),0,IF(AND(COUNTIFS(rl_key,$J71,rl_status,"planned",rl_eff,">="&DATE(nr_PlanYear,1,1),rl_eff,"<"&$C71)=0,COUNTIFS($J$7:$J71,$J71,$E$7:$E71,"planned",$C$7:$C71,$C71)=1),1,0)) -> 1 | U71: =IF(OR($C71="",$E71<>"taken"),0,IF(AND(COUNTIFS(rl_key,$J71,rl_effmonth,$M71,rl_eff,"<"&$C71,rl_status,"taken")=0,COUNTIFS($J$7:$J71,$J71,$M$7:$M71,$M71,$C$7:$C71,$C71,$E$7:$E71,"taken")=1),1,0)) -> 0 | V71: =IF($J71="","",IF(COUNTIF(lr_key,$J71)=0,"not in tbl_LR",INDEX(calc_cylr_p,MATCH($J71,lr_key,0)))) -> 0.58818912 | W71: =IF(OR($J71="",COUNTIF(lr_key,$J71)=0),"",(INDEX(calc_cylr_p,MATCH($J71,lr_key,0))-INDEX(calc_lrcur,MATCH($J71,lr_key,0)))*100) -> -0.78108774 | X71: =IF(OR($C71="",$J71<>nr_SelKey),"",(SUMPRODUCT(('Rate Engine'!$G$17:$G$64>YEAR($C71)*12+MONTH($C71)-1)*'Rate Engine'!$H$17:$H$64,'Rate Engine'!$Q$17:$Q$64)+(EOMONTH($C71,0)-$C71+1)/DAY(EOMONTH($C71,0))*SUMPRODUCT(('Rate Engine'!$G$17:$G$64=YEAR($C71)*12+MONTH($C71)-1)*'Rate Engine'!$H$17:$H$64,'Rate Engine'!$Q$17:$Q$64))/SUMPRODUCT('Rate Engine'!$H$17:$H$64,'Rate Engine'!$Q$17:$Q$64)) | Y71: =IF($C71="","",IF(AND($E71="taken",$G71<>"",$G71<>1),"achievement ignored — restate Filed %",""))
J72: =IF(OR($A72="",$B72=""),"",$A72&"|"&$B72) | K72: =IF($C72="","",$D72*IF($E72="planned",IF($G72="",1,$G72),1)) | L72: =IF($C72="",0,IF(1+$K72>0,LN(1+$K72),0)) -> 0 | M72: =IF($C72="","",DATE(YEAR($C72),MONTH($C72),1)) | N72: =IF($C72="",0,EOMONTH($C72,0)-$C72+1) -> 0 | O72: =IF($C72="",0,COUNTIFS(rl_key,$J72,rl_effmonth,$M72,rl_eff,"<"&$C72)) -> 0 | P72: =IF($C72="",0,COUNTIFS($J$7:$J72,$J72,$M$7:$M72,$M72,$C$7:$C72,$C72)) -> 0 | Q72: =IF($C72="",0,IF(AND($O72=0,$P72=1),1,0)) -> 0 | R72: =IF($C72="",0,IF(COUNTIFS(rl_key,$J72,rl_effmonth,$M72)>1,1,0)) -> 0 | S72: =IF($C72="",0,COUNTIFS(rl_key,$J72,rl_eff,"<"&$C72)+COUNTIFS($J$7:$J72,$J72,$C$7:$C72,$C72)) -> 0 | T72: =IF(OR($C72="",$E72<>"planned",$C72<DATE(nr_PlanYear,1,1),$C72>DATE(nr_PlanYear,12,31)),0,IF(AND(COUNTIFS(rl_key,$J72,rl_status,"planned",rl_eff,">="&DATE(nr_PlanYear,1,1),rl_eff,"<"&$C72)=0,COUNTIFS($J$7:$J72,$J72,$E$7:$E72,"planned",$C$7:$C72,$C72)=1),1,0)) -> 0 | U72: =IF(OR($C72="",$E72<>"taken"),0,IF(AND(COUNTIFS(rl_key,$J72,rl_effmonth,$M72,rl_eff,"<"&$C72,rl_status,"taken")=0,COUNTIFS($J$7:$J72,$J72,$M$7:$M72,$M72,$C$7:$C72,$C72,$E$7:$E72,"taken")=1),1,0)) -> 0 | V72: =IF($J72="","",IF(COUNTIF(lr_key,$J72)=0,"not in tbl_LR",INDEX(calc_cylr_p,MATCH($J72,lr_key,0)))) | W72: =IF(OR($J72="",COUNTIF(lr_key,$J72)=0),"",(INDEX(calc_cylr_p,MATCH($J72,lr_key,0))-INDEX(calc_lrcur,MATCH($J72,lr_key,0)))*100) | X72: =IF(OR($C72="",$J72<>nr_SelKey),"",(SUMPRODUCT(('Rate Engine'!$G$17:$G$64>YEAR($C72)*12+MONTH($C72)-1)*'Rate Engine'!$H$17:$H$64,'Rate Engine'!$Q$17:$Q$64)+(EOMONTH($C72,0)-$C72+1)/DAY(EOMONTH($C72,0))*SUMPRODUCT(('Rate Engine'!$G$17:$G$64=YEAR($C72)*12+MONTH($C72)-1)*'Rate Engine'!$H$17:$H$64,'Rate Engine'!$Q$17:$Q$64))/SUMPRODUCT('Rate Engine'!$H$17:$H$64,'Rate Engine'!$Q$17:$Q$64)) | Y72: =IF($C72="","",IF(AND($E72="taken",$G72<>"",$G72<>1),"achievement ignored — restate Filed %",""))
J73: =IF(OR($A73="",$B73=""),"",$A73&"|"&$B73) | K73: =IF($C73="","",$D73*IF($E73="planned",IF($G73="",1,$G73),1)) | L73: =IF($C73="",0,IF(1+$K73>0,LN(1+$K73),0)) -> 0 | M73: =IF($C73="","",DATE(YEAR($C73),MONTH($C73),1)) | N73: =IF($C73="",0,EOMONTH($C73,0)-$C73+1) -> 0 | O73: =IF($C73="",0,COUNTIFS(rl_key,$J73,rl_effmonth,$M73,rl_eff,"<"&$C73)) -> 0 | P73: =IF($C73="",0,COUNTIFS($J$7:$J73,$J73,$M$7:$M73,$M73,$C$7:$C73,$C73)) -> 0 | Q73: =IF($C73="",0,IF(AND($O73=0,$P73=1),1,0)) -> 0 | R73: =IF($C73="",0,IF(COUNTIFS(rl_key,$J73,rl_effmonth,$M73)>1,1,0)) -> 0 | S73: =IF($C73="",0,COUNTIFS(rl_key,$J73,rl_eff,"<"&$C73)+COUNTIFS($J$7:$J73,$J73,$C$7:$C73,$C73)) -> 0 | T73: =IF(OR($C73="",$E73<>"planned",$C73<DATE(nr_PlanYear,1,1),$C73>DATE(nr_PlanYear,12,31)),0,IF(AND(COUNTIFS(rl_key,$J73,rl_status,"planned",rl_eff,">="&DATE(nr_PlanYear,1,1),rl_eff,"<"&$C73)=0,COUNTIFS($J$7:$J73,$J73,$E$7:$E73,"planned",$C$7:$C73,$C73)=1),1,0)) -> 0 | U73: =IF(OR($C73="",$E73<>"taken"),0,IF(AND(COUNTIFS(rl_key,$J73,rl_effmonth,$M73,rl_eff,"<"&$C73,rl_status,"taken")=0,COUNTIFS($J$7:$J73,$J73,$M$7:$M73,$M73,$C$7:$C73,$C73,$E$7:$E73,"taken")=1),1,0)) -> 0 | V73: =IF($J73="","",IF(COUNTIF(lr_key,$J73)=0,"not in tbl_LR",INDEX(calc_cylr_p,MATCH($J73,lr_key,0)))) | W73: =IF(OR($J73="",COUNTIF(lr_key,$J73)=0),"",(INDEX(calc_cylr_p,MATCH($J73,lr_key,0))-INDEX(calc_lrcur,MATCH($J73,lr_key,0)))*100) | X73: =IF(OR($C73="",$J73<>nr_SelKey),"",(SUMPRODUCT(('Rate Engine'!$G$17:$G$64>YEAR($C73)*12+MONTH($C73)-1)*'Rate Engine'!$H$17:$H$64,'Rate Engine'!$Q$17:$Q$64)+(EOMONTH($C73,0)-$C73+1)/DAY(EOMONTH($C73,0))*SUMPRODUCT(('Rate Engine'!$G$17:$G$64=YEAR($C73)*12+MONTH($C73)-1)*'Rate Engine'!$H$17:$H$64,'Rate Engine'!$Q$17:$Q$64))/SUMPRODUCT('Rate Engine'!$H$17:$H$64,'Rate Engine'!$Q$17:$Q$64)) | Y73: =IF($C73="","",IF(AND($E73="taken",$G73<>"",$G73<>1),"achievement ignored — restate Filed %",""))
J74: =IF(OR($A74="",$B74=""),"",$A74&"|"&$B74) | K74: =IF($C74="","",$D74*IF($E74="planned",IF($G74="",1,$G74),1)) | L74: =IF($C74="",0,IF(1+$K74>0,LN(1+$K74),0)) -> 0 | M74: =IF($C74="","",DATE(YEAR($C74),MONTH($C74),1)) | N74: =IF($C74="",0,EOMONTH($C74,0)-$C74+1) -> 0 | O74: =IF($C74="",0,COUNTIFS(rl_key,$J74,rl_effmonth,$M74,rl_eff,"<"&$C74)) -> 0 | P74: =IF($C74="",0,COUNTIFS($J$7:$J74,$J74,$M$7:$M74,$M74,$C$7:$C74,$C74)) -> 0 | Q74: =IF($C74="",0,IF(AND($O74=0,$P74=1),1,0)) -> 0 | R74: =IF($C74="",0,IF(COUNTIFS(rl_key,$J74,rl_effmonth,$M74)>1,1,0)) -> 0 | S74: =IF($C74="",0,COUNTIFS(rl_key,$J74,rl_eff,"<"&$C74)+COUNTIFS($J$7:$J74,$J74,$C$7:$C74,$C74)) -> 0 | T74: =IF(OR($C74="",$E74<>"planned",$C74<DATE(nr_PlanYear,1,1),$C74>DATE(nr_PlanYear,12,31)),0,IF(AND(COUNTIFS(rl_key,$J74,rl_status,"planned",rl_eff,">="&DATE(nr_PlanYear,1,1),rl_eff,"<"&$C74)=0,COUNTIFS($J$7:$J74,$J74,$E$7:$E74,"planned",$C$7:$C74,$C74)=1),1,0)) -> 0 | U74: =IF(OR($C74="",$E74<>"taken"),0,IF(AND(COUNTIFS(rl_key,$J74,rl_effmonth,$M74,rl_eff,"<"&$C74,rl_status,"taken")=0,COUNTIFS($J$7:$J74,$J74,$M$7:$M74,$M74,$C$7:$C74,$C74,$E$7:$E74,"taken")=1),1,0)) -> 0 | V74: =IF($J74="","",IF(COUNTIF(lr_key,$J74)=0,"not in tbl_LR",INDEX(calc_cylr_p,MATCH($J74,lr_key,0)))) | W74: =IF(OR($J74="",COUNTIF(lr_key,$J74)=0),"",(INDEX(calc_cylr_p,MATCH($J74,lr_key,0))-INDEX(calc_lrcur,MATCH($J74,lr_key,0)))*100) | X74: =IF(OR($C74="",$J74<>nr_SelKey),"",(SUMPRODUCT(('Rate Engine'!$G$17:$G$64>YEAR($C74)*12+MONTH($C74)-1)*'Rate Engine'!$H$17:$H$64,'Rate Engine'!$Q$17:$Q$64)+(EOMONTH($C74,0)-$C74+1)/DAY(EOMONTH($C74,0))*SUMPRODUCT(('Rate Engine'!$G$17:$G$64=YEAR($C74)*12+MONTH($C74)-1)*'Rate Engine'!$H$17:$H$64,'Rate Engine'!$Q$17:$Q$64))/SUMPRODUCT('Rate Engine'!$H$17:$H$64,'Rate Engine'!$Q$17:$Q$64)) | Y74: =IF($C74="","",IF(AND($E74="taken",$G74<>"",$G74<>1),"achievement ignored — restate Filed %",""))
J75: =IF(OR($A75="",$B75=""),"",$A75&"|"&$B75) | K75: =IF($C75="","",$D75*IF($E75="planned",IF($G75="",1,$G75),1)) | L75: =IF($C75="",0,IF(1+$K75>0,LN(1+$K75),0)) -> 0 | M75: =IF($C75="","",DATE(YEAR($C75),MONTH($C75),1)) | N75: =IF($C75="",0,EOMONTH($C75,0)-$C75+1) -> 0 | O75: =IF($C75="",0,COUNTIFS(rl_key,$J75,rl_effmonth,$M75,rl_eff,"<"&$C75)) -> 0 | P75: =IF($C75="",0,COUNTIFS($J$7:$J75,$J75,$M$7:$M75,$M75,$C$7:$C75,$C75)) -> 0 | Q75: =IF($C75="",0,IF(AND($O75=0,$P75=1),1,0)) -> 0 | R75: =IF($C75="",0,IF(COUNTIFS(rl_key,$J75,rl_effmonth,$M75)>1,1,0)) -> 0 | S75: =IF($C75="",0,COUNTIFS(rl_key,$J75,rl_eff,"<"&$C75)+COUNTIFS($J$7:$J75,$J75,$C$7:$C75,$C75)) -> 0 | T75: =IF(OR($C75="",$E75<>"planned",$C75<DATE(nr_PlanYear,1,1),$C75>DATE(nr_PlanYear,12,31)),0,IF(AND(COUNTIFS(rl_key,$J75,rl_status,"planned",rl_eff,">="&DATE(nr_PlanYear,1,1),rl_eff,"<"&$C75)=0,COUNTIFS($J$7:$J75,$J75,$E$7:$E75,"planned",$C$7:$C75,$C75)=1),1,0)) -> 0 | U75: =IF(OR($C75="",$E75<>"taken"),0,IF(AND(COUNTIFS(rl_key,$J75,rl_effmonth,$M75,rl_eff,"<"&$C75,rl_status,"taken")=0,COUNTIFS($J$7:$J75,$J75,$M$7:$M75,$M75,$C$7:$C75,$C75,$E$7:$E75,"taken")=1),1,0)) -> 0 | V75: =IF($J75="","",IF(COUNTIF(lr_key,$J75)=0,"not in tbl_LR",INDEX(calc_cylr_p,MATCH($J75,lr_key,0)))) | W75: =IF(OR($J75="",COUNTIF(lr_key,$J75)=0),"",(INDEX(calc_cylr_p,MATCH($J75,lr_key,0))-INDEX(calc_lrcur,MATCH($J75,lr_key,0)))*100) | X75: =IF(OR($C75="",$J75<>nr_SelKey),"",(SUMPRODUCT(('Rate Engine'!$G$17:$G$64>YEAR($C75)*12+MONTH($C75)-1)*'Rate Engine'!$H$17:$H$64,'Rate Engine'!$Q$17:$Q$64)+(EOMONTH($C75,0)-$C75+1)/DAY(EOMONTH($C75,0))*SUMPRODUCT(('Rate Engine'!$G$17:$G$64=YEAR($C75)*12+MONTH($C75)-1)*'Rate Engine'!$H$17:$H$64,'Rate Engine'!$Q$17:$Q$64))/SUMPRODUCT('Rate Engine'!$H$17:$H$64,'Rate Engine'!$Q$17:$Q$64)) | Y75: =IF($C75="","",IF(AND($E75="taken",$G75<>"",$G75<>1),"achievement ignored — restate Filed %",""))
J76: =IF(OR($A76="",$B76=""),"",$A76&"|"&$B76) | K76: =IF($C76="","",$D76*IF($E76="planned",IF($G76="",1,$G76),1)) | L76: =IF($C76="",0,IF(1+$K76>0,LN(1+$K76),0)) -> 0 | M76: =IF($C76="","",DATE(YEAR($C76),MONTH($C76),1)) | N76: =IF($C76="",0,EOMONTH($C76,0)-$C76+1) -> 0 | O76: =IF($C76="",0,COUNTIFS(rl_key,$J76,rl_effmonth,$M76,rl_eff,"<"&$C76)) -> 0 | P76: =IF($C76="",0,COUNTIFS($J$7:$J76,$J76,$M$7:$M76,$M76,$C$7:$C76,$C76)) -> 0 | Q76: =IF($C76="",0,IF(AND($O76=0,$P76=1),1,0)) -> 0 | R76: =IF($C76="",0,IF(COUNTIFS(rl_key,$J76,rl_effmonth,$M76)>1,1,0)) -> 0 | S76: =IF($C76="",0,COUNTIFS(rl_key,$J76,rl_eff,"<"&$C76)+COUNTIFS($J$7:$J76,$J76,$C$7:$C76,$C76)) -> 0 | T76: =IF(OR($C76="",$E76<>"planned",$C76<DATE(nr_PlanYear,1,1),$C76>DATE(nr_PlanYear,12,31)),0,IF(AND(COUNTIFS(rl_key,$J76,rl_status,"planned",rl_eff,">="&DATE(nr_PlanYear,1,1),rl_eff,"<"&$C76)=0,COUNTIFS($J$7:$J76,$J76,$E$7:$E76,"planned",$C$7:$C76,$C76)=1),1,0)) -> 0 | U76: =IF(OR($C76="",$E76<>"taken"),0,IF(AND(COUNTIFS(rl_key,$J76,rl_effmonth,$M76,rl_eff,"<"&$C76,rl_status,"taken")=0,COUNTIFS($J$7:$J76,$J76,$M$7:$M76,$M76,$C$7:$C76,$C76,$E$7:$E76,"taken")=1),1,0)) -> 0 | V76: =IF($J76="","",IF(COUNTIF(lr_key,$J76)=0,"not in tbl_LR",INDEX(calc_cylr_p,MATCH($J76,lr_key,0)))) | W76: =IF(OR($J76="",COUNTIF(lr_key,$J76)=0),"",(INDEX(calc_cylr_p,MATCH($J76,lr_key,0))-INDEX(calc_lrcur,MATCH($J76,lr_key,0)))*100) | X76: =IF(OR($C76="",$J76<>nr_SelKey),"",(SUMPRODUCT(('Rate Engine'!$G$17:$G$64>YEAR($C76)*12+MONTH($C76)-1)*'Rate Engine'!$H$17:$H$64,'Rate Engine'!$Q$17:$Q$64)+(EOMONTH($C76,0)-$C76+1)/DAY(EOMONTH($C76,0))*SUMPRODUCT(('Rate Engine'!$G$17:$G$64=YEAR($C76)*12+MONTH($C76)-1)*'Rate Engine'!$H$17:$H$64,'Rate Engine'!$Q$17:$Q$64))/SUMPRODUCT('Rate Engine'!$H$17:$H$64,'Rate Engine'!$Q$17:$Q$64)) | Y76: =IF($C76="","",IF(AND($E76="taken",$G76<>"",$G76<>1),"achievement ignored — restate Filed %",""))
J77: =IF(OR($A77="",$B77=""),"",$A77&"|"&$B77) | K77: =IF($C77="","",$D77*IF($E77="planned",IF($G77="",1,$G77),1)) | L77: =IF($C77="",0,IF(1+$K77>0,LN(1+$K77),0)) -> 0 | M77: =IF($C77="","",DATE(YEAR($C77),MONTH($C77),1)) | N77: =IF($C77="",0,EOMONTH($C77,0)-$C77+1) -> 0 | O77: =IF($C77="",0,COUNTIFS(rl_key,$J77,rl_effmonth,$M77,rl_eff,"<"&$C77)) -> 0 | P77: =IF($C77="",0,COUNTIFS($J$7:$J77,$J77,$M$7:$M77,$M77,$C$7:$C77,$C77)) -> 0 | Q77: =IF($C77="",0,IF(AND($O77=0,$P77=1),1,0)) -> 0 | R77: =IF($C77="",0,IF(COUNTIFS(rl_key,$J77,rl_effmonth,$M77)>1,1,0)) -> 0 | S77: =IF($C77="",0,COUNTIFS(rl_key,$J77,rl_eff,"<"&$C77)+COUNTIFS($J$7:$J77,$J77,$C$7:$C77,$C77)) -> 0 | T77: =IF(OR($C77="",$E77<>"planned",$C77<DATE(nr_PlanYear,1,1),$C77>DATE(nr_PlanYear,12,31)),0,IF(AND(COUNTIFS(rl_key,$J77,rl_status,"planned",rl_eff,">="&DATE(nr_PlanYear,1,1),rl_eff,"<"&$C77)=0,COUNTIFS($J$7:$J77,$J77,$E$7:$E77,"planned",$C$7:$C77,$C77)=1),1,0)) -> 0 | U77: =IF(OR($C77="",$E77<>"taken"),0,IF(AND(COUNTIFS(rl_key,$J77,rl_effmonth,$M77,rl_eff,"<"&$C77,rl_status,"taken")=0,COUNTIFS($J$7:$J77,$J77,$M$7:$M77,$M77,$C$7:$C77,$C77,$E$7:$E77,"taken")=1),1,0)) -> 0 | V77: =IF($J77="","",IF(COUNTIF(lr_key,$J77)=0,"not in tbl_LR",INDEX(calc_cylr_p,MATCH($J77,lr_key,0)))) | W77: =IF(OR($J77="",COUNTIF(lr_key,$J77)=0),"",(INDEX(calc_cylr_p,MATCH($J77,lr_key,0))-INDEX(calc_lrcur,MATCH($J77,lr_key,0)))*100) | X77: =IF(OR($C77="",$J77<>nr_SelKey),"",(SUMPRODUCT(('Rate Engine'!$G$17:$G$64>YEAR($C77)*12+MONTH($C77)-1)*'Rate Engine'!$H$17:$H$64,'Rate Engine'!$Q$17:$Q$64)+(EOMONTH($C77,0)-$C77+1)/DAY(EOMONTH($C77,0))*SUMPRODUCT(('Rate Engine'!$G$17:$G$64=YEAR($C77)*12+MONTH($C77)-1)*'Rate Engine'!$H$17:$H$64,'Rate Engine'!$Q$17:$Q$64))/SUMPRODUCT('Rate Engine'!$H$17:$H$64,'Rate Engine'!$Q$17:$Q$64)) | Y77: =IF($C77="","",IF(AND($E77="taken",$G77<>"",$G77<>1),"achievement ignored — restate Filed %",""))
